Workbook

Sheet Blad1
A1: Musea - Nederlandse benaming (Title) | B1: Musea - Franse benaming (Alternative Title) | C1: Provincie (location) | D1: Alle Thema's | E1: Geschiedenis en archeologie | F1: Wetenschap en technologie | G1: Mode | H1: Literatuur | I1: Architectuur | J1: Beeldende kunst | K1: Toegepaste kunst en design | M1: Shop | N1: Café | O1: Parking | P1: Restaurant | Q1: Algemene naam --> als geen NL naam dan FR | R1: Prijs | S1: Tijdelijk gesloten | T1: Tijdelijke tentoonstelling(en) | U1: Prijs incl. tijdelijke tentoonstelling | X1: # Museums | Y1: Average Price | Z1: Median
A2: Archeologisch museum van de Boven-Maas | B2: Musée archéologique de la Haute-Meuse | C2: Namen | D2: Geschiedenis en archeologie | E2: =If(IFERROR(SEARCH(E$1, $D2),0) >= 1, true,false) -> TRUE | F2: =If(IFERROR(SEARCH(F$1, $D2),0) >= 1, true,false) -> FALSE | G2: =If(IFERROR(SEARCH(G$1, $D2),0) >= 1, true,false) -> FALSE | H2: =If(IFERROR(SEARCH(H$1, $D2),0) >= 1, true,false) -> FALSE | I2: =If(IFERROR(SEARCH(I$1, $D2),0) >= 1, true,false) -> FALSE | J2: =If(IFERROR(SEARCH(J$1, $D2),0) >= 1, true,false) -> FALSE | K2: =If(IFERROR(SEARCH(K$1, $D2),0) >= 1, true,false) -> FALSE | M2: TRUE | N2: FALSE | O2: TRUE | P2: FALSE | Q2: =IF(ISBLANK(A2),B2,A2) -> Archeologisch museum van de Boven-Maas | R2: 3.5 | S2: FALSE | T2: FALSE | W2: Namen | X2: =COUNTIF(C:C, "Namen") -> 15 | Y2: =AVERAGEIF(C:C, "Namen",R:R) -> 5.9666667 | Z2: =MEDIAN(R2:R16) -> 6
A3: Citadel van Namen / Bezoekerscentrum Terra Nova en toeristentreintje | B3: =IFERROR(__xludf.DUMMYFUNCTION("SPLIT(A3, "" - "", FALSE,FALSE)"),"Citadel van Namen / Bezoekerscentrum Terra Nova en toeristentreintje") -> Citadel van Namen / Bezoekerscentrum Terra Nova en toeristentreintje | C3: Namen | D3: Geschiedenis en archeologie | E3: =If(IFERROR(SEARCH(E$1, $D3),0) >= 1, true,false) -> TRUE | F3: =If(IFERROR(SEARCH(F$1, $D3),0) >= 1, true,false) -> FALSE | G3: =If(IFERROR(SEARCH(G$1, $D3),0) >= 1, true,false) -> FALSE | H3: =If(IFERROR(SEARCH(H$1, $D3),0) >= 1, true,false) -> FALSE | I3: =If(IFERROR(SEARCH(I$1, $D3),0) >= 1, true,false) -> FALSE | J3: =If(IFERROR(SEARCH(J$1, $D3),0) >= 1, true,false) -> FALSE | K3: =If(IFERROR(SEARCH(K$1, $D3),0) >= 1, true,false) -> FALSE | M3: TRUE | N3: TRUE | O3: FALSE | P3: FALSE | Q3: =IF(ISBLANK(A3),B3,A3) -> Citadel van Namen / Bezoekerscentrum Terra Nova en toeristentreintje | R3: 6 | S3: FALSE | T3: FALSE | W3: West-Vlaanderen | X3: =COUNTIF(C:C, "West-Vlaanderen") -> 41 | Y3: =AVERAGEIF(C:C, "West-Vlaanderen",R:R) -> 9.1463415 | Z3: =MEDIAN(R17:R57) -> 9
A4: NAM-IP Computermuseum | B4: Computer Museum NAM-IP | C4: Namen | D4: Wetenschap en technologie | E4: =If(IFERROR(SEARCH(E$1, $D4),0) >= 1, true,false) -> FALSE | F4: =If(IFERROR(SEARCH(F$1, $D4),0) >= 1, true,false) -> TRUE | G4: =If(IFERROR(SEARCH(G$1, $D4),0) >= 1, true,false) -> FALSE | H4: =If(IFERROR(SEARCH(H$1, $D4),0) >= 1, true,false) -> FALSE | I4: =If(IFERROR(SEARCH(I$1, $D4),0) >= 1, true,false) -> FALSE | J4: =If(IFERROR(SEARCH(J$1, $D4),0) >= 1, true,false) -> FALSE | K4: =If(IFERROR(SEARCH(K$1, $D4),0) >= 1, true,false) -> FALSE | M4: TRUE | N4: TRUE | O4: TRUE | P4: FALSE | Q4: =IF(ISBLANK(A4),B4,A4) -> NAM-IP Computermuseum | R4: 8 | S4: FALSE | T4: FALSE | W4: Antwerpen | X4: 35 | Y4: =AVERAGE($R$58:$R$91) -> 9.25 | Z4: =MEDIAN($R$58:$R$91) -> 10
A5: Ecomuseum van de Viroin | B5: Écomusée du Viroin | C5: Namen | D5: Geschiedenis en archeologie | E5: =If(IFERROR(SEARCH(E$1, $D5),0) >= 1, true,false) -> TRUE | F5: =If(IFERROR(SEARCH(F$1, $D5),0) >= 1, true,false) -> FALSE | G5: =If(IFERROR(SEARCH(G$1, $D5),0) >= 1, true,false) -> FALSE | H5: =If(IFERROR(SEARCH(H$1, $D5),0) >= 1, true,false) -> FALSE | I5: =If(IFERROR(SEARCH(I$1, $D5),0) >= 1, true,false) -> FALSE | J5: =If(IFERROR(SEARCH(J$1, $D5),0) >= 1, true,false) -> FALSE | K5: =If(IFERROR(SEARCH(K$1, $D5),0) >= 1, true,false) -> FALSE | M5: TRUE | N5: FALSE | O5: FALSE | P5: FALSE | Q5: =IF(ISBLANK(A5),B5,A5) -> Ecomuseum van de Viroin | R5: 4 | S5: FALSE | T5: TRUE | U5: 4 | W5: Waals-Brabant | X5: 5 | Y5: =AVERAGE($R$93:$R$97) -> 8.8 | Z5: =MEDIAN($R$93:$R$97) -> 10
A6: Andenne Museum | B6: Espace Muséal d’Andenne | C6: Namen | D6: Toegepaste kunst en design, Geschiedenis en archeologie | E6: =If(IFERROR(SEARCH(E$1, $D6),0) >= 1, true,false) -> TRUE | F6: =If(IFERROR(SEARCH(F$1, $D6),0) >= 1, true,false) -> FALSE | G6: =If(IFERROR(SEARCH(G$1, $D6),0) >= 1, true,false) -> FALSE | H6: =If(IFERROR(SEARCH(H$1, $D6),0) >= 1, true,false) -> FALSE | I6: =If(IFERROR(SEARCH(I$1, $D6),0) >= 1, true,false) -> FALSE | J6: =If(IFERROR(SEARCH(J$1, $D6),0) >= 1, true,false) -> FALSE | K6: =If(IFERROR(SEARCH(K$1, $D6),0) >= 1, true,false) -> TRUE | M6: TRUE | N6: FALSE | O6: FALSE | P6: FALSE | Q6: =IF(ISBLANK(A6),B6,A6) -> Andenne Museum | R6: 10 | S6: FALSE | T6: FALSE | W6: Vlaams-Brabant | X6: 13 | Y6: =AVERAGE($R$98:$R$110) -> 8.1923077 | Z6: =MEDIAN($R$98:$R$110) -> 10
B7: Le Delta | C7: Namen | D7: Beeldende kunst | E7: =If(IFERROR(SEARCH(E$1, $D7),0) >= 1, true,false) -> FALSE | F7: =If(IFERROR(SEARCH(F$1, $D7),0) >= 1, true,false) -> FALSE | G7: =If(IFERROR(SEARCH(G$1, $D7),0) >= 1, true,false) -> FALSE | H7: =If(IFERROR(SEARCH(H$1, $D7),0) >= 1, true,false) -> FALSE | I7: =If(IFERROR(SEARCH(I$1, $D7),0) >= 1, true,false) -> FALSE | J7: =If(IFERROR(SEARCH(J$1, $D7),0) >= 1, true,false) -> TRUE | K7: =If(IFERROR(SEARCH(K$1, $D7),0) >= 1, true,false) -> FALSE | M7: TRUE | N7: FALSE | O7: FALSE | P7: TRUE | Q7: =IF(ISBLANK(A7),B7,A7) -> Le Delta | R7: 5 | S7: FALSE | T7: TRUE | U7: 5 | W7: Limburg | X7: =COUNTIF(C:C, "Limburg") -> 15 | Y7: =AVERAGEIF(C:C, "Limburg",R:R) -> 8.3333333 | Z7: =MEDIAN(R111,R125) -> 9
B8: Le Pavillon | C8: Namen | D8: Beeldende kunst, Wetenschap en technologie | E8: =If(IFERROR(SEARCH(E$1, $D8),0) >= 1, true,false) -> FALSE | F8: =If(IFERROR(SEARCH(F$1, $D8),0) >= 1, true,false) -> TRUE | G8: =If(IFERROR(SEARCH(G$1, $D8),0) >= 1, true,false) -> FALSE | H8: =If(IFERROR(SEARCH(H$1, $D8),0) >= 1, true,false) -> FALSE | I8: =If(IFERROR(SEARCH(I$1, $D8),0) >= 1, true,false) -> FALSE | J8: =If(IFERROR(SEARCH(J$1, $D8),0) >= 1, true,false) -> TRUE | K8: =If(IFERROR(SEARCH(K$1, $D8),0) >= 1, true,false) -> FALSE | M8: TRUE | N8: FALSE | O8: FALSE | P8: FALSE | Q8: =IF(ISBLANK(A8),B8,A8) -> Le Pavillon | R8: 10 | S8: FALSE | T8: TRUE | U8: 10 | W8: Luik | X8: =COUNTIF(C:C, "Luik") -> 19 | Y8: =AVERAGEIF(C:C, "Luik",R:R) -> 6.6315789 | Z8: =MEDIAN(R126,R144) -> 10.5
B9: Maison du patrimoine médiéval mosan | C9: Namen | D9: Geschiedenis en archeologie | E9: =If(IFERROR(SEARCH(E$1, $D9),0) >= 1, true,false) -> TRUE | F9: =If(IFERROR(SEARCH(F$1, $D9),0) >= 1, true,false) -> FALSE | G9: =If(IFERROR(SEARCH(G$1, $D9),0) >= 1, true,false) -> FALSE | H9: =If(IFERROR(SEARCH(H$1, $D9),0) >= 1, true,false) -> FALSE | I9: =If(IFERROR(SEARCH(I$1, $D9),0) >= 1, true,false) -> FALSE | J9: =If(IFERROR(SEARCH(J$1, $D9),0) >= 1, true,false) -> FALSE | K9: =If(IFERROR(SEARCH(K$1, $D9),0) >= 1, true,false) -> FALSE | M9: TRUE | N9: FALSE | O9: TRUE | P9: FALSE | Q9: =IF(ISBLANK(A9),B9,A9) -> Maison du patrimoine médiéval mosan | R9: 6 | S9: FALSE | T9: TRUE | U9: 6 | W9: Henegouwen | X9: =COUNTIF(C:C,"Henegouwen") -> 37 | Y9: =AVERAGEIF(C:C,"Henegouwen",R:R) -> 6.5405405 | Z9: =MEDIAN(R145:R181) -> 6
A10: Archeopark van Rochefort | B10: Malagne | Archéoparc de Rochefort | C10: Namen | D10: Geschiedenis en archeologie | E10: =If(IFERROR(SEARCH(E$1, $D10),0) >= 1, true,false) -> TRUE | F10: =If(IFERROR(SEARCH(F$1, $D10),0) >= 1, true,false) -> FALSE | G10: =If(IFERROR(SEARCH(G$1, $D10),0) >= 1, true,false) -> FALSE | H10: =If(IFERROR(SEARCH(H$1, $D10),0) >= 1, true,false) -> FALSE | I10: =If(IFERROR(SEARCH(I$1, $D10),0) >= 1, true,false) -> FALSE | J10: =If(IFERROR(SEARCH(J$1, $D10),0) >= 1, true,false) -> FALSE | K10: =If(IFERROR(SEARCH(K$1, $D10),0) >= 1, true,false) -> FALSE | M10: TRUE | N10: TRUE | O10: TRUE | P10: FALSE | Q10: =IF(ISBLANK(A10),B10,A10) -> Archeopark van Rochefort | R10: 8 | S10: FALSE | T10: FALSE | W10: Luxemburg | X10: =COUNTIF(C:C,"Luxemburg") -> 9 | Y10: =AVERAGEIF(C:C,"Luxemburg",R:R) -> 7.0555556 | Z10: =MEDIAN(R182,R190) -> 10.5
A11: MusAfrica Namen | B11: MusAfrica Namur | C11: Namen | D11: Toegepaste kunst en design, Geschiedenis en archeologie | E11: =If(IFERROR(SEARCH(E$1, $D11),0) >= 1, true,false) -> TRUE | F11: =If(IFERROR(SEARCH(F$1, $D11),0) >= 1, true,false) -> FALSE | G11: =If(IFERROR(SEARCH(G$1, $D11),0) >= 1, true,false) -> FALSE | H11: =If(IFERROR(SEARCH(H$1, $D11),0) >= 1, true,false) -> FALSE | I11: =If(IFERROR(SEARCH(I$1, $D11),0) >= 1, true,false) -> FALSE | J11: =If(IFERROR(SEARCH(J$1, $D11),0) >= 1, true,false) -> FALSE | K11: =If(IFERROR(SEARCH(K$1, $D11),0) >= 1, true,false) -> TRUE | M11: TRUE | N11: FALSE | O11: FALSE | P11: FALSE | Q11: =IF(ISBLANK(A11),B11,A11) -> MusAfrica Namen | R11: 8 | S11: FALSE | T11: FALSE | W11: Brussel | X11: =countif(C2:C261,"Brussel") -> 48 | Y11: =AVERAGE(R191:R238) -> 9.1875 | Z11: =MEDIAN(R191:R238) -> 10
A12: Aardbeimuseum | B12: Musée de la Fraise | C12: Namen | D12: Beeldende kunst, Geschiedenis en archeologie, Wetenschap en technologie | E12: =If(IFERROR(SEARCH(E$1, $D12),0) >= 1, true,false) -> TRUE | F12: =If(IFERROR(SEARCH(F$1, $D12),0) >= 1, true,false) -> TRUE | G12: =If(IFERROR(SEARCH(G$1, $D12),0) >= 1, true,false) -> FALSE | H12: =If(IFERROR(SEARCH(H$1, $D12),0) >= 1, true,false) -> FALSE | I12: =If(IFERROR(SEARCH(I$1, $D12),0) >= 1, true,false) -> FALSE | J12: =If(IFERROR(SEARCH(J$1, $D12),0) >= 1, true,false) -> TRUE | K12: =If(IFERROR(SEARCH(K$1, $D12),0) >= 1, true,false) -> FALSE | M12: TRUE | N12: FALSE | O12: FALSE | P12: FALSE | Q12: =IF(ISBLANK(A12),B12,A12) -> Aardbeimuseum | R12: 6 | S12: FALSE | T12: FALSE | W12: Oost-Vlaanderen | X12: =countif(C2:C261,"Oost-Vlaanderen") -> 23 | Y12: =AVERAGE(R239:R261) -> 8.5652174 | Z12: =MEDIAN(R239:R261) -> 9
B13: Musée du Malgré-Tout | C13: Namen | D13: Geschiedenis en archeologie | E13: =If(IFERROR(SEARCH(E$1, $D13),0) >= 1, true,false) -> TRUE | F13: =If(IFERROR(SEARCH(F$1, $D13),0) >= 1, true,false) -> FALSE | G13: =If(IFERROR(SEARCH(G$1, $D13),0) >= 1, true,false) -> FALSE | H13: =If(IFERROR(SEARCH(H$1, $D13),0) >= 1, true,false) -> FALSE | I13: =If(IFERROR(SEARCH(I$1, $D13),0) >= 1, true,false) -> FALSE | J13: =If(IFERROR(SEARCH(J$1, $D13),0) >= 1, true,false) -> FALSE | K13: =If(IFERROR(SEARCH(K$1, $D13),0) >= 1, true,false) -> FALSE | M13: TRUE | N13: FALSE | O13: FALSE | P13: FALSE | Q13: =IF(ISBLANK(A13),B13,A13) -> Musée du Malgré-Tout | R13: 5 | S13: FALSE | T13: FALSE
A14: Museum van het Klein Formaat | B14: Musée du Petit Format | C14: Namen | D14: Beeldende kunst | E14: =If(IFERROR(SEARCH(E$1, $D14),0) >= 1, true,false) -> FALSE | F14: =If(IFERROR(SEARCH(F$1, $D14),0) >= 1, true,false) -> FALSE | G14: =If(IFERROR(SEARCH(G$1, $D14),0) >= 1, true,false) -> FALSE | H14: =If(IFERROR(SEARCH(H$1, $D14),0) >= 1, true,false) -> FALSE | I14: =If(IFERROR(SEARCH(I$1, $D14),0) >= 1, true,false) -> FALSE | J14: =If(IFERROR(SEARCH(J$1, $D14),0) >= 1, true,false) -> TRUE | K14: =If(IFERROR(SEARCH(K$1, $D14),0) >= 1, true,false) -> FALSE | M14: TRUE | N14: FALSE | O14: FALSE | P14: FALSE | Q14: =IF(ISBLANK(A14),B14,A14) -> Museum van het Klein Formaat | R14: 5 | S14: FALSE | T14: TRUE | U14: 5
A15: Félicien Rops Museum | B15: Musée Félicien Rops | C15: Namen | D15: Beeldende kunst | E15: =If(IFERROR(SEARCH(E$1, $D15),0) >= 1, true,false) -> FALSE | F15: =If(IFERROR(SEARCH(F$1, $D15),0) >= 1, true,false) -> FALSE | G15: =If(IFERROR(SEARCH(G$1, $D15),0) >= 1, true,false) -> FALSE | H15: =If(IFERROR(SEARCH(H$1, $D15),0) >= 1, true,false) -> FALSE | I15: =If(IFERROR(SEARCH(I$1, $D15),0) >= 1, true,false) -> FALSE | J15: =If(IFERROR(SEARCH(J$1, $D15),0) >= 1, true,false) -> TRUE | K15: =If(IFERROR(SEARCH(K$1, $D15),0) >= 1, true,false) -> FALSE | M15: TRUE | N15: FALSE | O15: FALSE | P15: FALSE | Q15: =IF(ISBLANK(A15),B15,A15) -> Félicien Rops Museum | R15: 0 | S15: FALSE | T15: TRUE | U15: 8
A16: Museum voor Oude Kunsten | B16: TreM.a | Musée des Arts anciens | C16: Namen | D16: Beeldende kunst | E16: =If(IFERROR(SEARCH(E$1, $D16),0) >= 1, true,false) -> FALSE | F16: =If(IFERROR(SEARCH(F$1, $D16),0) >= 1, true,false) -> FALSE | G16: =If(IFERROR(SEARCH(G$1, $D16),0) >= 1, true,false) -> FALSE | H16: =If(IFERROR(SEARCH(H$1, $D16),0) >= 1, true,false) -> FALSE | I16: =If(IFERROR(SEARCH(I$1, $D16),0) >= 1, true,false) -> FALSE | J16: =If(IFERROR(SEARCH(J$1, $D16),0) >= 1, true,false) -> TRUE | K16: =If(IFERROR(SEARCH(K$1, $D16),0) >= 1, true,false) -> FALSE | M16: TRUE | N16: FALSE | O16: FALSE | P16: FALSE | Q16: =IF(ISBLANK(A16),B16,A16) -> Museum voor Oude Kunsten | R16: 5 | S16: FALSE | T16: TRUE | U16: 8
A17: Abdijmuseum Ten Duinen | B17: Musée de l’Abbaye des Dunes | C17: West-Vlaanderen | D17: Geschiedenis en archeologie, Wetenschap en technologie, Architectuur | E17: =If(IFERROR(SEARCH(E$1, $D17),0) >= 1, true,false) -> TRUE | F17: =If(IFERROR(SEARCH(F$1, $D17),0) >= 1, true,false) -> TRUE | G17: =If(IFERROR(SEARCH(G$1, $D17),0) >= 1, true,false) -> FALSE | H17: =If(IFERROR(SEARCH(H$1, $D17),0) >= 1, true,false) -> FALSE | I17: =If(IFERROR(SEARCH(I$1, $D17),0) >= 1, true,false) -> TRUE | J17: =If(IFERROR(SEARCH(J$1, $D17),0) >= 1, true,false) -> FALSE | K17: =If(IFERROR(SEARCH(K$1, $D17),0) >= 1, true,false) -> FALSE | M17: TRUE | N17: FALSE | O17: TRUE | P17: FALSE | Q17: =IF(ISBLANK(A17),B17,A17) -> Abdijmuseum Ten Duinen | R17: 10 | S17: FALSE | T17: TRUE | U17: 10
A18: Adornesdomein | B18: Le domaine Adornes | C18: West-Vlaanderen | D18: Beeldende kunst, Toegepaste kunst en design, Geschiedenis en archeologie, Architectuur | E18: =If(IFERROR(SEARCH(E$1, $D18),0) >= 1, true,false) -> TRUE | F18: =If(IFERROR(SEARCH(F$1, $D18),0) >= 1, true,false) -> FALSE | G18: =If(IFERROR(SEARCH(G$1, $D18),0) >= 1, true,false) -> FALSE | H18: =If(IFERROR(SEARCH(H$1, $D18),0) >= 1, true,false) -> FALSE | I18: =If(IFERROR(SEARCH(I$1, $D18),0) >= 1, true,false) -> TRUE | J18: =If(IFERROR(SEARCH(J$1, $D18),0) >= 1, true,false) -> TRUE | K18: =If(IFERROR(SEARCH(K$1, $D18),0) >= 1, true,false) -> TRUE | M18: TRUE | N18: TRUE | O18: FALSE | P18: FALSE | Q18: =IF(ISBLANK(A18),B18,A18) -> Adornesdomein | R18: 10 | S18: FALSE | T18: FALSE
A19: Atlantikwall Raversyde | C19: West-Vlaanderen | D19: Beeldende kunst, Toegepaste kunst en design, Geschiedenis en archeologie, Wetenschap en technologie, Architectuur | E19: =If(IFERROR(SEARCH(E$1, $D19),0) >= 1, true,false) -> TRUE | F19: =If(IFERROR(SEARCH(F$1, $D19),0) >= 1, true,false) -> TRUE | G19: =If(IFERROR(SEARCH(G$1, $D19),0) >= 1, true,false) -> FALSE | H19: =If(IFERROR(SEARCH(H$1, $D19),0) >= 1, true,false) -> FALSE | I19: =If(IFERROR(SEARCH(I$1, $D19),0) >= 1, true,false) -> TRUE | J19: =If(IFERROR(SEARCH(J$1, $D19),0) >= 1, true,false) -> TRUE | K19: =If(IFERROR(SEARCH(K$1, $D19),0) >= 1, true,false) -> TRUE | M19: TRUE | N19: TRUE | O19: TRUE | P19: TRUE | Q19: =IF(ISBLANK(A19),B19,A19) -> Atlantikwall Raversyde | R19: 10 | S19: FALSE | T19: TRUE | U19: 10
A20: Bakkerijmuseum | B20: Musée de la Boulangerie | C20: West-Vlaanderen | D20: Geschiedenis en archeologie | E20: =If(IFERROR(SEARCH(E$1, $D20),0) >= 1, true,false) -> TRUE | F20: =If(IFERROR(SEARCH(F$1, $D20),0) >= 1, true,false) -> FALSE | G20: =If(IFERROR(SEARCH(G$1, $D20),0) >= 1, true,false) -> FALSE | H20: =If(IFERROR(SEARCH(H$1, $D20),0) >= 1, true,false) -> FALSE | I20: =If(IFERROR(SEARCH(I$1, $D20),0) >= 1, true,false) -> FALSE | J20: =If(IFERROR(SEARCH(J$1, $D20),0) >= 1, true,false) -> FALSE | K20: =If(IFERROR(SEARCH(K$1, $D20),0) >= 1, true,false) -> FALSE | M20: TRUE | N20: TRUE | O20: TRUE | P20: TRUE | Q20: =IF(ISBLANK(A20),B20,A20) -> Bakkerijmuseum | R20: 8 | S20: FALSE | T20: FALSE
A21: Belfort van Brugge | B21: Beffroi de Bruges | C21: West-Vlaanderen | D21: Geschiedenis en archeologie, Wetenschap en technologie, Architectuur | E21: =If(IFERROR(SEARCH(E$1, $D21),0) >= 1, true,false) -> TRUE | F21: =If(IFERROR(SEARCH(F$1, $D21),0) >= 1, true,false) -> TRUE | G21: =If(IFERROR(SEARCH(G$1, $D21),0) >= 1, true,false) -> FALSE | H21: =If(IFERROR(SEARCH(H$1, $D21),0) >= 1, true,false) -> FALSE | I21: =If(IFERROR(SEARCH(I$1, $D21),0) >= 1, true,false) -> TRUE | J21: =If(IFERROR(SEARCH(J$1, $D21),0) >= 1, true,false) -> FALSE | K21: =If(IFERROR(SEARCH(K$1, $D21),0) >= 1, true,false) -> FALSE | M21: FALSE | N21: FALSE | O21: FALSE | P21: FALSE | Q21: =IF(ISBLANK(A21),B21,A21) -> Belfort van Brugge | R21: 15 | S21: FALSE | T21: FALSE
A22: Belle Epoque Centrum | B22: Centre Belle Epoque | C22: West-Vlaanderen | D22: Geschiedenis en archeologie | E22: =If(IFERROR(SEARCH(E$1, $D22),0) >= 1, true,false) -> TRUE | F22: =If(IFERROR(SEARCH(F$1, $D22),0) >= 1, true,false) -> FALSE | G22: =If(IFERROR(SEARCH(G$1, $D22),0) >= 1, true,false) -> FALSE | H22: =If(IFERROR(SEARCH(H$1, $D22),0) >= 1, true,false) -> FALSE | I22: =If(IFERROR(SEARCH(I$1, $D22),0) >= 1, true,false) -> FALSE | J22: =If(IFERROR(SEARCH(J$1, $D22),0) >= 1, true,false) -> FALSE | K22: =If(IFERROR(SEARCH(K$1, $D22),0) >= 1, true,false) -> FALSE | M22: TRUE | N22: FALSE | O22: FALSE | P22: FALSE | Q22: =IF(ISBLANK(A22),B22,A22) -> Belle Epoque Centrum | R22: 5 | S22: FALSE | T22: FALSE
A23: Brugse Vrije | B23: Franc de Bruges | C23: West-Vlaanderen | D23: Beeldende kunst, Toegepaste kunst en design, Geschiedenis en archeologie | E23: =If(IFERROR(SEARCH(E$1, $D23),0) >= 1, true,false) -> TRUE | F23: =If(IFERROR(SEARCH(F$1, $D23),0) >= 1, true,false) -> FALSE | G23: =If(IFERROR(SEARCH(G$1, $D23),0) >= 1, true,false) -> FALSE | H23: =If(IFERROR(SEARCH(H$1, $D23),0) >= 1, true,false) -> FALSE | I23: =If(IFERROR(SEARCH(I$1, $D23),0) >= 1, true,false) -> FALSE | J23: =If(IFERROR(SEARCH(J$1, $D23),0) >= 1, true,false) -> TRUE | K23: =If(IFERROR(SEARCH(K$1, $D23),0) >= 1, true,false) -> TRUE | M23: FALSE | N23: FALSE | O23: FALSE | P23: FALSE | Q23: =IF(ISBLANK(A23),B23,A23) -> Brugse Vrije | R23: 3 | S23: FALSE | T23: FALSE
A24: Dodengang | B24: Boyau de la Mort | C24: West-Vlaanderen | D24: Geschiedenis en archeologie | E24: =If(IFERROR(SEARCH(E$1, $D24),0) >= 1, true,false) -> TRUE | F24: =If(IFERROR(SEARCH(F$1, $D24),0) >= 1, true,false) -> FALSE | G24: =If(IFERROR(SEARCH(G$1, $D24),0) >= 1, true,false) -> FALSE | H24: =If(IFERROR(SEARCH(H$1, $D24),0) >= 1, true,false) -> FALSE | I24: =If(IFERROR(SEARCH(I$1, $D24),0) >= 1, true,false) -> FALSE | J24: =If(IFERROR(SEARCH(J$1, $D24),0) >= 1, true,false) -> FALSE | K24: =If(IFERROR(SEARCH(K$1, $D24),0) >= 1, true,false) -> FALSE | M24: FALSE | N24: FALSE | O24: TRUE | P24: FALSE | Q24: =IF(ISBLANK(A24),B24,A24) -> Dodengang | R24: 6 | S24: FALSE | T24: FALSE
B25: Eperon d’Or | C25: West-Vlaanderen | D25: Geschiedenis en archeologie, Wetenschap en technologie, Architectuur, Mode | E25: =If(IFERROR(SEARCH(E$1, $D25),0) >= 1, true,false) -> TRUE | F25: =If(IFERROR(SEARCH(F$1, $D25),0) >= 1, true,false) -> TRUE | G25: =If(IFERROR(SEARCH(G$1, $D25),0) >= 1, true,false) -> TRUE | H25: =If(IFERROR(SEARCH(H$1, $D25),0) >= 1, true,false) -> FALSE | I25: =If(IFERROR(SEARCH(I$1, $D25),0) >= 1, true,false) -> TRUE | J25: =If(IFERROR(SEARCH(J$1, $D25),0) >= 1, true,false) -> FALSE | K25: =If(IFERROR(SEARCH(K$1, $D25),0) >= 1, true,false) -> FALSE | M25: TRUE | N25: FALSE | O25: TRUE | P25: FALSE | Q25: =IF(ISBLANK(A25),B25,A25) -> Eperon d’Or | R25: 8 | S25: FALSE | T25: TRUE | U25: 8
A26: Gezellehuis | B26: Maison Gezelle | C26: West-Vlaanderen | D26: Literatuur | E26: =If(IFERROR(SEARCH(E$1, $D26),0) >= 1, true,false) -> FALSE | F26: =If(IFERROR(SEARCH(F$1, $D26),0) >= 1, true,false) -> FALSE | G26: =If(IFERROR(SEARCH(G$1, $D26),0) >= 1, true,false) -> FALSE | H26: =If(IFERROR(SEARCH(H$1, $D26),0) >= 1, true,false) -> TRUE | I26: =If(IFERROR(SEARCH(I$1, $D26),0) >= 1, true,false) -> FALSE | J26: =If(IFERROR(SEARCH(J$1, $D26),0) >= 1, true,false) -> FALSE | K26: =If(IFERROR(SEARCH(K$1, $D26),0) >= 1, true,false) -> FALSE | M26: FALSE | N26: FALSE | O26: FALSE | P26: FALSE | Q26: =IF(ISBLANK(A26),B26,A26) -> Gezellehuis | R26: 0 | S26: FALSE | T26: FALSE
A27: Groeningemuseum | B27: Musée Groeninge | C27: West-Vlaanderen | D27: Beeldende kunst | E27: =If(IFERROR(SEARCH(E$1, $D27),0) >= 1, true,false) -> FALSE | F27: =If(IFERROR(SEARCH(F$1, $D27),0) >= 1, true,false) -> FALSE | G27: =If(IFERROR(SEARCH(G$1, $D27),0) >= 1, true,false) -> FALSE | H27: =If(IFERROR(SEARCH(H$1, $D27),0) >= 1, true,false) -> FALSE | I27: =If(IFERROR(SEARCH(I$1, $D27),0) >= 1, true,false) -> FALSE | J27: =If(IFERROR(SEARCH(J$1, $D27),0) >= 1, true,false) -> TRUE | K27: =If(IFERROR(SEARCH(K$1, $D27),0) >= 1, true,false) -> FALSE | M27: TRUE | N27: FALSE | O27: FALSE | P27: FALSE | Q27: =IF(ISBLANK(A27),B27,A27) -> Groeningemuseum | R27: 15 | S27: FALSE | T27: FALSE
A28: Gruuthusemuseum | B28: Musée Gruuthuse | C28: West-Vlaanderen | D28: Beeldende kunst, Toegepaste kunst en design, Geschiedenis en archeologie, Architectuur | E28: =If(IFERROR(SEARCH(E$1, $D28),0) >= 1, true,false) -> TRUE | F28: =If(IFERROR(SEARCH(F$1, $D28),0) >= 1, true,false) -> FALSE | G28: =If(IFERROR(SEARCH(G$1, $D28),0) >= 1, true,false) -> FALSE | H28: =If(IFERROR(SEARCH(H$1, $D28),0) >= 1, true,false) -> FALSE | I28: =If(IFERROR(SEARCH(I$1, $D28),0) >= 1, true,false) -> TRUE | J28: =If(IFERROR(SEARCH(J$1, $D28),0) >= 1, true,false) -> TRUE | K28: =If(IFERROR(SEARCH(K$1, $D28),0) >= 1, true,false) -> TRUE | M28: FALSE | N28: FALSE | O28: FALSE | P28: FALSE | Q28: =IF(ISBLANK(A28),B28,A28) -> Gruuthusemuseum | R28: 15 | S28: FALSE | T28: FALSE
A29: Het James Ensorhuis | B29: La Maison de James Ensor | C29: West-Vlaanderen | D29: Beeldende kunst | E29: =If(IFERROR(SEARCH(E$1, $D29),0) >= 1, true,false) -> FALSE | F29: =If(IFERROR(SEARCH(F$1, $D29),0) >= 1, true,false) -> FALSE | G29: =If(IFERROR(SEARCH(G$1, $D29),0) >= 1, true,false) -> FALSE | H29: =If(IFERROR(SEARCH(H$1, $D29),0) >= 1, true,false) -> FALSE | I29: =If(IFERROR(SEARCH(I$1, $D29),0) >= 1, true,false) -> FALSE | J29: =If(IFERROR(SEARCH(J$1, $D29),0) >= 1, true,false) -> TRUE | K29: =If(IFERROR(SEARCH(K$1, $D29),0) >= 1, true,false) -> FALSE | M29: TRUE | N29: FALSE | O29: FALSE | P29: FALSE | Q29: =IF(ISBLANK(A29),B29,A29) -> Het James Ensorhuis | R29: 13 | S29: FALSE | T29: TRUE | U29: 13
A30: Het Lijsternest | Streuvelshuis & Schrijversresidentie | C30: West-Vlaanderen | D30: Beeldende kunst, Architectuur, Literatuur | E30: =If(IFERROR(SEARCH(E$1, $D30),0) >= 1, true,false) -> FALSE | F30: =If(IFERROR(SEARCH(F$1, $D30),0) >= 1, true,false) -> FALSE | G30: =If(IFERROR(SEARCH(G$1, $D30),0) >= 1, true,false) -> FALSE | H30: =If(IFERROR(SEARCH(H$1, $D30),0) >= 1, true,false) -> TRUE | I30: =If(IFERROR(SEARCH(I$1, $D30),0) >= 1, true,false) -> TRUE | J30: =If(IFERROR(SEARCH(J$1, $D30),0) >= 1, true,false) -> TRUE | K30: =If(IFERROR(SEARCH(K$1, $D30),0) >= 1, true,false) -> FALSE | M30: TRUE | N30: FALSE | O30: TRUE | P30: FALSE | Q30: =IF(ISBLANK(A30),B30,A30) -> Het Lijsternest | Streuvelshuis & Schrijversresidentie | R30: 3 | S30: TRUE | T30: FALSE
A31: HEY Museum | C31: West-Vlaanderen | D31: Beeldende kunst, Geschiedenis en archeologie | E31: =If(IFERROR(SEARCH(E$1, $D31),0) >= 1, true,false) -> TRUE | F31: =If(IFERROR(SEARCH(F$1, $D31),0) >= 1, true,false) -> FALSE | G31: =If(IFERROR(SEARCH(G$1, $D31),0) >= 1, true,false) -> FALSE | H31: =If(IFERROR(SEARCH(H$1, $D31),0) >= 1, true,false) -> FALSE | I31: =If(IFERROR(SEARCH(I$1, $D31),0) >= 1, true,false) -> FALSE | J31: =If(IFERROR(SEARCH(J$1, $D31),0) >= 1, true,false) -> TRUE | K31: =If(IFERROR(SEARCH(K$1, $D31),0) >= 1, true,false) -> FALSE | M31: TRUE | N31: FALSE | O31: FALSE | P31: FALSE | Q31: =IF(ISBLANK(A31),B31,A31) -> HEY Museum | R31: 10 | S31: FALSE | T31: FALSE
A32: Hopmuseum Poperinge | B32: Musée du Houblon Poperinge | C32: West-Vlaanderen | D32: Geschiedenis en archeologie | E32: =If(IFERROR(SEARCH(E$1, $D32),0) >= 1, true,false) -> TRUE | F32: =If(IFERROR(SEARCH(F$1, $D32),0) >= 1, true,false) -> FALSE | G32: =If(IFERROR(SEARCH(G$1, $D32),0) >= 1, true,false) -> FALSE | H32: =If(IFERROR(SEARCH(H$1, $D32),0) >= 1, true,false) -> FALSE | I32: =If(IFERROR(SEARCH(I$1, $D32),0) >= 1, true,false) -> FALSE | J32: =If(IFERROR(SEARCH(J$1, $D32),0) >= 1, true,false) -> FALSE | K32: =If(IFERROR(SEARCH(K$1, $D32),0) >= 1, true,false) -> FALSE | M32: TRUE | N32: TRUE | O32: FALSE | P32: FALSE | Q32: =IF(ISBLANK(A32),B32,A32) -> Hopmuseum Poperinge | R32: 7 | S32: FALSE | T32: FALSE
A33: In Flanders Fields Museum | B33: Musée In Flanders Fields | C33: West-Vlaanderen | D33: Geschiedenis en archeologie | E33: =If(IFERROR(SEARCH(E$1, $D33),0) >= 1, true,false) -> TRUE | F33: =If(IFERROR(SEARCH(F$1, $D33),0) >= 1, true,false) -> FALSE | G33: =If(IFERROR(SEARCH(G$1, $D33),0) >= 1, true,false) -> FALSE | H33: =If(IFERROR(SEARCH(H$1, $D33),0) >= 1, true,false) -> FALSE | I33: =If(IFERROR(SEARCH(I$1, $D33),0) >= 1, true,false) -> FALSE | J33: =If(IFERROR(SEARCH(J$1, $D33),0) >= 1, true,false) -> FALSE | K33: =If(IFERROR(SEARCH(K$1, $D33),0) >= 1, true,false) -> FALSE | M33: TRUE | N33: TRUE | O33: FALSE | P33: FALSE | Q33: =IF(ISBLANK(A33),B33,A33) -> In Flanders Fields Museum | R33: 12 | S33: FALSE | T33: TRUE | U33: 12
A34: Kantmuseum Brugge | B34: Musée de la Dentelle Bruges | C34: West-Vlaanderen | D34: Toegepaste kunst en design, Geschiedenis en archeologie, Mode | E34: =If(IFERROR(SEARCH(E$1, $D34),0) >= 1, true,false) -> TRUE | F34: =If(IFERROR(SEARCH(F$1, $D34),0) >= 1, true,false) -> FALSE | G34: =If(IFERROR(SEARCH(G$1, $D34),0) >= 1, true,false) -> TRUE | H34: =If(IFERROR(SEARCH(H$1, $D34),0) >= 1, true,false) -> FALSE | I34: =If(IFERROR(SEARCH(I$1, $D34),0) >= 1, true,false) -> FALSE | J34: =If(IFERROR(SEARCH(J$1, $D34),0) >= 1, true,false) -> FALSE | K34: =If(IFERROR(SEARCH(K$1, $D34),0) >= 1, true,false) -> TRUE | M34: TRUE | N34: FALSE | O34: FALSE | P34: FALSE | Q34: =IF(ISBLANK(A34),B34,A34) -> Kantmuseum Brugge | R34: 8 | S34: FALSE | T34: FALSE
A35: Kasteel van Loppem | B35: Château de Loppem | C35: West-Vlaanderen | D35: Beeldende kunst, Geschiedenis en archeologie | E35: =If(IFERROR(SEARCH(E$1, $D35),0) >= 1, true,false) -> TRUE | F35: =If(IFERROR(SEARCH(F$1, $D35),0) >= 1, true,false) -> FALSE | G35: =If(IFERROR(SEARCH(G$1, $D35),0) >= 1, true,false) -> FALSE | H35: =If(IFERROR(SEARCH(H$1, $D35),0) >= 1, true,false) -> FALSE | I35: =If(IFERROR(SEARCH(I$1, $D35),0) >= 1, true,false) -> FALSE | J35: =If(IFERROR(SEARCH(J$1, $D35),0) >= 1, true,false) -> TRUE | K35: =If(IFERROR(SEARCH(K$1, $D35),0) >= 1, true,false) -> FALSE | M35: TRUE | N35: FALSE | O35: TRUE | P35: FALSE | Q35: =IF(ISBLANK(A35),B35,A35) -> Kasteel van Loppem | R35: 9 | S35: FALSE | T35: FALSE
A36: KOERS | Museum van de Wielersport | B36: Musée de la Course Cycliste | C36: West-Vlaanderen | D36: Geschiedenis en archeologie, Wetenschap en technologie | E36: =If(IFERROR(SEARCH(E$1, $D36),0) >= 1, true,false) -> TRUE | F36: =If(IFERROR(SEARCH(F$1, $D36),0) >= 1, true,false) -> TRUE | G36: =If(IFERROR(SEARCH(G$1, $D36),0) >= 1, true,false) -> FALSE | H36: =If(IFERROR(SEARCH(H$1, $D36),0) >= 1, true,false) -> FALSE | I36: =If(IFERROR(SEARCH(I$1, $D36),0) >= 1, true,false) -> FALSE | J36: =If(IFERROR(SEARCH(J$1, $D36),0) >= 1, true,false) -> FALSE | K36: =If(IFERROR(SEARCH(K$1, $D36),0) >= 1, true,false) -> FALSE | M36: TRUE | N36: TRUE | O36: FALSE | P36: TRUE | Q36: =IF(ISBLANK(A36),B36,A36) -> KOERS | Museum van de Wielersport | R36: 9 | S36: FALSE | T36: FALSE
A37: Museum aan de IJzer | B37: Musée la tour de L’Yser | C37: West-Vlaanderen | D37: Geschiedenis en archeologie | E37: =If(IFERROR(SEARCH(E$1, $D37),0) >= 1, true,false) -> TRUE | F37: =If(IFERROR(SEARCH(F$1, $D37),0) >= 1, true,false) -> FALSE | G37: =If(IFERROR(SEARCH(G$1, $D37),0) >= 1, true,false) -> FALSE | H37: =If(IFERROR(SEARCH(H$1, $D37),0) >= 1, true,false) -> FALSE | I37: =If(IFERROR(SEARCH(I$1, $D37),0) >= 1, true,false) -> FALSE | J37: =If(IFERROR(SEARCH(J$1, $D37),0) >= 1, true,false) -> FALSE | K37: =If(IFERROR(SEARCH(K$1, $D37),0) >= 1, true,false) -> FALSE | M37: TRUE | N37: TRUE | O37: TRUE | P37: FALSE | Q37: =IF(ISBLANK(A37),B37,A37) -> Museum aan de IJzer | R37: 9.5 | S37: FALSE | T37: TRUE | U37: 9.5
A38: Museum Sint-Janshospitaal | B38: Musée Hôpital Saint-Jean | C38: West-Vlaanderen | D38: Beeldende kunst, Toegepaste kunst en design, Geschiedenis en archeologie, Wetenschap en technologie, Architectuur | E38: =If(IFERROR(SEARCH(E$1, $D38),0) >= 1, true,false) -> TRUE | F38: =If(IFERROR(SEARCH(F$1, $D38),0) >= 1, true,false) -> TRUE | G38: =If(IFERROR(SEARCH(G$1, $D38),0) >= 1, true,false) -> FALSE | H38: =If(IFERROR(SEARCH(H$1, $D38),0) >= 1, true,false) -> FALSE | I38: =If(IFERROR(SEARCH(I$1, $D38),0) >= 1, true,false) -> TRUE | J38: =If(IFERROR(SEARCH(J$1, $D38),0) >= 1, true,false) -> TRUE | K38: =If(IFERROR(SEARCH(K$1, $D38),0) >= 1, true,false) -> TRUE | M38: TRUE | N38: FALSE | O38: FALSE | P38: FALSE | Q38: =IF(ISBLANK(A38),B38,A38) -> Museum Sint-Janshospitaal | R38: 15 | S38: FALSE | T38: TRUE | U38: 15
A39: Mu.ZEE | Kunstmuseum aan Zee | B39: Musée Art-sur-Mer | C39: West-Vlaanderen | D39: Beeldende kunst | E39: =If(IFERROR(SEARCH(E$1, $D39),0) >= 1, true,false) -> FALSE | F39: =If(IFERROR(SEARCH(F$1, $D39),0) >= 1, true,false) -> FALSE | G39: =If(IFERROR(SEARCH(G$1, $D39),0) >= 1, true,false) -> FALSE | H39: =If(IFERROR(SEARCH(H$1, $D39),0) >= 1, true,false) -> FALSE | I39: =If(IFERROR(SEARCH(I$1, $D39),0) >= 1, true,false) -> FALSE | J39: =If(IFERROR(SEARCH(J$1, $D39),0) >= 1, true,false) -> TRUE | K39: =If(IFERROR(SEARCH(K$1, $D39),0) >= 1, true,false) -> FALSE | M39: TRUE | N39: FALSE | O39: FALSE | P39: FALSE | Q39: =IF(ISBLANK(A39),B39,A39) -> Mu.ZEE | Kunstmuseum aan Zee | R39: 12 | S39: TRUE | T39: TRUE | U39: 12
A40: Nationaal Tabaksmuseum | B40: Musée National du Tabac | C40: West-Vlaanderen | D40: Geschiedenis en archeologie | E40: =If(IFERROR(SEARCH(E$1, $D40),0) >= 1, true,false) -> TRUE | F40: =If(IFERROR(SEARCH(F$1, $D40),0) >= 1, true,false) -> FALSE | G40: =If(IFERROR(SEARCH(G$1, $D40),0) >= 1, true,false) -> FALSE | H40: =If(IFERROR(SEARCH(H$1, $D40),0) >= 1, true,false) -> FALSE | I40: =If(IFERROR(SEARCH(I$1, $D40),0) >= 1, true,false) -> FALSE | J40: =If(IFERROR(SEARCH(J$1, $D40),0) >= 1, true,false) -> FALSE | K40: =If(IFERROR(SEARCH(K$1, $D40),0) >= 1, true,false) -> FALSE | M40: FALSE | N40: FALSE | O40: FALSE | P40: FALSE | Q40: =IF(ISBLANK(A40),B40,A40) -> Nationaal Tabaksmuseum | R40: 4.5 | S40: FALSE | T40: TRUE | U40: 4.5
A41: NAVIGO Visserijmuseum | B41: Musée de la Pêche NAVIGO | C41: West-Vlaanderen | D41: Beeldende kunst, Wetenschap en technologie | E41: =If(IFERROR(SEARCH(E$1, $D41),0) >= 1, true,false) -> FALSE | F41: =If(IFERROR(SEARCH(F$1, $D41),0) >= 1, true,false) -> TRUE | G41: =If(IFERROR(SEARCH(G$1, $D41),0) >= 1, true,false) -> FALSE | H41: =If(IFERROR(SEARCH(H$1, $D41),0) >= 1, true,false) -> FALSE | I41: =If(IFERROR(SEARCH(I$1, $D41),0) >= 1, true,false) -> FALSE | J41: =If(IFERROR(SEARCH(J$1, $D41),0) >= 1, true,false) -> TRUE | K41: =If(IFERROR(SEARCH(K$1, $D41),0) >= 1, true,false) -> FALSE | M41: TRUE | N41: TRUE | O41: TRUE | P41: TRUE | Q41: =IF(ISBLANK(A41),B41,A41) -> NAVIGO Visserijmuseum | R41: 10 | S41: FALSE | T41: TRUE | U41: 0
A42: O.L.V.-kerk Museum | B42: Musée de l’Église Notre-Dame | C42: West-Vlaanderen | D42: Beeldende kunst, Architectuur | E42: =If(IFERROR(SEARCH(E$1, $D42),0) >= 1, true,false) -> FALSE | F42: =If(IFERROR(SEARCH(F$1, $D42),0) >= 1, true,false) -> FALSE | G42: =If(IFERROR(SEARCH(G$1, $D42),0) >= 1, true,false) -> FALSE | H42: =If(IFERROR(SEARCH(H$1, $D42),0) >= 1, true,false) -> FALSE | I42: =If(IFERROR(SEARCH(I$1, $D42),0) >= 1, true,false) -> TRUE | J42: =If(IFERROR(SEARCH(J$1, $D42),0) >= 1, true,false) -> TRUE | K42: =If(IFERROR(SEARCH(K$1, $D42),0) >= 1, true,false) -> FALSE | M42: FALSE | N42: FALSE | O42: FALSE | P42: FALSE | Q42: =IF(ISBLANK(A42),B42,A42) -> O.L.V.-kerk Museum | R42: 8 | S42: FALSE | T42: FALSE
A43: O.L.V. ter Potterie | B43: Musée Notre-Dame de la Poterie | C43: West-Vlaanderen | D43: Beeldende kunst, Toegepaste kunst en design, Geschiedenis en archeologie, Architectuur | E43: =If(IFERROR(SEARCH(E$1, $D43),0) >= 1, true,false) -> TRUE | F43: =If(IFERROR(SEARCH(F$1, $D43),0) >= 1, true,false) -> FALSE | G43: =If(IFERROR(SEARCH(G$1, $D43),0) >= 1, true,false) -> FALSE | H43: =If(IFERROR(SEARCH(H$1, $D43),0) >= 1, true,false) -> FALSE | I43: =If(IFERROR(SEARCH(I$1, $D43),0) >= 1, true,false) -> TRUE | J43: =If(IFERROR(SEARCH(J$1, $D43),0) >= 1, true,false) -> TRUE | K43: =If(IFERROR(SEARCH(K$1, $D43),0) >= 1, true,false) -> TRUE | M43: FALSE | N43: FALSE | O43: FALSE | P43: FALSE | Q43: =IF(ISBLANK(A43),B43,A43) -> O.L.V. ter Potterie | R43: 8 | S43: FALSE | T43: FALSE
A44: Passchendaele Museum | C44: West-Vlaanderen | D44: Geschiedenis en archeologie | E44: =If(IFERROR(SEARCH(E$1, $D44),0) >= 1, true,false) -> TRUE | F44: =If(IFERROR(SEARCH(F$1, $D44),0) >= 1, true,false) -> FALSE | G44: =If(IFERROR(SEARCH(G$1, $D44),0) >= 1, true,false) -> FALSE | H44: =If(IFERROR(SEARCH(H$1, $D44),0) >= 1, true,false) -> FALSE | I44: =If(IFERROR(SEARCH(I$1, $D44),0) >= 1, true,false) -> FALSE | J44: =If(IFERROR(SEARCH(J$1, $D44),0) >= 1, true,false) -> FALSE | K44: =If(IFERROR(SEARCH(K$1, $D44),0) >= 1, true,false) -> FALSE | M44: TRUE | N44: FALSE | O44: TRUE | P44: FALSE | Q44: =IF(ISBLANK(A44),B44,A44) -> Passchendaele Museum | R44: 13 | S44: FALSE | T44: TRUE | U44: 13
A45: Paul Delvaux Museum | B45: Musée Paul Delvaux | C45: West-Vlaanderen | D45: Beeldende kunst | E45: =If(IFERROR(SEARCH(E$1, $D45),0) >= 1, true,false) -> FALSE | F45: =If(IFERROR(SEARCH(F$1, $D45),0) >= 1, true,false) -> FALSE | G45: =If(IFERROR(SEARCH(G$1, $D45),0) >= 1, true,false) -> FALSE | H45: =If(IFERROR(SEARCH(H$1, $D45),0) >= 1, true,false) -> FALSE | I45: =If(IFERROR(SEARCH(I$1, $D45),0) >= 1, true,false) -> FALSE | J45: =If(IFERROR(SEARCH(J$1, $D45),0) >= 1, true,false) -> TRUE | K45: =If(IFERROR(SEARCH(K$1, $D45),0) >= 1, true,false) -> FALSE | M45: TRUE | N45: TRUE | O45: TRUE | P45: FALSE | Q45: =IF(ISBLANK(A45),B45,A45) -> Paul Delvaux Museum | R45: 12 | S45: FALSE | T45: FALSE
A46: Peiremuzee | C46: West-Vlaanderen | D46: Beeldende kunst | E46: =If(IFERROR(SEARCH(E$1, $D46),0) >= 1, true,false) -> FALSE | F46: =If(IFERROR(SEARCH(F$1, $D46),0) >= 1, true,false) -> FALSE | G46: =If(IFERROR(SEARCH(G$1, $D46),0) >= 1, true,false) -> FALSE | H46: =If(IFERROR(SEARCH(H$1, $D46),0) >= 1, true,false) -> FALSE | I46: =If(IFERROR(SEARCH(I$1, $D46),0) >= 1, true,false) -> FALSE | J46: =If(IFERROR(SEARCH(J$1, $D46),0) >= 1, true,false) -> TRUE | K46: =If(IFERROR(SEARCH(K$1, $D46),0) >= 1, true,false) -> FALSE | M46: TRUE | N46: FALSE | O46: FALSE | P46: FALSE | Q46: =IF(ISBLANK(A46),B46,A46) -> Peiremuzee | R46: 12 | S46: FALSE | T46: FALSE
A47: Permekemuseum | B47: Musée Permeke | C47: West-Vlaanderen | D47: Beeldende kunst | E47: =If(IFERROR(SEARCH(E$1, $D47),0) >= 1, true,false) -> FALSE | F47: =If(IFERROR(SEARCH(F$1, $D47),0) >= 1, true,false) -> FALSE | G47: =If(IFERROR(SEARCH(G$1, $D47),0) >= 1, true,false) -> FALSE | H47: =If(IFERROR(SEARCH(H$1, $D47),0) >= 1, true,false) -> FALSE | I47: =If(IFERROR(SEARCH(I$1, $D47),0) >= 1, true,false) -> FALSE | J47: =If(IFERROR(SEARCH(J$1, $D47),0) >= 1, true,false) -> TRUE | K47: =If(IFERROR(SEARCH(K$1, $D47),0) >= 1, true,false) -> FALSE | M47: FALSE | N47: FALSE | O47: FALSE | P47: FALSE | Q47: =IF(ISBLANK(A47),B47,A47) -> Permekemuseum | R47: 12 | S47: FALSE | T47: FALSE
A48: Romeins Archeologisch Museum Oudenburg | B48: Musée d’archéologie romaine Oudenburg | C48: West-Vlaanderen | D48: Geschiedenis en archeologie | E48: =If(IFERROR(SEARCH(E$1, $D48),0) >= 1, true,false) -> TRUE | F48: =If(IFERROR(SEARCH(F$1, $D48),0) >= 1, true,false) -> FALSE | G48: =If(IFERROR(SEARCH(G$1, $D48),0) >= 1, true,false) -> FALSE | H48: =If(IFERROR(SEARCH(H$1, $D48),0) >= 1, true,false) -> FALSE | I48: =If(IFERROR(SEARCH(I$1, $D48),0) >= 1, true,false) -> FALSE | J48: =If(IFERROR(SEARCH(J$1, $D48),0) >= 1, true,false) -> FALSE | K48: =If(IFERROR(SEARCH(K$1, $D48),0) >= 1, true,false) -> FALSE | M48: TRUE | N48: TRUE | O48: TRUE | P48: FALSE | Q48: =IF(ISBLANK(A48),B48,A48) -> Romeins Archeologisch Museum Oudenburg | R48: 8 | S48: FALSE | T48: FALSE
A49: Sint-Janshuismolen | B49: Moulin Sint-Janshuis | C49: West-Vlaanderen | D49: Geschiedenis en archeologie, Wetenschap en technologie | E49: =If(IFERROR(SEARCH(E$1, $D49),0) >= 1, true,false) -> TRUE | F49: =If(IFERROR(SEARCH(F$1, $D49),0) >= 1, true,false) -> TRUE | G49: =If(IFERROR(SEARCH(G$1, $D49),0) >= 1, true,false) -> FALSE | H49: =If(IFERROR(SEARCH(H$1, $D49),0) >= 1, true,false) -> FALSE | I49: =If(IFERROR(SEARCH(I$1, $D49),0) >= 1, true,false) -> FALSE | J49: =If(IFERROR(SEARCH(J$1, $D49),0) >= 1, true,false) -> FALSE | K49: =If(IFERROR(SEARCH(K$1, $D49),0) >= 1, true,false) -> FALSE | M49: FALSE | N49: FALSE | O49: FALSE | P49: FALSE | Q49: =IF(ISBLANK(A49),B49,A49) -> Sint-Janshuismolen | R49: 5 | S49: FALSE | T49: FALSE
A50: Stadhuis Brugge | B50: L’Hôtel de ville Bruges | C50: West-Vlaanderen | D50: Beeldende kunst, Toegepaste kunst en design, Geschiedenis en archeologie, Architectuur | E50: =If(IFERROR(SEARCH(E$1, $D50),0) >= 1, true,false) -> TRUE | F50: =If(IFERROR(SEARCH(F$1, $D50),0) >= 1, true,false) -> FALSE | G50: =If(IFERROR(SEARCH(G$1, $D50),0) >= 1, true,false) -> FALSE | H50: =If(IFERROR(SEARCH(H$1, $D50),0) >= 1, true,false) -> FALSE | I50: =If(IFERROR(SEARCH(I$1, $D50),0) >= 1, true,false) -> TRUE | J50: =If(IFERROR(SEARCH(J$1, $D50),0) >= 1, true,false) -> TRUE | K50: =If(IFERROR(SEARCH(K$1, $D50),0) >= 1, true,false) -> TRUE | M50: FALSE | N50: FALSE | O50: FALSE | P50: FALSE | Q50: =IF(ISBLANK(A50),B50,A50) -> Stadhuis Brugge | R50: 8 | S50: FALSE | T50: FALSE
A51: Talbot House | C51: West-Vlaanderen | D51: Geschiedenis en archeologie | E51: =If(IFERROR(SEARCH(E$1, $D51),0) >= 1, true,false) -> TRUE | F51: =If(IFERROR(SEARCH(F$1, $D51),0) >= 1, true,false) -> FALSE | G51: =If(IFERROR(SEARCH(G$1, $D51),0) >= 1, true,false) -> FALSE | H51: =If(IFERROR(SEARCH(H$1, $D51),0) >= 1, true,false) -> FALSE | I51: =If(IFERROR(SEARCH(I$1, $D51),0) >= 1, true,false) -> FALSE | J51: =If(IFERROR(SEARCH(J$1, $D51),0) >= 1, true,false) -> FALSE | K51: =If(IFERROR(SEARCH(K$1, $D51),0) >= 1, true,false) -> FALSE | M51: TRUE | N51: FALSE | O51: FALSE | P51: FALSE | Q51: =IF(ISBLANK(A51),B51,A51) -> Talbot House | R51: 10 | S51: FALSE | T51: TRUE | U51: 10
A52: Texture | Museum van Vlas en Textiel | B52: Musée du Lin et du Textile | C52: West-Vlaanderen | D52: Toegepaste kunst en design, Wetenschap en technologie, Architectuur, Mode | E52: =If(IFERROR(SEARCH(E$1, $D52),0) >= 1, true,false) -> FALSE | F52: =If(IFERROR(SEARCH(F$1, $D52),0) >= 1, true,false) -> TRUE | G52: =If(IFERROR(SEARCH(G$1, $D52),0) >= 1, true,false) -> TRUE | H52: =If(IFERROR(SEARCH(H$1, $D52),0) >= 1, true,false) -> FALSE | I52: =If(IFERROR(SEARCH(I$1, $D52),0) >= 1, true,false) -> TRUE | J52: =If(IFERROR(SEARCH(J$1, $D52),0) >= 1, true,false) -> FALSE | K52: =If(IFERROR(SEARCH(K$1, $D52),0) >= 1, true,false) -> TRUE | M52: TRUE | N52: TRUE | O52: TRUE | P52: FALSE | Q52: =IF(ISBLANK(A52),B52,A52) -> Texture | Museum van Vlas en Textiel | R52: 8 | S52: FALSE | T52: TRUE | U52: 8
A53: Uilenspiegelmuseum | B53: Musée d’Ulenspiegel | C53: West-Vlaanderen | D53: Literatuur | E53: =If(IFERROR(SEARCH(E$1, $D53),0) >= 1, true,false) -> FALSE | F53: =If(IFERROR(SEARCH(F$1, $D53),0) >= 1, true,false) -> FALSE | G53: =If(IFERROR(SEARCH(G$1, $D53),0) >= 1, true,false) -> FALSE | H53: =If(IFERROR(SEARCH(H$1, $D53),0) >= 1, true,false) -> TRUE | I53: =If(IFERROR(SEARCH(I$1, $D53),0) >= 1, true,false) -> FALSE | J53: =If(IFERROR(SEARCH(J$1, $D53),0) >= 1, true,false) -> FALSE | K53: =If(IFERROR(SEARCH(K$1, $D53),0) >= 1, true,false) -> FALSE | M53: FALSE | N53: FALSE | O53: FALSE | P53: FALSE | Q53: =IF(ISBLANK(A53),B53,A53) -> Uilenspiegelmuseum | R53: 6 | S53: FALSE | T53: FALSE
A54: Volkskundemuseum | B54: Musée de la vie populaire | C54: West-Vlaanderen | D54: Geschiedenis en archeologie | E54: =If(IFERROR(SEARCH(E$1, $D54),0) >= 1, true,false) -> TRUE | F54: =If(IFERROR(SEARCH(F$1, $D54),0) >= 1, true,false) -> FALSE | G54: =If(IFERROR(SEARCH(G$1, $D54),0) >= 1, true,false) -> FALSE | H54: =If(IFERROR(SEARCH(H$1, $D54),0) >= 1, true,false) -> FALSE | I54: =If(IFERROR(SEARCH(I$1, $D54),0) >= 1, true,false) -> FALSE | J54: =If(IFERROR(SEARCH(J$1, $D54),0) >= 1, true,false) -> FALSE | K54: =If(IFERROR(SEARCH(K$1, $D54),0) >= 1, true,false) -> FALSE | M54: FALSE | N54: FALSE | O54: FALSE | P54: FALSE | Q54: =IF(ISBLANK(A54),B54,A54) -> Volkskundemuseum | R54: 8 | S54: FALSE | T54: FALSE
A55: Westfront Nieuwpoort | C55: West-Vlaanderen | D55: Geschiedenis en archeologie, Architectuur | E55: =If(IFERROR(SEARCH(E$1, $D55),0) >= 1, true,false) -> TRUE | F55: =If(IFERROR(SEARCH(F$1, $D55),0) >= 1, true,false) -> FALSE | G55: =If(IFERROR(SEARCH(G$1, $D55),0) >= 1, true,false) -> FALSE | H55: =If(IFERROR(SEARCH(H$1, $D55),0) >= 1, true,false) -> FALSE | I55: =If(IFERROR(SEARCH(I$1, $D55),0) >= 1, true,false) -> TRUE | J55: =If(IFERROR(SEARCH(J$1, $D55),0) >= 1, true,false) -> FALSE | K55: =If(IFERROR(SEARCH(K$1, $D55),0) >= 1, true,false) -> FALSE | M55: TRUE | N55: FALSE | O55: FALSE | P55: FALSE | Q55: =IF(ISBLANK(A55),B55,A55) -> Westfront Nieuwpoort | R55: 9.5 | S55: FALSE | T55: FALSE
A56: Yper Museum | C56: West-Vlaanderen | D56: Beeldende kunst, Toegepaste kunst en design, Geschiedenis en archeologie, Architectuur | E56: =If(IFERROR(SEARCH(E$1, $D56),0) >= 1, true,false) -> TRUE | F56: =If(IFERROR(SEARCH(F$1, $D56),0) >= 1, true,false) -> FALSE | G56: =If(IFERROR(SEARCH(G$1, $D56),0) >= 1, true,false) -> FALSE | H56: =If(IFERROR(SEARCH(H$1, $D56),0) >= 1, true,false) -> FALSE | I56: =If(IFERROR(SEARCH(I$1, $D56),0) >= 1, true,false) -> TRUE | J56: =If(IFERROR(SEARCH(J$1, $D56),0) >= 1, true,false) -> TRUE | K56: =If(IFERROR(SEARCH(K$1, $D56),0) >= 1, true,false) -> TRUE | M56: FALSE | N56: TRUE | O56: FALSE | P56: FALSE | Q56: =IF(ISBLANK(A56),B56,A56) -> Yper Museum | R56: 8.5 | S56: FALSE | T56: FALSE
A57: Zwin Natuur Park | B57: Zwin Parc Naturel | C57: West-Vlaanderen | D57: Geschiedenis en archeologie, Wetenschap en technologie | E57: =If(IFERROR(SEARCH(E$1, $D57),0) >= 1, true,false) -> TRUE | F57: =If(IFERROR(SEARCH(F$1, $D57),0) >= 1, true,false) -> TRUE | G57: =If(IFERROR(SEARCH(G$1, $D57),0) >= 1, true,false) -> FALSE | H57: =If(IFERROR(SEARCH(H$1, $D57),0) >= 1, true,false) -> FALSE | I57: =If(IFERROR(SEARCH(I$1, $D57),0) >= 1, true,false) -> FALSE | J57: =If(IFERROR(SEARCH(J$1, $D57),0) >= 1, true,false) -> FALSE | K57: =If(IFERROR(SEARCH(K$1, $D57),0) >= 1, true,false) -> FALSE | M57: TRUE | N57: TRUE | O57: TRUE | P57: TRUE | Q57: =IF(ISBLANK(A57),B57,A57) -> Zwin Natuur Park | R57: 12 | S57: FALSE | T57: TRUE | U57: 14
A58: Arboretum Kalmtout | C58: Antwerpen | D58: Wetenschap en technologie | E58: =If(IFERROR(SEARCH(E$1, $D58),0) >= 1, true,false) -> FALSE | F58: =If(IFERROR(SEARCH(F$1, $D58),0) >= 1, true,false) -> TRUE | G58: =If(IFERROR(SEARCH(G$1, $D58),0) >= 1, true,false) -> FALSE | H58: =If(IFERROR(SEARCH(H$1, $D58),0) >= 1, true,false) -> FALSE | I58: =If(IFERROR(SEARCH(I$1, $D58),0) >= 1, true,false) -> FALSE | J58: =If(IFERROR(SEARCH(J$1, $D58),0) >= 1, true,false) -> FALSE | K58: =If(IFERROR(SEARCH(K$1, $D58),0) >= 1, true,false) -> FALSE | M58: TRUE | N58: TRUE | O58: TRUE | P58: TRUE | Q58: =IF(ISBLANK(A58),B58,A58) -> Arboretum Kalmtout | R58: 8 | S58: FALSE | T58: TRUE | U58: 9.5
A59: Begijnhofmuseum Turnhout | B59: Musée du béguinage Turnhout | C59: Antwerpen | D59: Beeldende kunst, Geschiedenis en archeologie | E59: =If(IFERROR(SEARCH(E$1, $D59),0) >= 1, true,false) -> TRUE | F59: =If(IFERROR(SEARCH(F$1, $D59),0) >= 1, true,false) -> FALSE | G59: =If(IFERROR(SEARCH(G$1, $D59),0) >= 1, true,false) -> FALSE | H59: =If(IFERROR(SEARCH(H$1, $D59),0) >= 1, true,false) -> FALSE | I59: =If(IFERROR(SEARCH(I$1, $D59),0) >= 1, true,false) -> FALSE | J59: =If(IFERROR(SEARCH(J$1, $D59),0) >= 1, true,false) -> TRUE | K59: =If(IFERROR(SEARCH(K$1, $D59),0) >= 1, true,false) -> FALSE | M59: TRUE | N59: FALSE | O59: FALSE | P59: FALSE | Q59: =IF(ISBLANK(A59),B59,A59) -> Begijnhofmuseum Turnhout | R59: 5 | S59: FALSE | T59: FALSE
A60: DIVA | museum voor diamant juwelen en zilver | B60: le musée du diamant, des bijoux et de l’orfèvrerie | C60: Antwerpen | D60: Toegepaste kunst en design, Geschiedenis en archeologie, Wetenschap en technologie | E60: =If(IFERROR(SEARCH(E$1, $D60),0) >= 1, true,false) -> TRUE | F60: =If(IFERROR(SEARCH(F$1, $D60),0) >= 1, true,false) -> TRUE | G60: =If(IFERROR(SEARCH(G$1, $D60),0) >= 1, true,false) -> FALSE | H60: =If(IFERROR(SEARCH(H$1, $D60),0) >= 1, true,false) -> FALSE | I60: =If(IFERROR(SEARCH(I$1, $D60),0) >= 1, true,false) -> FALSE | J60: =If(IFERROR(SEARCH(J$1, $D60),0) >= 1, true,false) -> FALSE | K60: =If(IFERROR(SEARCH(K$1, $D60),0) >= 1, true,false) -> TRUE | M60: TRUE | N60: FALSE | O60: FALSE | P60: FALSE | Q60: =IF(ISBLANK(A60),B60,A60) -> DIVA | museum voor diamant juwelen en zilver | R60: 12 | S60: FALSE | T60: FALSE
A61: Erfgoedbibliotheek Hendrik Conscience - Nottebohmzaal | B61: Bibliothèque Patrimoniale Hendrik Conscience - salle Nottebohm | C61: Antwerpen | D61: Geschiedenis en archeologie, Literatuur | E61: =If(IFERROR(SEARCH(E$1, $D61),0) >= 1, true,false) -> TRUE | F61: =If(IFERROR(SEARCH(F$1, $D61),0) >= 1, true,false) -> FALSE | G61: =If(IFERROR(SEARCH(G$1, $D61),0) >= 1, true,false) -> FALSE | H61: =If(IFERROR(SEARCH(H$1, $D61),0) >= 1, true,false) -> TRUE | I61: =If(IFERROR(SEARCH(I$1, $D61),0) >= 1, true,false) -> FALSE | J61: =If(IFERROR(SEARCH(J$1, $D61),0) >= 1, true,false) -> FALSE | K61: =If(IFERROR(SEARCH(K$1, $D61),0) >= 1, true,false) -> FALSE | M61: FALSE | N61: FALSE | O61: FALSE | P61: FALSE | Q61: =IF(ISBLANK(A61),B61,A61) -> Erfgoedbibliotheek Hendrik Conscience - Nottebohmzaal | R61: 0 | S61: FALSE | T61: FALSE
A62: FOMU | Fotomuseum Antwerpen | B62: Musée de la Photographie d’Anvers | C62: Antwerpen | D62: Beeldende kunst | E62: =If(IFERROR(SEARCH(E$1, $D62),0) >= 1, true,false) -> FALSE | F62: =If(IFERROR(SEARCH(F$1, $D62),0) >= 1, true,false) -> FALSE | G62: =If(IFERROR(SEARCH(G$1, $D62),0) >= 1, true,false) -> FALSE | H62: =If(IFERROR(SEARCH(H$1, $D62),0) >= 1, true,false) -> FALSE | I62: =If(IFERROR(SEARCH(I$1, $D62),0) >= 1, true,false) -> FALSE | J62: =If(IFERROR(SEARCH(J$1, $D62),0) >= 1, true,false) -> TRUE | K62: =If(IFERROR(SEARCH(K$1, $D62),0) >= 1, true,false) -> FALSE | M62: TRUE | N62: TRUE | O62: TRUE | P62: FALSE | Q62: =IF(ISBLANK(A62),B62,A62) -> FOMU | Fotomuseum Antwerpen | R62: 12 | S62: FALSE | T62: TRUE | U62: 12
A63: Fort van Breendonk | B63: Fort de Breendonk | C63: Antwerpen | D63: Geschiedenis en archeologie | E63: =If(IFERROR(SEARCH(E$1, $D63),0) >= 1, true,false) -> TRUE | F63: =If(IFERROR(SEARCH(F$1, $D63),0) >= 1, true,false) -> FALSE | G63: =If(IFERROR(SEARCH(G$1, $D63),0) >= 1, true,false) -> FALSE | H63: =If(IFERROR(SEARCH(H$1, $D63),0) >= 1, true,false) -> FALSE | I63: =If(IFERROR(SEARCH(I$1, $D63),0) >= 1, true,false) -> FALSE | J63: =If(IFERROR(SEARCH(J$1, $D63),0) >= 1, true,false) -> FALSE | K63: =If(IFERROR(SEARCH(K$1, $D63),0) >= 1, true,false) -> FALSE | M63: FALSE | N63: FALSE | O63: TRUE | P63: FALSE | Q63: =IF(ISBLANK(A63),B63,A63) -> Fort van Breendonk | R63: 12 | S63: FALSE | T63: FALSE
A64: Gasthuismuseum Geel | B64: Musée de l’hôpital Geel | C64: Antwerpen | D64: Beeldende kunst, Geschiedenis en archeologie, Wetenschap en technologie, Architectuur | E64: =If(IFERROR(SEARCH(E$1, $D64),0) >= 1, true,false) -> TRUE | F64: =If(IFERROR(SEARCH(F$1, $D64),0) >= 1, true,false) -> TRUE | G64: =If(IFERROR(SEARCH(G$1, $D64),0) >= 1, true,false) -> FALSE | H64: =If(IFERROR(SEARCH(H$1, $D64),0) >= 1, true,false) -> FALSE | I64: =If(IFERROR(SEARCH(I$1, $D64),0) >= 1, true,false) -> TRUE | J64: =If(IFERROR(SEARCH(J$1, $D64),0) >= 1, true,false) -> TRUE | K64: =If(IFERROR(SEARCH(K$1, $D64),0) >= 1, true,false) -> FALSE | M64: TRUE | N64: FALSE | O64: TRUE | P64: FALSE | Q64: =IF(ISBLANK(A64),B64,A64) -> Gasthuismuseum Geel | R64: 12 | S64: FALSE | T64: TRUE | U64: 6
A65: Het Snijders&Rockoxhuis | B65: La maison Snijders&Rockox | C65: Antwerpen | D65: Geschiedenis en archeologie | E65: =If(IFERROR(SEARCH(E$1, $D65),0) >= 1, true,false) -> TRUE | F65: =If(IFERROR(SEARCH(F$1, $D65),0) >= 1, true,false) -> FALSE | G65: =If(IFERROR(SEARCH(G$1, $D65),0) >= 1, true,false) -> FALSE | H65: =If(IFERROR(SEARCH(H$1, $D65),0) >= 1, true,false) -> FALSE | I65: =If(IFERROR(SEARCH(I$1, $D65),0) >= 1, true,false) -> FALSE | J65: =If(IFERROR(SEARCH(J$1, $D65),0) >= 1, true,false) -> FALSE | K65: =If(IFERROR(SEARCH(K$1, $D65),0) >= 1, true,false) -> FALSE | M65: TRUE | N65: FALSE | O65: FALSE | P65: FALSE | Q65: =IF(ISBLANK(A65),B65,A65) -> Het Snijders&Rockoxhuis | R65: 10 | S65: FALSE | T65: TRUE | U65: 10
A66: Jakob Smitsmuseum | B66: Musée Jakob Smits | C66: Antwerpen | D66: Beeldende kunst | E66: =If(IFERROR(SEARCH(E$1, $D66),0) >= 1, true,false) -> FALSE | F66: =If(IFERROR(SEARCH(F$1, $D66),0) >= 1, true,false) -> FALSE | G66: =If(IFERROR(SEARCH(G$1, $D66),0) >= 1, true,false) -> FALSE | H66: =If(IFERROR(SEARCH(H$1, $D66),0) >= 1, true,false) -> FALSE | I66: =If(IFERROR(SEARCH(I$1, $D66),0) >= 1, true,false) -> FALSE | J66: =If(IFERROR(SEARCH(J$1, $D66),0) >= 1, true,false) -> TRUE | K66: =If(IFERROR(SEARCH(K$1, $D66),0) >= 1, true,false) -> FALSE | M66: TRUE | N66: FALSE | O66: TRUE | P66: FALSE | Q66: =IF(ISBLANK(A66),B66,A66) -> Jakob Smitsmuseum | R66: 5 | S66: FALSE | T66: TRUE | U66: 5
A67: Karrenmuseum Essen | B67: Musée de Chariot Essen | C67: Antwerpen | D67: Geschiedenis en archeologie, Wetenschap en technologie | E67: =If(IFERROR(SEARCH(E$1, $D67),0) >= 1, true,false) -> TRUE | F67: =If(IFERROR(SEARCH(F$1, $D67),0) >= 1, true,false) -> TRUE | G67: =If(IFERROR(SEARCH(G$1, $D67),0) >= 1, true,false) -> FALSE | H67: =If(IFERROR(SEARCH(H$1, $D67),0) >= 1, true,false) -> FALSE | I67: =If(IFERROR(SEARCH(I$1, $D67),0) >= 1, true,false) -> FALSE | J67: =If(IFERROR(SEARCH(J$1, $D67),0) >= 1, true,false) -> FALSE | K67: =If(IFERROR(SEARCH(K$1, $D67),0) >= 1, true,false) -> FALSE | M67: TRUE | N67: TRUE | O67: TRUE | P67: TRUE | Q67: =IF(ISBLANK(A67),B67,A67) -> Karrenmuseum Essen | R67: 6 | S67: FALSE | T67: FALSE
A68: Kazerne Dossin | B68: Caserne Dossin | C68: Antwerpen | D68: Geschiedenis en archeologie | E68: =If(IFERROR(SEARCH(E$1, $D68),0) >= 1, true,false) -> TRUE | F68: =If(IFERROR(SEARCH(F$1, $D68),0) >= 1, true,false) -> FALSE | G68: =If(IFERROR(SEARCH(G$1, $D68),0) >= 1, true,false) -> FALSE | H68: =If(IFERROR(SEARCH(H$1, $D68),0) >= 1, true,false) -> FALSE | I68: =If(IFERROR(SEARCH(I$1, $D68),0) >= 1, true,false) -> FALSE | J68: =If(IFERROR(SEARCH(J$1, $D68),0) >= 1, true,false) -> FALSE | K68: =If(IFERROR(SEARCH(K$1, $D68),0) >= 1, true,false) -> FALSE | M68: TRUE | N68: FALSE | O68: TRUE | P68: FALSE | Q68: =IF(ISBLANK(A68),B68,A68) -> Kazerne Dossin | R68: 12 | S68: FALSE | T68: TRUE | U68: 10
A69: KMSKA | Koninklijk Museum voor Schone Kunsten Antwerpen | B69: Musée Royal des Beaux-Arts d’Anver | C69: Antwerpen | D69: Beeldende kunst | E69: =If(IFERROR(SEARCH(E$1, $D69),0) >= 1, true,false) -> FALSE | F69: =If(IFERROR(SEARCH(F$1, $D69),0) >= 1, true,false) -> FALSE | G69: =If(IFERROR(SEARCH(G$1, $D69),0) >= 1, true,false) -> FALSE | H69: =If(IFERROR(SEARCH(H$1, $D69),0) >= 1, true,false) -> FALSE | I69: =If(IFERROR(SEARCH(I$1, $D69),0) >= 1, true,false) -> FALSE | J69: =If(IFERROR(SEARCH(J$1, $D69),0) >= 1, true,false) -> TRUE | K69: =If(IFERROR(SEARCH(K$1, $D69),0) >= 1, true,false) -> FALSE | M69: TRUE | N69: TRUE | O69: FALSE | P69: TRUE | Q69: =IF(ISBLANK(A69),B69,A69) -> KMSKA | Koninklijk Museum voor Schone Kunsten Antwerpen | R69: 20 | S69: FALSE | T69: TRUE | U69: 20
A70: Kunsthal Extra City | C70: Antwerpen | D70: Beeldende kunst | E70: =If(IFERROR(SEARCH(E$1, $D70),0) >= 1, true,false) -> FALSE | F70: =If(IFERROR(SEARCH(F$1, $D70),0) >= 1, true,false) -> FALSE | G70: =If(IFERROR(SEARCH(G$1, $D70),0) >= 1, true,false) -> FALSE | H70: =If(IFERROR(SEARCH(H$1, $D70),0) >= 1, true,false) -> FALSE | I70: =If(IFERROR(SEARCH(I$1, $D70),0) >= 1, true,false) -> FALSE | J70: =If(IFERROR(SEARCH(J$1, $D70),0) >= 1, true,false) -> TRUE | K70: =If(IFERROR(SEARCH(K$1, $D70),0) >= 1, true,false) -> FALSE | M70: TRUE | N70: TRUE | O70: FALSE | P70: FALSE | Q70: =IF(ISBLANK(A70),B70,A70) -> Kunsthal Extra City | R70: 7 | S70: FALSE | T70: TRUE | U70: 7
A71: Kunsthal Mechelen | B71: Kunsthal Malines | C71: Antwerpen | D71: Beeldende kunst | E71: =If(IFERROR(SEARCH(E$1, $D71),0) >= 1, true,false) -> FALSE | F71: =If(IFERROR(SEARCH(F$1, $D71),0) >= 1, true,false) -> FALSE | G71: =If(IFERROR(SEARCH(G$1, $D71),0) >= 1, true,false) -> FALSE | H71: =If(IFERROR(SEARCH(H$1, $D71),0) >= 1, true,false) -> FALSE | I71: =If(IFERROR(SEARCH(I$1, $D71),0) >= 1, true,false) -> FALSE | J71: =If(IFERROR(SEARCH(J$1, $D71),0) >= 1, true,false) -> TRUE | K71: =If(IFERROR(SEARCH(K$1, $D71),0) >= 1, true,false) -> FALSE | M71: TRUE | N71: TRUE | O71: FALSE | P71: FALSE | Q71: =IF(ISBLANK(A71),B71,A71) -> Kunsthal Mechelen | R71: 5 | S71: FALSE | T71: TRUE | U71: 5
A72: MAS | Museum aan de Stroom | C72: Antwerpen | D72: Beeldende kunst, Toegepaste kunst en design, Geschiedenis en archeologie | E72: =If(IFERROR(SEARCH(E$1, $D72),0) >= 1, true,false) -> TRUE | F72: =If(IFERROR(SEARCH(F$1, $D72),0) >= 1, true,false) -> FALSE | G72: =If(IFERROR(SEARCH(G$1, $D72),0) >= 1, true,false) -> FALSE | H72: =If(IFERROR(SEARCH(H$1, $D72),0) >= 1, true,false) -> FALSE | I72: =If(IFERROR(SEARCH(I$1, $D72),0) >= 1, true,false) -> FALSE | J72: =If(IFERROR(SEARCH(J$1, $D72),0) >= 1, true,false) -> TRUE | K72: =If(IFERROR(SEARCH(K$1, $D72),0) >= 1, true,false) -> TRUE | M72: TRUE | N72: TRUE | O72: FALSE | P72: TRUE | Q72: =IF(ISBLANK(A72),B72,A72) -> MAS | Museum aan de Stroom | R72: 10 | S72: FALSE | T72: TRUE | U72: 10
A73: M HKA | Museum van Hedendaagse Kunst Antwerpen | B73: Musée d’Art Contemporain d’Anvers | C73: Antwerpen | D73: Beeldende kunst, Toegepaste kunst en design | E73: =If(IFERROR(SEARCH(E$1, $D73),0) >= 1, true,false) -> FALSE | F73: =If(IFERROR(SEARCH(F$1, $D73),0) >= 1, true,false) -> FALSE | G73: =If(IFERROR(SEARCH(G$1, $D73),0) >= 1, true,false) -> FALSE | H73: =If(IFERROR(SEARCH(H$1, $D73),0) >= 1, true,false) -> FALSE | I73: =If(IFERROR(SEARCH(I$1, $D73),0) >= 1, true,false) -> FALSE | J73: =If(IFERROR(SEARCH(J$1, $D73),0) >= 1, true,false) -> TRUE | K73: =If(IFERROR(SEARCH(K$1, $D73),0) >= 1, true,false) -> TRUE | M73: TRUE | N73: TRUE | O73: FALSE | P73: FALSE | Q73: =IF(ISBLANK(A73),B73,A73) -> M HKA | Museum van Hedendaagse Kunst Antwerpen | R73: 14 | S73: FALSE | T73: TRUE | U73: 14
A74: Middelheimmuseum | B74: Musée Middelheim | C74: Antwerpen | D74: Beeldende kunst, Toegepaste kunst en design | E74: =If(IFERROR(SEARCH(E$1, $D74),0) >= 1, true,false) -> FALSE | F74: =If(IFERROR(SEARCH(F$1, $D74),0) >= 1, true,false) -> FALSE | G74: =If(IFERROR(SEARCH(G$1, $D74),0) >= 1, true,false) -> FALSE | H74: =If(IFERROR(SEARCH(H$1, $D74),0) >= 1, true,false) -> FALSE | I74: =If(IFERROR(SEARCH(I$1, $D74),0) >= 1, true,false) -> FALSE | J74: =If(IFERROR(SEARCH(J$1, $D74),0) >= 1, true,false) -> TRUE | K74: =If(IFERROR(SEARCH(K$1, $D74),0) >= 1, true,false) -> TRUE | M74: TRUE | N74: TRUE | O74: FALSE | P74: FALSE | Q74: =IF(ISBLANK(A74),B74,A74) -> Middelheimmuseum | R74: 0 | S74: FALSE | T74: TRUE | U74: 0
A75: MoMu | ModeMuseum Antwerpen | B75: Musée de la Mode Anvers | C75: Antwerpen | D75: Toegepaste kunst en design, Mode | E75: =If(IFERROR(SEARCH(E$1, $D75),0) >= 1, true,false) -> FALSE | F75: =If(IFERROR(SEARCH(F$1, $D75),0) >= 1, true,false) -> FALSE | G75: =If(IFERROR(SEARCH(G$1, $D75),0) >= 1, true,false) -> TRUE | H75: =If(IFERROR(SEARCH(H$1, $D75),0) >= 1, true,false) -> FALSE | I75: =If(IFERROR(SEARCH(I$1, $D75),0) >= 1, true,false) -> FALSE | J75: =If(IFERROR(SEARCH(J$1, $D75),0) >= 1, true,false) -> FALSE | K75: =If(IFERROR(SEARCH(K$1, $D75),0) >= 1, true,false) -> TRUE | M75: TRUE | N75: TRUE | O75: FALSE | P75: FALSE | Q75: =IF(ISBLANK(A75),B75,A75) -> MoMu | ModeMuseum Antwerpen | R75: 12 | S75: FALSE | T75: TRUE | U75: 12
A76: Museum De Reede | B76: Musée De Reede | C76: Antwerpen | D76: Beeldende kunst | E76: =If(IFERROR(SEARCH(E$1, $D76),0) >= 1, true,false) -> FALSE | F76: =If(IFERROR(SEARCH(F$1, $D76),0) >= 1, true,false) -> FALSE | G76: =If(IFERROR(SEARCH(G$1, $D76),0) >= 1, true,false) -> FALSE | H76: =If(IFERROR(SEARCH(H$1, $D76),0) >= 1, true,false) -> FALSE | I76: =If(IFERROR(SEARCH(I$1, $D76),0) >= 1, true,false) -> FALSE | J76: =If(IFERROR(SEARCH(J$1, $D76),0) >= 1, true,false) -> TRUE | K76: =If(IFERROR(SEARCH(K$1, $D76),0) >= 1, true,false) -> FALSE | M76: TRUE | N76: FALSE | O76: FALSE | P76: FALSE | Q76: =IF(ISBLANK(A76),B76,A76) -> Museum De Reede | R76: 15 | S76: FALSE | T76: TRUE | U76: 15
A77: Museum Fort Liezele | B77: Musée Fort Liezele | C77: Antwerpen | D77: Geschiedenis en archeologie | E77: =If(IFERROR(SEARCH(E$1, $D77),0) >= 1, true,false) -> TRUE | F77: =If(IFERROR(SEARCH(F$1, $D77),0) >= 1, true,false) -> FALSE | G77: =If(IFERROR(SEARCH(G$1, $D77),0) >= 1, true,false) -> FALSE | H77: =If(IFERROR(SEARCH(H$1, $D77),0) >= 1, true,false) -> FALSE | I77: =If(IFERROR(SEARCH(I$1, $D77),0) >= 1, true,false) -> FALSE | J77: =If(IFERROR(SEARCH(J$1, $D77),0) >= 1, true,false) -> FALSE | K77: =If(IFERROR(SEARCH(K$1, $D77),0) >= 1, true,false) -> FALSE | M77: TRUE | N77: TRUE | O77: TRUE | P77: TRUE | Q77: =IF(ISBLANK(A77),B77,A77) -> Museum Fort Liezele | R77: 12 | S77: FALSE | T77: FALSE
A78: Museum Hof van Busleyden | C78: Antwerpen | D78: Geschiedenis en archeologie | E78: =If(IFERROR(SEARCH(E$1, $D78),0) >= 1, true,false) -> TRUE | F78: =If(IFERROR(SEARCH(F$1, $D78),0) >= 1, true,false) -> FALSE | G78: =If(IFERROR(SEARCH(G$1, $D78),0) >= 1, true,false) -> FALSE | H78: =If(IFERROR(SEARCH(H$1, $D78),0) >= 1, true,false) -> FALSE | I78: =If(IFERROR(SEARCH(I$1, $D78),0) >= 1, true,false) -> FALSE | J78: =If(IFERROR(SEARCH(J$1, $D78),0) >= 1, true,false) -> FALSE | K78: =If(IFERROR(SEARCH(K$1, $D78),0) >= 1, true,false) -> FALSE | M78: TRUE | N78: TRUE | O78: FALSE | P78: FALSE | Q78: =IF(ISBLANK(A78),B78,A78) -> Museum Hof van Busleyden | R78: 15 | S78: FALSE | T78: TRUE | U78: 15
A79: Museum Mayer van den Bergh | B79: Musée Mayer van den Bergh | C79: Antwerpen | D79: Beeldende kunst, Geschiedenis en archeologie | E79: =If(IFERROR(SEARCH(E$1, $D79),0) >= 1, true,false) -> TRUE | F79: =If(IFERROR(SEARCH(F$1, $D79),0) >= 1, true,false) -> FALSE | G79: =If(IFERROR(SEARCH(G$1, $D79),0) >= 1, true,false) -> FALSE | H79: =If(IFERROR(SEARCH(H$1, $D79),0) >= 1, true,false) -> FALSE | I79: =If(IFERROR(SEARCH(I$1, $D79),0) >= 1, true,false) -> FALSE | J79: =If(IFERROR(SEARCH(J$1, $D79),0) >= 1, true,false) -> TRUE | K79: =If(IFERROR(SEARCH(K$1, $D79),0) >= 1, true,false) -> FALSE | M79: TRUE | N79: FALSE | O79: FALSE | P79: FALSE | Q79: =IF(ISBLANK(A79),B79,A79) -> Museum Mayer van den Bergh | R79: 10 | S79: TRUE | T79: FALSE
A80: Museum Plantin-Moretus | B80: Musée Plantin-Moretus | C80: Antwerpen | D80: Beeldende kunst, Geschiedenis en archeologie, Wetenschap en technologie, Architectuur, Literatuur | E80: =If(IFERROR(SEARCH(E$1, $D80),0) >= 1, true,false) -> TRUE | F80: =If(IFERROR(SEARCH(F$1, $D80),0) >= 1, true,false) -> TRUE | G80: =If(IFERROR(SEARCH(G$1, $D80),0) >= 1, true,false) -> FALSE | H80: =If(IFERROR(SEARCH(H$1, $D80),0) >= 1, true,false) -> TRUE | I80: =If(IFERROR(SEARCH(I$1, $D80),0) >= 1, true,false) -> TRUE | J80: =If(IFERROR(SEARCH(J$1, $D80),0) >= 1, true,false) -> TRUE | K80: =If(IFERROR(SEARCH(K$1, $D80),0) >= 1, true,false) -> FALSE | M80: TRUE | N80: FALSE | O80: FALSE | P80: FALSE | Q80: =IF(ISBLANK(A80),B80,A80) -> Museum Plantin-Moretus | R80: 12 | S80: FALSE | T80: TRUE | U80: 12
A81: Museum Vleeshuis | B81: Musée Vleeshuis | C81: Antwerpen | D81: Beeldende kunst, Geschiedenis en archeologie, Architectuur | E81: =If(IFERROR(SEARCH(E$1, $D81),0) >= 1, true,false) -> TRUE | F81: =If(IFERROR(SEARCH(F$1, $D81),0) >= 1, true,false) -> FALSE | G81: =If(IFERROR(SEARCH(G$1, $D81),0) >= 1, true,false) -> FALSE | H81: =If(IFERROR(SEARCH(H$1, $D81),0) >= 1, true,false) -> FALSE | I81: =If(IFERROR(SEARCH(I$1, $D81),0) >= 1, true,false) -> TRUE | J81: =If(IFERROR(SEARCH(J$1, $D81),0) >= 1, true,false) -> TRUE | K81: =If(IFERROR(SEARCH(K$1, $D81),0) >= 1, true,false) -> FALSE | M81: TRUE | N81: FALSE | O81: FALSE | P81: FALSE | Q81: =IF(ISBLANK(A81),B81,A81) -> Museum Vleeshuis | R81: 8 | S81: TRUE | T81: FALSE
A82: Nationaal Museum van de Speelkaart | B82: Musée National de la Carte à jouer | C82: Antwerpen | D82: Geschiedenis en archeologie, Wetenschap en technologie | E82: =If(IFERROR(SEARCH(E$1, $D82),0) >= 1, true,false) -> TRUE | F82: =If(IFERROR(SEARCH(F$1, $D82),0) >= 1, true,false) -> TRUE | G82: =If(IFERROR(SEARCH(G$1, $D82),0) >= 1, true,false) -> FALSE | H82: =If(IFERROR(SEARCH(H$1, $D82),0) >= 1, true,false) -> FALSE | I82: =If(IFERROR(SEARCH(I$1, $D82),0) >= 1, true,false) -> FALSE | J82: =If(IFERROR(SEARCH(J$1, $D82),0) >= 1, true,false) -> FALSE | K82: =If(IFERROR(SEARCH(K$1, $D82),0) >= 1, true,false) -> FALSE | M82: TRUE | N82: TRUE | O82: TRUE | P82: FALSE | Q82: =IF(ISBLANK(A82),B82,A82) -> Nationaal Museum van de Speelkaart | R82: 5 | S82: FALSE | T82: TRUE | U82: 5
A83: Red Star Line Museum | B83: Musée Red Star Line | C83: Antwerpen | D83: Geschiedenis en archeologie | E83: =If(IFERROR(SEARCH(E$1, $D83),0) >= 1, true,false) -> TRUE | F83: =If(IFERROR(SEARCH(F$1, $D83),0) >= 1, true,false) -> FALSE | G83: =If(IFERROR(SEARCH(G$1, $D83),0) >= 1, true,false) -> FALSE | H83: =If(IFERROR(SEARCH(H$1, $D83),0) >= 1, true,false) -> FALSE | I83: =If(IFERROR(SEARCH(I$1, $D83),0) >= 1, true,false) -> FALSE | J83: =If(IFERROR(SEARCH(J$1, $D83),0) >= 1, true,false) -> FALSE | K83: =If(IFERROR(SEARCH(K$1, $D83),0) >= 1, true,false) -> FALSE | M83: TRUE | N83: TRUE | O83: FALSE | P83: FALSE | Q83: =IF(ISBLANK(A83),B83,A83) -> Red Star Line Museum | R83: 10 | S83: FALSE | T83: TRUE | U83: 0
A84: Rubenshuis | B84: Maison Rubens | C84: Antwerpen | D84: Beeldende kunst, Geschiedenis en archeologie | E84: =If(IFERROR(SEARCH(E$1, $D84),0) >= 1, true,false) -> TRUE | F84: =If(IFERROR(SEARCH(F$1, $D84),0) >= 1, true,false) -> FALSE | G84: =If(IFERROR(SEARCH(G$1, $D84),0) >= 1, true,false) -> FALSE | H84: =If(IFERROR(SEARCH(H$1, $D84),0) >= 1, true,false) -> FALSE | I84: =If(IFERROR(SEARCH(I$1, $D84),0) >= 1, true,false) -> FALSE | J84: =If(IFERROR(SEARCH(J$1, $D84),0) >= 1, true,false) -> TRUE | K84: =If(IFERROR(SEARCH(K$1, $D84),0) >= 1, true,false) -> FALSE | M84: TRUE | N84: FALSE | O84: FALSE | P84: FALSE | Q84: =IF(ISBLANK(A84),B84,A84) -> Rubenshuis | R84: 12 | S84: FALSE | T84: TRUE | U84: 12
A85: Sint-Pauluskerk | B85: Église Saint-Paul | C85: Antwerpen | D85: Beeldende kunst, Toegepaste kunst en design, Geschiedenis en archeologie, Architectuur, Mode, Literatuur | E85: =If(IFERROR(SEARCH(E$1, $D85),0) >= 1, true,false) -> TRUE | F85: =If(IFERROR(SEARCH(F$1, $D85),0) >= 1, true,false) -> FALSE | G85: =If(IFERROR(SEARCH(G$1, $D85),0) >= 1, true,false) -> TRUE | H85: =If(IFERROR(SEARCH(H$1, $D85),0) >= 1, true,false) -> TRUE | I85: =If(IFERROR(SEARCH(I$1, $D85),0) >= 1, true,false) -> TRUE | J85: =If(IFERROR(SEARCH(J$1, $D85),0) >= 1, true,false) -> TRUE | K85: =If(IFERROR(SEARCH(K$1, $D85),0) >= 1, true,false) -> TRUE | M85: TRUE | N85: FALSE | O85: FALSE | P85: FALSE | Q85: =IF(ISBLANK(A85),B85,A85) -> Sint-Pauluskerk | R85: 5 | S85: FALSE | T85: TRUE | U85: 5
A86: Speelgoedmuseum | B86: Musée du jouet | C86: Antwerpen | D86: Geschiedenis en archeologie, Wetenschap en technologie | E86: =If(IFERROR(SEARCH(E$1, $D86),0) >= 1, true,false) -> TRUE | F86: =If(IFERROR(SEARCH(F$1, $D86),0) >= 1, true,false) -> TRUE | G86: =If(IFERROR(SEARCH(G$1, $D86),0) >= 1, true,false) -> FALSE | H86: =If(IFERROR(SEARCH(H$1, $D86),0) >= 1, true,false) -> FALSE | I86: =If(IFERROR(SEARCH(I$1, $D86),0) >= 1, true,false) -> FALSE | J86: =If(IFERROR(SEARCH(J$1, $D86),0) >= 1, true,false) -> FALSE | K86: =If(IFERROR(SEARCH(K$1, $D86),0) >= 1, true,false) -> FALSE | M86: TRUE | N86: TRUE | O86: TRUE | P86: FALSE | Q86: =IF(ISBLANK(A86),B86,A86) -> Speelgoedmuseum | R86: 17.5 | S86: FALSE | T86: FALSE
A87: Stadsmuseum Lier | B87: Musée de la Ville de Lier | C87: Antwerpen | D87: Beeldende kunst, Toegepaste kunst en design, Geschiedenis en archeologie, Wetenschap en technologie, Architectuur, Mode, Literatuur | E87: =If(IFERROR(SEARCH(E$1, $D87),0) >= 1, true,false) -> TRUE | F87: =If(IFERROR(SEARCH(F$1, $D87),0) >= 1, true,false) -> TRUE | G87: =If(IFERROR(SEARCH(G$1, $D87),0) >= 1, true,false) -> TRUE | H87: =If(IFERROR(SEARCH(H$1, $D87),0) >= 1, true,false) -> TRUE | I87: =If(IFERROR(SEARCH(I$1, $D87),0) >= 1, true,false) -> TRUE | J87: =If(IFERROR(SEARCH(J$1, $D87),0) >= 1, true,false) -> TRUE | K87: =If(IFERROR(SEARCH(K$1, $D87),0) >= 1, true,false) -> TRUE | M87: TRUE | N87: FALSE | O87: FALSE | P87: FALSE | Q87: =IF(ISBLANK(A87),B87,A87) -> Stadsmuseum Lier | R87: 4 | S87: FALSE | T87: TRUE | U87: 4
A88: Stedelijk Museum Hoogstraten | B88: Musée Municipal de Hoogstraten | C88: Antwerpen | D88: Beeldende kunst, Geschiedenis en archeologie | E88: =If(IFERROR(SEARCH(E$1, $D88),0) >= 1, true,false) -> TRUE | F88: =If(IFERROR(SEARCH(F$1, $D88),0) >= 1, true,false) -> FALSE | G88: =If(IFERROR(SEARCH(G$1, $D88),0) >= 1, true,false) -> FALSE | H88: =If(IFERROR(SEARCH(H$1, $D88),0) >= 1, true,false) -> FALSE | I88: =If(IFERROR(SEARCH(I$1, $D88),0) >= 1, true,false) -> FALSE | J88: =If(IFERROR(SEARCH(J$1, $D88),0) >= 1, true,false) -> TRUE | K88: =If(IFERROR(SEARCH(K$1, $D88),0) >= 1, true,false) -> FALSE | M88: TRUE | N88: FALSE | O88: FALSE | P88: FALSE | Q88: =IF(ISBLANK(A88),B88,A88) -> Stedelijk Museum Hoogstraten | R88: 0 | S88: FALSE | T88: TRUE | U88: 0
A89: Suske en Wiske Museum | B89: Musée Bob et Bobette | C89: Antwerpen | D89: Geschiedenis en archeologie, Literatuur | E89: =If(IFERROR(SEARCH(E$1, $D89),0) >= 1, true,false) -> TRUE | F89: =If(IFERROR(SEARCH(F$1, $D89),0) >= 1, true,false) -> FALSE | G89: =If(IFERROR(SEARCH(G$1, $D89),0) >= 1, true,false) -> FALSE | H89: =If(IFERROR(SEARCH(H$1, $D89),0) >= 1, true,false) -> TRUE | I89: =If(IFERROR(SEARCH(I$1, $D89),0) >= 1, true,false) -> FALSE | J89: =If(IFERROR(SEARCH(J$1, $D89),0) >= 1, true,false) -> FALSE | K89: =If(IFERROR(SEARCH(K$1, $D89),0) >= 1, true,false) -> FALSE | M89: TRUE | N89: TRUE | O89: TRUE | P89: FALSE | Q89: =IF(ISBLANK(A89),B89,A89) -> Suske en Wiske Museum | R89: 15 | S89: FALSE | T89: FALSE
A90: Taxandriamuseum | C90: Antwerpen | D90: Beeldende kunst, Geschiedenis en archeologie, Architectuur | E90: =If(IFERROR(SEARCH(E$1, $D90),0) >= 1, true,false) -> TRUE | F90: =If(IFERROR(SEARCH(F$1, $D90),0) >= 1, true,false) -> FALSE | G90: =If(IFERROR(SEARCH(G$1, $D90),0) >= 1, true,false) -> FALSE | H90: =If(IFERROR(SEARCH(H$1, $D90),0) >= 1, true,false) -> FALSE | I90: =If(IFERROR(SEARCH(I$1, $D90),0) >= 1, true,false) -> TRUE | J90: =If(IFERROR(SEARCH(J$1, $D90),0) >= 1, true,false) -> TRUE | K90: =If(IFERROR(SEARCH(K$1, $D90),0) >= 1, true,false) -> FALSE | M90: TRUE | N90: TRUE | O90: FALSE | P90: FALSE | Q90: =IF(ISBLANK(A90),B90,A90) -> Taxandriamuseum | R90: 5 | S90: FALSE | T90: TRUE | U90: 5
A91: ‘t Grom | C91: Antwerpen | D91: Geschiedenis en archeologie, Wetenschap en technologie | E91: =If(IFERROR(SEARCH(E$1, $D91),0) >= 1, true,false) -> TRUE | F91: =If(IFERROR(SEARCH(F$1, $D91),0) >= 1, true,false) -> TRUE | G91: =If(IFERROR(SEARCH(G$1, $D91),0) >= 1, true,false) -> FALSE | H91: =If(IFERROR(SEARCH(H$1, $D91),0) >= 1, true,false) -> FALSE | I91: =If(IFERROR(SEARCH(I$1, $D91),0) >= 1, true,false) -> FALSE | J91: =If(IFERROR(SEARCH(J$1, $D91),0) >= 1, true,false) -> FALSE | K91: =If(IFERROR(SEARCH(K$1, $D91),0) >= 1, true,false) -> FALSE | M91: TRUE | N91: TRUE | O91: TRUE | P91: TRUE | Q91: =IF(ISBLANK(A91),B91,A91) -> ‘t Grom | R91: 7 | S91: FALSE | T91: TRUE | U91: 7
A92: Het steen, The Antwerp Story | C92: Antwerpen | D92: Toegepaste kunst en design, Geschiedenis en archeologie, Wetenschap en technologie, Architectuur, Mode | E92: =If(IFERROR(SEARCH(E$1, $D92),0) >= 1, true,false) -> TRUE | F92: =If(IFERROR(SEARCH(F$1, $D92),0) >= 1, true,false) -> TRUE | G92: =If(IFERROR(SEARCH(G$1, $D92),0) >= 1, true,false) -> TRUE | H92: =If(IFERROR(SEARCH(H$1, $D92),0) >= 1, true,false) -> FALSE | I92: =If(IFERROR(SEARCH(I$1, $D92),0) >= 1, true,false) -> TRUE | J92: =If(IFERROR(SEARCH(J$1, $D92),0) >= 1, true,false) -> FALSE | K92: =If(IFERROR(SEARCH(K$1, $D92),0) >= 1, true,false) -> TRUE | M92: TRUE | N92: FALSE | O92: FALSE | P92: FALSE | Q92: =IF(ISBLANK(A92),B92,A92) -> Het steen, The Antwerp Story | R92: 7 | S92: FALSE | T92: TRUE | U92: 7
A93: Stichting Folon | B93: Fondation Folon | C93: Waals-Brabant | D93: Beeldende kunst | E93: =If(IFERROR(SEARCH(E$1, $D93),0) >= 1, true,false) -> FALSE | F93: =If(IFERROR(SEARCH(F$1, $D93),0) >= 1, true,false) -> FALSE | G93: =If(IFERROR(SEARCH(G$1, $D93),0) >= 1, true,false) -> FALSE | H93: =If(IFERROR(SEARCH(H$1, $D93),0) >= 1, true,false) -> FALSE | I93: =If(IFERROR(SEARCH(I$1, $D93),0) >= 1, true,false) -> FALSE | J93: =If(IFERROR(SEARCH(J$1, $D93),0) >= 1, true,false) -> TRUE | K93: =If(IFERROR(SEARCH(K$1, $D93),0) >= 1, true,false) -> FALSE | M93: TRUE | N93: TRUE | O93: TRUE | P93: TRUE | Q93: =IF(ISBLANK(A93),B93,A93) -> Stichting Folon | R93: 12 | S93: FALSE | T93: TRUE | U93: 10
A94: Hergé Museum | B94: Musée Hergé | C94: Waals-Brabant | D94: Beeldende kunst | E94: =If(IFERROR(SEARCH(E$1, $D94),0) >= 1, true,false) -> FALSE | F94: =If(IFERROR(SEARCH(F$1, $D94),0) >= 1, true,false) -> FALSE | G94: =If(IFERROR(SEARCH(G$1, $D94),0) >= 1, true,false) -> FALSE | H94: =If(IFERROR(SEARCH(H$1, $D94),0) >= 1, true,false) -> FALSE | I94: =If(IFERROR(SEARCH(I$1, $D94),0) >= 1, true,false) -> FALSE | J94: =If(IFERROR(SEARCH(J$1, $D94),0) >= 1, true,false) -> TRUE | K94: =If(IFERROR(SEARCH(K$1, $D94),0) >= 1, true,false) -> FALSE | M94: TRUE | N94: TRUE | O94: FALSE | P94: TRUE | Q94: =IF(ISBLANK(A94),B94,A94) -> Hergé Museum | R94: 12 | S94: FALSE | T94: TRUE | U94: 12
B95: Musée L | C95: Waals-Brabant | D95: Beeldende kunst | E95: =If(IFERROR(SEARCH(E$1, $D95),0) >= 1, true,false) -> FALSE | F95: =If(IFERROR(SEARCH(F$1, $D95),0) >= 1, true,false) -> FALSE | G95: =If(IFERROR(SEARCH(G$1, $D95),0) >= 1, true,false) -> FALSE | H95: =If(IFERROR(SEARCH(H$1, $D95),0) >= 1, true,false) -> FALSE | I95: =If(IFERROR(SEARCH(I$1, $D95),0) >= 1, true,false) -> FALSE | J95: =If(IFERROR(SEARCH(J$1, $D95),0) >= 1, true,false) -> TRUE | K95: =If(IFERROR(SEARCH(K$1, $D95),0) >= 1, true,false) -> FALSE | M95: TRUE | N95: TRUE | O95: TRUE | P95: TRUE | Q95: =IF(ISBLANK(A95),B95,A95) -> Musée L | R95: 8 | S95: FALSE | T95: TRUE | U95: 8
A96: Marthe Donas museum | B96: MiMDo - Musée Marthe Donas | C96: Waals-Brabant | D96: Beeldende kunst | E96: =If(IFERROR(SEARCH(E$1, $D96),0) >= 1, true,false) -> FALSE | F96: =If(IFERROR(SEARCH(F$1, $D96),0) >= 1, true,false) -> FALSE | G96: =If(IFERROR(SEARCH(G$1, $D96),0) >= 1, true,false) -> FALSE | H96: =If(IFERROR(SEARCH(H$1, $D96),0) >= 1, true,false) -> FALSE | I96: =If(IFERROR(SEARCH(I$1, $D96),0) >= 1, true,false) -> FALSE | J96: =If(IFERROR(SEARCH(J$1, $D96),0) >= 1, true,false) -> TRUE | K96: =If(IFERROR(SEARCH(K$1, $D96),0) >= 1, true,false) -> FALSE | M96: TRUE | N96: FALSE | O96: TRUE | P96: FALSE | Q96: =IF(ISBLANK(A96),B96,A96) -> Marthe Donas museum | R96: 2 | S96: FALSE | T96: TRUE | U96: 2
A97: Wellington Museum | B97: Musée Wellington | C97: Waals-Brabant | D97: Geschiedenis en archeologie | E97: =If(IFERROR(SEARCH(E$1, $D97),0) >= 1, true,false) -> TRUE | F97: =If(IFERROR(SEARCH(F$1, $D97),0) >= 1, true,false) -> FALSE | G97: =If(IFERROR(SEARCH(G$1, $D97),0) >= 1, true,false) -> FALSE | H97: =If(IFERROR(SEARCH(H$1, $D97),0) >= 1, true,false) -> FALSE | I97: =If(IFERROR(SEARCH(I$1, $D97),0) >= 1, true,false) -> FALSE | J97: =If(IFERROR(SEARCH(J$1, $D97),0) >= 1, true,false) -> FALSE | K97: =If(IFERROR(SEARCH(K$1, $D97),0) >= 1, true,false) -> FALSE | M97: TRUE | N97: FALSE | O97: FALSE | P97: FALSE | Q97: =IF(ISBLANK(A97),B97,A97) -> Wellington Museum | R97: 10 | S97: FALSE | T97: TRUE | U97: 8
A98: AfricaMuseum | C98: Vlaams-Brabant | D98: Beeldende kunst, Geschiedenis en archeologie, Wetenschap en technologie | E98: =If(IFERROR(SEARCH(E$1, $D98),0) >= 1, true,false) -> TRUE | F98: =If(IFERROR(SEARCH(F$1, $D98),0) >= 1, true,false) -> TRUE | G98: =If(IFERROR(SEARCH(G$1, $D98),0) >= 1, true,false) -> FALSE | H98: =If(IFERROR(SEARCH(H$1, $D98),0) >= 1, true,false) -> FALSE | I98: =If(IFERROR(SEARCH(I$1, $D98),0) >= 1, true,false) -> FALSE | J98: =If(IFERROR(SEARCH(J$1, $D98),0) >= 1, true,false) -> TRUE | K98: =If(IFERROR(SEARCH(K$1, $D98),0) >= 1, true,false) -> FALSE | M98: TRUE | N98: TRUE | O98: TRUE | P98: TRUE | Q98: =IF(ISBLANK(A98),B98,A98) -> AfricaMuseum | R98: 13 | S98: FALSE | T98: TRUE | U98: 13
A99: Damiaanmuseum | B99: Musée Damien | C99: Vlaams-Brabant | D99: Geschiedenis en archeologie | E99: =If(IFERROR(SEARCH(E$1, $D99),0) >= 1, true,false) -> TRUE | F99: =If(IFERROR(SEARCH(F$1, $D99),0) >= 1, true,false) -> FALSE | G99: =If(IFERROR(SEARCH(G$1, $D99),0) >= 1, true,false) -> FALSE | H99: =If(IFERROR(SEARCH(H$1, $D99),0) >= 1, true,false) -> FALSE | I99: =If(IFERROR(SEARCH(I$1, $D99),0) >= 1, true,false) -> FALSE | J99: =If(IFERROR(SEARCH(J$1, $D99),0) >= 1, true,false) -> FALSE | K99: =If(IFERROR(SEARCH(K$1, $D99),0) >= 1, true,false) -> FALSE | M99: TRUE | N99: FALSE | O99: TRUE | P99: FALSE | Q99: =IF(ISBLANK(A99),B99,A99) -> Damiaanmuseum | R99: 7 | S99: FALSE | T99: FALSE
A100: Dru!f, huis van de tafeldruif | B100: maison du raisin de table | C100: Vlaams-Brabant | D100: Beeldende kunst, Geschiedenis en archeologie | E100: =If(IFERROR(SEARCH(E$1, $D100),0) >= 1, true,false) -> TRUE | F100: =If(IFERROR(SEARCH(F$1, $D100),0) >= 1, true,false) -> FALSE | G100: =If(IFERROR(SEARCH(G$1, $D100),0) >= 1, true,false) -> FALSE | H100: =If(IFERROR(SEARCH(H$1, $D100),0) >= 1, true,false) -> FALSE | I100: =If(IFERROR(SEARCH(I$1, $D100),0) >= 1, true,false) -> FALSE | J100: =If(IFERROR(SEARCH(J$1, $D100),0) >= 1, true,false) -> TRUE | K100: =If(IFERROR(SEARCH(K$1, $D100),0) >= 1, true,false) -> FALSE | M100: TRUE | N100: FALSE | O100: FALSE | P100: TRUE | Q100: =IF(ISBLANK(A100),B100,A100) -> Dru!f, huis van de tafeldruif | R100: 0 | S100: FALSE | T100: TRUE | U100: 0
...

Sheet Blad14
A1: Musea - Nederlandse benaming (Title) | B1: Musea - Franse benaming (Alternative Title) | C1: Provincie | D1: Alle Thema's | E1: Geschiedenis en archeologie | F1: Wetenschap en technologie | G1: Mode | H1: Literatuur | I1: Architectuur | J1: Beeldende kunst | K1: Toegepaste kunst en design | M1: Shop | N1: Café | O1: Parking | P1: Restaurant | Q1: Algemene naam --> als geen NL naam dan FR | R1: Prijs | S1: Tijdelijk gesloten | T1: Tijdelijke tentoonstelling(en) | U1: Prijs incl. tijdelijke tentoonstelling | X1: # Museums | Y1: Average Price | Z1: Median
A2: Archeologisch museum van de Boven-Maas | B2: Musée archéologique de la Haute-Meuse | C2: Namen | D2: Geschiedenis en archeologie | E2: =IF(IFERROR(SEARCH(E$1, $D2),0) >= 1, TRUE,FALSE) -> TRUE | F2: =IF(IFERROR(SEARCH(F$1, $D2),0) >= 1, TRUE,FALSE) -> FALSE | G2: =IF(IFERROR(SEARCH(G$1, $D2),0) >= 1, TRUE,FALSE) -> FALSE | H2: =IF(IFERROR(SEARCH(H$1, $D2),0) >= 1, TRUE,FALSE) -> FALSE | I2: =IF(IFERROR(SEARCH(I$1, $D2),0) >= 1, TRUE,FALSE) -> FALSE | J2: =IF(IFERROR(SEARCH(J$1, $D2),0) >= 1, TRUE,FALSE) -> FALSE | K2: =IF(IFERROR(SEARCH(K$1, $D2),0) >= 1, TRUE,FALSE) -> FALSE | M2: TRUE | N2: FALSE | O2: TRUE | P2: FALSE | Q2: =IF(ISBLANK(A2),B2,A2) -> Archeologisch museum van de Boven-Maas | R2: 3.5 | S2: FALSE | T2: FALSE | W2: Namen | X2: =COUNTIF(C:C, "Namen") -> 15 | Y2: =AVERAGEIF(C:C, "Namen",R:R) -> 5.9666667 | Z2: =MEDIAN(R2:R16) -> 6
A3: Citadel van Namen / Bezoekerscentrum Terra Nova en toeristentreintje | B3: =IFERROR(__xludf.DUMMYFUNCTION("SPLIT(A3, "" - "", FALSE,FALSE)"),"Citadel van Namen / Bezoekerscentrum Terra Nova en toeristentreintje") -> Citadel van Namen / Bezoekerscentrum Terra Nova en toeristentreintje | C3: Namen | D3: Geschiedenis en archeologie | E3: =IF(IFERROR(SEARCH(E$1, $D3),0) >= 1, TRUE,FALSE) -> TRUE | F3: =IF(IFERROR(SEARCH(F$1, $D3),0) >= 1, TRUE,FALSE) -> FALSE | G3: =IF(IFERROR(SEARCH(G$1, $D3),0) >= 1, TRUE,FALSE) -> FALSE | H3: =IF(IFERROR(SEARCH(H$1, $D3),0) >= 1, TRUE,FALSE) -> FALSE | I3: =IF(IFERROR(SEARCH(I$1, $D3),0) >= 1, TRUE,FALSE) -> FALSE | J3: =IF(IFERROR(SEARCH(J$1, $D3),0) >= 1, TRUE,FALSE) -> FALSE | K3: =IF(IFERROR(SEARCH(K$1, $D3),0) >= 1, TRUE,FALSE) -> FALSE | M3: TRUE | N3: TRUE | O3: FALSE | P3: FALSE | Q3: =IF(ISBLANK(A3),B3,A3) -> Citadel van Namen / Bezoekerscentrum Terra Nova en toeristentreintje | R3: 6 | S3: FALSE | T3: FALSE | W3: West-Vlaanderen | X3: =COUNTIF(C:C, "West-Vlaanderen") -> 41 | Y3: =AVERAGEIF(C:C, "West-Vlaanderen",R:R) -> 9.1463415 | Z3: =MEDIAN(R17:R57) -> 9
A4: NAM-IP Computermuseum | B4: Computer Museum NAM-IP | C4: Namen | D4: Wetenschap en technologie | E4: =IF(IFERROR(SEARCH(E$1, $D4),0) >= 1, TRUE,FALSE) -> FALSE | F4: =IF(IFERROR(SEARCH(F$1, $D4),0) >= 1, TRUE,FALSE) -> TRUE | G4: =IF(IFERROR(SEARCH(G$1, $D4),0) >= 1, TRUE,FALSE) -> FALSE | H4: =IF(IFERROR(SEARCH(H$1, $D4),0) >= 1, TRUE,FALSE) -> FALSE | I4: =IF(IFERROR(SEARCH(I$1, $D4),0) >= 1, TRUE,FALSE) -> FALSE | J4: =IF(IFERROR(SEARCH(J$1, $D4),0) >= 1, TRUE,FALSE) -> FALSE | K4: =IF(IFERROR(SEARCH(K$1, $D4),0) >= 1, TRUE,FALSE) -> FALSE | M4: TRUE | N4: TRUE | O4: TRUE | P4: FALSE | Q4: =IF(ISBLANK(A4),B4,A4) -> NAM-IP Computermuseum | R4: 8 | S4: FALSE | T4: FALSE | W4: Antwerpen | X4: 35 | Y4: =AVERAGE($R$58:$R$91) -> 9.25 | Z4: =MEDIAN($R$58:$R$91) -> 10
A5: Ecomuseum van de Viroin | B5: Écomusée du Viroin | C5: Namen | D5: Geschiedenis en archeologie | E5: =IF(IFERROR(SEARCH(E$1, $D5),0) >= 1, TRUE,FALSE) -> TRUE | F5: =IF(IFERROR(SEARCH(F$1, $D5),0) >= 1, TRUE,FALSE) -> FALSE | G5: =IF(IFERROR(SEARCH(G$1, $D5),0) >= 1, TRUE,FALSE) -> FALSE | H5: =IF(IFERROR(SEARCH(H$1, $D5),0) >= 1, TRUE,FALSE) -> FALSE | I5: =IF(IFERROR(SEARCH(I$1, $D5),0) >= 1, TRUE,FALSE) -> FALSE | J5: =IF(IFERROR(SEARCH(J$1, $D5),0) >= 1, TRUE,FALSE) -> FALSE | K5: =IF(IFERROR(SEARCH(K$1, $D5),0) >= 1, TRUE,FALSE) -> FALSE | M5: TRUE | N5: FALSE | O5: FALSE | P5: FALSE | Q5: =IF(ISBLANK(A5),B5,A5) -> Ecomuseum van de Viroin | R5: 4 | S5: FALSE | T5: TRUE | U5: 4 | W5: Waals-Brabant | X5: 5 | Y5: =AVERAGE($R$93:$R$97) -> 8.8 | Z5: =MEDIAN($R$93:$R$97) -> 10
A6: Andenne Museum | B6: Espace Muséal d’Andenne | C6: Namen | D6: Toegepaste kunst en design, Geschiedenis en archeologie | E6: =IF(IFERROR(SEARCH(E$1, $D6),0) >= 1, TRUE,FALSE) -> TRUE | F6: =IF(IFERROR(SEARCH(F$1, $D6),0) >= 1, TRUE,FALSE) -> FALSE | G6: =IF(IFERROR(SEARCH(G$1, $D6),0) >= 1, TRUE,FALSE) -> FALSE | H6: =IF(IFERROR(SEARCH(H$1, $D6),0) >= 1, TRUE,FALSE) -> FALSE | I6: =IF(IFERROR(SEARCH(I$1, $D6),0) >= 1, TRUE,FALSE) -> FALSE | J6: =IF(IFERROR(SEARCH(J$1, $D6),0) >= 1, TRUE,FALSE) -> FALSE | K6: =IF(IFERROR(SEARCH(K$1, $D6),0) >= 1, TRUE,FALSE) -> TRUE | M6: TRUE | N6: FALSE | O6: FALSE | P6: FALSE | Q6: =IF(ISBLANK(A6),B6,A6) -> Andenne Museum | R6: 10 | S6: FALSE | T6: FALSE | W6: Vlaams-Brabant | X6: 13 | Y6: =AVERAGE($R$98:$R$110) -> 8.1923077 | Z6: =MEDIAN($R$98:$R$110) -> 10
B7: Le Delta | C7: Namen | D7: Beeldende kunst | E7: =IF(IFERROR(SEARCH(E$1, $D7),0) >= 1, TRUE,FALSE) -> FALSE | F7: =IF(IFERROR(SEARCH(F$1, $D7),0) >= 1, TRUE,FALSE) -> FALSE | G7: =IF(IFERROR(SEARCH(G$1, $D7),0) >= 1, TRUE,FALSE) -> FALSE | H7: =IF(IFERROR(SEARCH(H$1, $D7),0) >= 1, TRUE,FALSE) -> FALSE | I7: =IF(IFERROR(SEARCH(I$1, $D7),0) >= 1, TRUE,FALSE) -> FALSE | J7: =IF(IFERROR(SEARCH(J$1, $D7),0) >= 1, TRUE,FALSE) -> TRUE | K7: =IF(IFERROR(SEARCH(K$1, $D7),0) >= 1, TRUE,FALSE) -> FALSE | M7: TRUE | N7: FALSE | O7: FALSE | P7: TRUE | Q7: =IF(ISBLANK(A7),B7,A7) -> Le Delta | R7: 5 | S7: FALSE | T7: TRUE | U7: 5 | W7: Limburg | X7: =COUNTIF(C:C, "Limburg") -> 15 | Y7: =AVERAGEIF(C:C, "Limburg",R:R) -> 8.3333333 | Z7: =MEDIAN(R111,R125) -> 9
B8: Le Pavillon | C8: Namen | D8: Beeldende kunst, Wetenschap en technologie | E8: =IF(IFERROR(SEARCH(E$1, $D8),0) >= 1, TRUE,FALSE) -> FALSE | F8: =IF(IFERROR(SEARCH(F$1, $D8),0) >= 1, TRUE,FALSE) -> TRUE | G8: =IF(IFERROR(SEARCH(G$1, $D8),0) >= 1, TRUE,FALSE) -> FALSE | H8: =IF(IFERROR(SEARCH(H$1, $D8),0) >= 1, TRUE,FALSE) -> FALSE | I8: =IF(IFERROR(SEARCH(I$1, $D8),0) >= 1, TRUE,FALSE) -> FALSE | J8: =IF(IFERROR(SEARCH(J$1, $D8),0) >= 1, TRUE,FALSE) -> TRUE | K8: =IF(IFERROR(SEARCH(K$1, $D8),0) >= 1, TRUE,FALSE) -> FALSE | M8: TRUE | N8: FALSE | O8: FALSE | P8: FALSE | Q8: =IF(ISBLANK(A8),B8,A8) -> Le Pavillon | R8: 10 | S8: FALSE | T8: TRUE | U8: 10 | W8: Luik | X8: =COUNTIF(C:C, "Luik") -> 19 | Y8: =AVERAGEIF(C:C, "Luik",R:R) -> 6.6315789 | Z8: =MEDIAN(R126,R144) -> 10.5
B9: Maison du patrimoine médiéval mosan | C9: Namen | D9: Geschiedenis en archeologie | E9: =IF(IFERROR(SEARCH(E$1, $D9),0) >= 1, TRUE,FALSE) -> TRUE | F9: =IF(IFERROR(SEARCH(F$1, $D9),0) >= 1, TRUE,FALSE) -> FALSE | G9: =IF(IFERROR(SEARCH(G$1, $D9),0) >= 1, TRUE,FALSE) -> FALSE | H9: =IF(IFERROR(SEARCH(H$1, $D9),0) >= 1, TRUE,FALSE) -> FALSE | I9: =IF(IFERROR(SEARCH(I$1, $D9),0) >= 1, TRUE,FALSE) -> FALSE | J9: =IF(IFERROR(SEARCH(J$1, $D9),0) >= 1, TRUE,FALSE) -> FALSE | K9: =IF(IFERROR(SEARCH(K$1, $D9),0) >= 1, TRUE,FALSE) -> FALSE | M9: TRUE | N9: FALSE | O9: TRUE | P9: FALSE | Q9: =IF(ISBLANK(A9),B9,A9) -> Maison du patrimoine médiéval mosan | R9: 6 | S9: FALSE | T9: TRUE | U9: 6 | W9: Henegouwen | X9: =COUNTIF(C:C,"Henegouwen") -> 37 | Y9: =AVERAGEIF(C:C,"Henegouwen",R:R) -> 6.5405405 | Z9: =MEDIAN(R145:R181) -> 6
A10: Archeopark van Rochefort | B10: Malagne | Archéoparc de Rochefort | C10: Namen | D10: Geschiedenis en archeologie | E10: =IF(IFERROR(SEARCH(E$1, $D10),0) >= 1, TRUE,FALSE) -> TRUE | F10: =IF(IFERROR(SEARCH(F$1, $D10),0) >= 1, TRUE,FALSE) -> FALSE | G10: =IF(IFERROR(SEARCH(G$1, $D10),0) >= 1, TRUE,FALSE) -> FALSE | H10: =IF(IFERROR(SEARCH(H$1, $D10),0) >= 1, TRUE,FALSE) -> FALSE | I10: =IF(IFERROR(SEARCH(I$1, $D10),0) >= 1, TRUE,FALSE) -> FALSE | J10: =IF(IFERROR(SEARCH(J$1, $D10),0) >= 1, TRUE,FALSE) -> FALSE | K10: =IF(IFERROR(SEARCH(K$1, $D10),0) >= 1, TRUE,FALSE) -> FALSE | M10: TRUE | N10: TRUE | O10: TRUE | P10: FALSE | Q10: =IF(ISBLANK(A10),B10,A10) -> Archeopark van Rochefort | R10: 8 | S10: FALSE | T10: FALSE | W10: Luxemburg | X10: =COUNTIF(C:C,"Luxemburg") -> 9 | Y10: =AVERAGEIF(C:C,"Luxemburg",R:R) -> 7.0555556 | Z10: =MEDIAN(R182,R190) -> 10.5
A11: MusAfrica Namen | B11: MusAfrica Namur | C11: Namen | D11: Toegepaste kunst en design, Geschiedenis en archeologie | E11: =IF(IFERROR(SEARCH(E$1, $D11),0) >= 1, TRUE,FALSE) -> TRUE | F11: =IF(IFERROR(SEARCH(F$1, $D11),0) >= 1, TRUE,FALSE) -> FALSE | G11: =IF(IFERROR(SEARCH(G$1, $D11),0) >= 1, TRUE,FALSE) -> FALSE | H11: =IF(IFERROR(SEARCH(H$1, $D11),0) >= 1, TRUE,FALSE) -> FALSE | I11: =IF(IFERROR(SEARCH(I$1, $D11),0) >= 1, TRUE,FALSE) -> FALSE | J11: =IF(IFERROR(SEARCH(J$1, $D11),0) >= 1, TRUE,FALSE) -> FALSE | K11: =IF(IFERROR(SEARCH(K$1, $D11),0) >= 1, TRUE,FALSE) -> TRUE | M11: TRUE | N11: FALSE | O11: FALSE | P11: FALSE | Q11: =IF(ISBLANK(A11),B11,A11) -> MusAfrica Namen | R11: 8 | S11: FALSE | T11: FALSE | W11: Brussel | X11: =COUNTIF(C2:C261,"Brussel") -> 48 | Y11: =AVERAGE(R191:R238) -> 9.1875 | Z11: =MEDIAN(R191:R238) -> 10
A12: Aardbeimuseum | B12: Musée de la Fraise | C12: Namen | D12: Beeldende kunst, Geschiedenis en archeologie, Wetenschap en technologie | E12: =IF(IFERROR(SEARCH(E$1, $D12),0) >= 1, TRUE,FALSE) -> TRUE | F12: =IF(IFERROR(SEARCH(F$1, $D12),0) >= 1, TRUE,FALSE) -> TRUE | G12: =IF(IFERROR(SEARCH(G$1, $D12),0) >= 1, TRUE,FALSE) -> FALSE | H12: =IF(IFERROR(SEARCH(H$1, $D12),0) >= 1, TRUE,FALSE) -> FALSE | I12: =IF(IFERROR(SEARCH(I$1, $D12),0) >= 1, TRUE,FALSE) -> FALSE | J12: =IF(IFERROR(SEARCH(J$1, $D12),0) >= 1, TRUE,FALSE) -> TRUE | K12: =IF(IFERROR(SEARCH(K$1, $D12),0) >= 1, TRUE,FALSE) -> FALSE | M12: TRUE | N12: FALSE | O12: FALSE | P12: FALSE | Q12: =IF(ISBLANK(A12),B12,A12) -> Aardbeimuseum | R12: 6 | S12: FALSE | T12: FALSE | W12: Oost-Vlaanderen | X12: =COUNTIF(C2:C261,"Oost-Vlaanderen") -> 23 | Y12: =AVERAGE(R239:R261) -> 8.5652174 | Z12: =MEDIAN(R239:R261) -> 9
B13: Musée du Malgré-Tout | C13: Namen | D13: Geschiedenis en archeologie | E13: =IF(IFERROR(SEARCH(E$1, $D13),0) >= 1, TRUE,FALSE) -> TRUE | F13: =IF(IFERROR(SEARCH(F$1, $D13),0) >= 1, TRUE,FALSE) -> FALSE | G13: =IF(IFERROR(SEARCH(G$1, $D13),0) >= 1, TRUE,FALSE) -> FALSE | H13: =IF(IFERROR(SEARCH(H$1, $D13),0) >= 1, TRUE,FALSE) -> FALSE | I13: =IF(IFERROR(SEARCH(I$1, $D13),0) >= 1, TRUE,FALSE) -> FALSE | J13: =IF(IFERROR(SEARCH(J$1, $D13),0) >= 1, TRUE,FALSE) -> FALSE | K13: =IF(IFERROR(SEARCH(K$1, $D13),0) >= 1, TRUE,FALSE) -> FALSE | M13: TRUE | N13: FALSE | O13: FALSE | P13: FALSE | Q13: =IF(ISBLANK(A13),B13,A13) -> Musée du Malgré-Tout | R13: 5 | S13: FALSE | T13: FALSE
A14: Museum van het Klein Formaat | B14: Musée du Petit Format | C14: Namen | D14: Beeldende kunst | E14: =IF(IFERROR(SEARCH(E$1, $D14),0) >= 1, TRUE,FALSE) -> FALSE | F14: =IF(IFERROR(SEARCH(F$1, $D14),0) >= 1, TRUE,FALSE) -> FALSE | G14: =IF(IFERROR(SEARCH(G$1, $D14),0) >= 1, TRUE,FALSE) -> FALSE | H14: =IF(IFERROR(SEARCH(H$1, $D14),0) >= 1, TRUE,FALSE) -> FALSE | I14: =IF(IFERROR(SEARCH(I$1, $D14),0) >= 1, TRUE,FALSE) -> FALSE | J14: =IF(IFERROR(SEARCH(J$1, $D14),0) >= 1, TRUE,FALSE) -> TRUE | K14: =IF(IFERROR(SEARCH(K$1, $D14),0) >= 1, TRUE,FALSE) -> FALSE | M14: TRUE | N14: FALSE | O14: FALSE | P14: FALSE | Q14: =IF(ISBLANK(A14),B14,A14) -> Museum van het Klein Formaat | R14: 5 | S14: FALSE | T14: TRUE | U14: 5
A15: Félicien Rops Museum | B15: Musée Félicien Rops | C15: Namen | D15: Beeldende kunst | E15: =IF(IFERROR(SEARCH(E$1, $D15),0) >= 1, TRUE,FALSE) -> FALSE | F15: =IF(IFERROR(SEARCH(F$1, $D15),0) >= 1, TRUE,FALSE) -> FALSE | G15: =IF(IFERROR(SEARCH(G$1, $D15),0) >= 1, TRUE,FALSE) -> FALSE | H15: =IF(IFERROR(SEARCH(H$1, $D15),0) >= 1, TRUE,FALSE) -> FALSE | I15: =IF(IFERROR(SEARCH(I$1, $D15),0) >= 1, TRUE,FALSE) -> FALSE | J15: =IF(IFERROR(SEARCH(J$1, $D15),0) >= 1, TRUE,FALSE) -> TRUE | K15: =IF(IFERROR(SEARCH(K$1, $D15),0) >= 1, TRUE,FALSE) -> FALSE | M15: TRUE | N15: FALSE | O15: FALSE | P15: FALSE | Q15: =IF(ISBLANK(A15),B15,A15) -> Félicien Rops Museum | R15: 0 | S15: FALSE | T15: TRUE | U15: 8
A16: Museum voor Oude Kunsten | B16: TreM.a | Musée des Arts anciens | C16: Namen | D16: Beeldende kunst | E16: =IF(IFERROR(SEARCH(E$1, $D16),0) >= 1, TRUE,FALSE) -> FALSE | F16: =IF(IFERROR(SEARCH(F$1, $D16),0) >= 1, TRUE,FALSE) -> FALSE | G16: =IF(IFERROR(SEARCH(G$1, $D16),0) >= 1, TRUE,FALSE) -> FALSE | H16: =IF(IFERROR(SEARCH(H$1, $D16),0) >= 1, TRUE,FALSE) -> FALSE | I16: =IF(IFERROR(SEARCH(I$1, $D16),0) >= 1, TRUE,FALSE) -> FALSE | J16: =IF(IFERROR(SEARCH(J$1, $D16),0) >= 1, TRUE,FALSE) -> TRUE | K16: =IF(IFERROR(SEARCH(K$1, $D16),0) >= 1, TRUE,FALSE) -> FALSE | M16: TRUE | N16: FALSE | O16: FALSE | P16: FALSE | Q16: =IF(ISBLANK(A16),B16,A16) -> Museum voor Oude Kunsten | R16: 5 | S16: FALSE | T16: TRUE | U16: 8
A17: Abdijmuseum Ten Duinen | B17: Musée de l’Abbaye des Dunes | C17: West-Vlaanderen | D17: Geschiedenis en archeologie, Wetenschap en technologie, Architectuur | E17: =IF(IFERROR(SEARCH(E$1, $D17),0) >= 1, TRUE,FALSE) -> TRUE | F17: =IF(IFERROR(SEARCH(F$1, $D17),0) >= 1, TRUE,FALSE) -> TRUE | G17: =IF(IFERROR(SEARCH(G$1, $D17),0) >= 1, TRUE,FALSE) -> FALSE | H17: =IF(IFERROR(SEARCH(H$1, $D17),0) >= 1, TRUE,FALSE) -> FALSE | I17: =IF(IFERROR(SEARCH(I$1, $D17),0) >= 1, TRUE,FALSE) -> TRUE | J17: =IF(IFERROR(SEARCH(J$1, $D17),0) >= 1, TRUE,FALSE) -> FALSE | K17: =IF(IFERROR(SEARCH(K$1, $D17),0) >= 1, TRUE,FALSE) -> FALSE | M17: TRUE | N17: FALSE | O17: TRUE | P17: FALSE | Q17: =IF(ISBLANK(A17),B17,A17) -> Abdijmuseum Ten Duinen | R17: 10 | S17: FALSE | T17: TRUE | U17: 10
A18: Adornesdomein | B18: Le domaine Adornes | C18: West-Vlaanderen | D18: Beeldende kunst, Toegepaste kunst en design, Geschiedenis en archeologie, Architectuur | E18: =IF(IFERROR(SEARCH(E$1, $D18),0) >= 1, TRUE,FALSE) -> TRUE | F18: =IF(IFERROR(SEARCH(F$1, $D18),0) >= 1, TRUE,FALSE) -> FALSE | G18: =IF(IFERROR(SEARCH(G$1, $D18),0) >= 1, TRUE,FALSE) -> FALSE | H18: =IF(IFERROR(SEARCH(H$1, $D18),0) >= 1, TRUE,FALSE) -> FALSE | I18: =IF(IFERROR(SEARCH(I$1, $D18),0) >= 1, TRUE,FALSE) -> TRUE | J18: =IF(IFERROR(SEARCH(J$1, $D18),0) >= 1, TRUE,FALSE) -> TRUE | K18: =IF(IFERROR(SEARCH(K$1, $D18),0) >= 1, TRUE,FALSE) -> TRUE | M18: TRUE | N18: TRUE | O18: FALSE | P18: FALSE | Q18: =IF(ISBLANK(A18),B18,A18) -> Adornesdomein | R18: 10 | S18: FALSE | T18: FALSE
A19: Atlantikwall Raversyde | C19: West-Vlaanderen | D19: Beeldende kunst, Toegepaste kunst en design, Geschiedenis en archeologie, Wetenschap en technologie, Architectuur | E19: =IF(IFERROR(SEARCH(E$1, $D19),0) >= 1, TRUE,FALSE) -> TRUE | F19: =IF(IFERROR(SEARCH(F$1, $D19),0) >= 1, TRUE,FALSE) -> TRUE | G19: =IF(IFERROR(SEARCH(G$1, $D19),0) >= 1, TRUE,FALSE) -> FALSE | H19: =IF(IFERROR(SEARCH(H$1, $D19),0) >= 1, TRUE,FALSE) -> FALSE | I19: =IF(IFERROR(SEARCH(I$1, $D19),0) >= 1, TRUE,FALSE) -> TRUE | J19: =IF(IFERROR(SEARCH(J$1, $D19),0) >= 1, TRUE,FALSE) -> TRUE | K19: =IF(IFERROR(SEARCH(K$1, $D19),0) >= 1, TRUE,FALSE) -> TRUE | M19: TRUE | N19: TRUE | O19: TRUE | P19: TRUE | Q19: =IF(ISBLANK(A19),B19,A19) -> Atlantikwall Raversyde | R19: 10 | S19: FALSE | T19: TRUE | U19: 10
A20: Bakkerijmuseum | B20: Musée de la Boulangerie | C20: West-Vlaanderen | D20: Geschiedenis en archeologie | E20: =IF(IFERROR(SEARCH(E$1, $D20),0) >= 1, TRUE,FALSE) -> TRUE | F20: =IF(IFERROR(SEARCH(F$1, $D20),0) >= 1, TRUE,FALSE) -> FALSE | G20: =IF(IFERROR(SEARCH(G$1, $D20),0) >= 1, TRUE,FALSE) -> FALSE | H20: =IF(IFERROR(SEARCH(H$1, $D20),0) >= 1, TRUE,FALSE) -> FALSE | I20: =IF(IFERROR(SEARCH(I$1, $D20),0) >= 1, TRUE,FALSE) -> FALSE | J20: =IF(IFERROR(SEARCH(J$1, $D20),0) >= 1, TRUE,FALSE) -> FALSE | K20: =IF(IFERROR(SEARCH(K$1, $D20),0) >= 1, TRUE,FALSE) -> FALSE | M20: TRUE | N20: TRUE | O20: TRUE | P20: TRUE | Q20: =IF(ISBLANK(A20),B20,A20) -> Bakkerijmuseum | R20: 8 | S20: FALSE | T20: FALSE
A21: Belfort van Brugge | B21: Beffroi de Bruges | C21: West-Vlaanderen | D21: Geschiedenis en archeologie, Wetenschap en technologie, Architectuur | E21: =IF(IFERROR(SEARCH(E$1, $D21),0) >= 1, TRUE,FALSE) -> TRUE | F21: =IF(IFERROR(SEARCH(F$1, $D21),0) >= 1, TRUE,FALSE) -> TRUE | G21: =IF(IFERROR(SEARCH(G$1, $D21),0) >= 1, TRUE,FALSE) -> FALSE | H21: =IF(IFERROR(SEARCH(H$1, $D21),0) >= 1, TRUE,FALSE) -> FALSE | I21: =IF(IFERROR(SEARCH(I$1, $D21),0) >= 1, TRUE,FALSE) -> TRUE | J21: =IF(IFERROR(SEARCH(J$1, $D21),0) >= 1, TRUE,FALSE) -> FALSE | K21: =IF(IFERROR(SEARCH(K$1, $D21),0) >= 1, TRUE,FALSE) -> FALSE | M21: FALSE | N21: FALSE | O21: FALSE | P21: FALSE | Q21: =IF(ISBLANK(A21),B21,A21) -> Belfort van Brugge | R21: 15 | S21: FALSE | T21: FALSE
A22: Belle Epoque Centrum | B22: Centre Belle Epoque | C22: West-Vlaanderen | D22: Geschiedenis en archeologie | E22: =IF(IFERROR(SEARCH(E$1, $D22),0) >= 1, TRUE,FALSE) -> TRUE | F22: =IF(IFERROR(SEARCH(F$1, $D22),0) >= 1, TRUE,FALSE) -> FALSE | G22: =IF(IFERROR(SEARCH(G$1, $D22),0) >= 1, TRUE,FALSE) -> FALSE | H22: =IF(IFERROR(SEARCH(H$1, $D22),0) >= 1, TRUE,FALSE) -> FALSE | I22: =IF(IFERROR(SEARCH(I$1, $D22),0) >= 1, TRUE,FALSE) -> FALSE | J22: =IF(IFERROR(SEARCH(J$1, $D22),0) >= 1, TRUE,FALSE) -> FALSE | K22: =IF(IFERROR(SEARCH(K$1, $D22),0) >= 1, TRUE,FALSE) -> FALSE | M22: TRUE | N22: FALSE | O22: FALSE | P22: FALSE | Q22: =IF(ISBLANK(A22),B22,A22) -> Belle Epoque Centrum | R22: 5 | S22: FALSE | T22: FALSE
A23: Brugse Vrije | B23: Franc de Bruges | C23: West-Vlaanderen | D23: Beeldende kunst, Toegepaste kunst en design, Geschiedenis en archeologie | E23: =IF(IFERROR(SEARCH(E$1, $D23),0) >= 1, TRUE,FALSE) -> TRUE | F23: =IF(IFERROR(SEARCH(F$1, $D23),0) >= 1, TRUE,FALSE) -> FALSE | G23: =IF(IFERROR(SEARCH(G$1, $D23),0) >= 1, TRUE,FALSE) -> FALSE | H23: =IF(IFERROR(SEARCH(H$1, $D23),0) >= 1, TRUE,FALSE) -> FALSE | I23: =IF(IFERROR(SEARCH(I$1, $D23),0) >= 1, TRUE,FALSE) -> FALSE | J23: =IF(IFERROR(SEARCH(J$1, $D23),0) >= 1, TRUE,FALSE) -> TRUE | K23: =IF(IFERROR(SEARCH(K$1, $D23),0) >= 1, TRUE,FALSE) -> TRUE | M23: FALSE | N23: FALSE | O23: FALSE | P23: FALSE | Q23: =IF(ISBLANK(A23),B23,A23) -> Brugse Vrije | R23: 3 | S23: FALSE | T23: FALSE
A24: Dodengang | B24: Boyau de la Mort | C24: West-Vlaanderen | D24: Geschiedenis en archeologie | E24: =IF(IFERROR(SEARCH(E$1, $D24),0) >= 1, TRUE,FALSE) -> TRUE | F24: =IF(IFERROR(SEARCH(F$1, $D24),0) >= 1, TRUE,FALSE) -> FALSE | G24: =IF(IFERROR(SEARCH(G$1, $D24),0) >= 1, TRUE,FALSE) -> FALSE | H24: =IF(IFERROR(SEARCH(H$1, $D24),0) >= 1, TRUE,FALSE) -> FALSE | I24: =IF(IFERROR(SEARCH(I$1, $D24),0) >= 1, TRUE,FALSE) -> FALSE | J24: =IF(IFERROR(SEARCH(J$1, $D24),0) >= 1, TRUE,FALSE) -> FALSE | K24: =IF(IFERROR(SEARCH(K$1, $D24),0) >= 1, TRUE,FALSE) -> FALSE | M24: FALSE | N24: FALSE | O24: TRUE | P24: FALSE | Q24: =IF(ISBLANK(A24),B24,A24) -> Dodengang | R24: 6 | S24: FALSE | T24: FALSE
B25: Eperon d’Or | C25: West-Vlaanderen | D25: Geschiedenis en archeologie, Wetenschap en technologie, Architectuur, Mode | E25: =IF(IFERROR(SEARCH(E$1, $D25),0) >= 1, TRUE,FALSE) -> TRUE | F25: =IF(IFERROR(SEARCH(F$1, $D25),0) >= 1, TRUE,FALSE) -> TRUE | G25: =IF(IFERROR(SEARCH(G$1, $D25),0) >= 1, TRUE,FALSE) -> TRUE | H25: =IF(IFERROR(SEARCH(H$1, $D25),0) >= 1, TRUE,FALSE) -> FALSE | I25: =IF(IFERROR(SEARCH(I$1, $D25),0) >= 1, TRUE,FALSE) -> TRUE | J25: =IF(IFERROR(SEARCH(J$1, $D25),0) >= 1, TRUE,FALSE) -> FALSE | K25: =IF(IFERROR(SEARCH(K$1, $D25),0) >= 1, TRUE,FALSE) -> FALSE | M25: TRUE | N25: FALSE | O25: TRUE | P25: FALSE | Q25: =IF(ISBLANK(A25),B25,A25) -> Eperon d’Or | R25: 8 | S25: FALSE | T25: TRUE | U25: 8
A26: Gezellehuis | B26: Maison Gezelle | C26: West-Vlaanderen | D26: Literatuur | E26: =IF(IFERROR(SEARCH(E$1, $D26),0) >= 1, TRUE,FALSE) -> FALSE | F26: =IF(IFERROR(SEARCH(F$1, $D26),0) >= 1, TRUE,FALSE) -> FALSE | G26: =IF(IFERROR(SEARCH(G$1, $D26),0) >= 1, TRUE,FALSE) -> FALSE | H26: =IF(IFERROR(SEARCH(H$1, $D26),0) >= 1, TRUE,FALSE) -> TRUE | I26: =IF(IFERROR(SEARCH(I$1, $D26),0) >= 1, TRUE,FALSE) -> FALSE | J26: =IF(IFERROR(SEARCH(J$1, $D26),0) >= 1, TRUE,FALSE) -> FALSE | K26: =IF(IFERROR(SEARCH(K$1, $D26),0) >= 1, TRUE,FALSE) -> FALSE | M26: FALSE | N26: FALSE | O26: FALSE | P26: FALSE | Q26: =IF(ISBLANK(A26),B26,A26) -> Gezellehuis | R26: 0 | S26: FALSE | T26: FALSE
A27: Groeningemuseum | B27: Musée Groeninge | C27: West-Vlaanderen | D27: Beeldende kunst | E27: =IF(IFERROR(SEARCH(E$1, $D27),0) >= 1, TRUE,FALSE) -> FALSE | F27: =IF(IFERROR(SEARCH(F$1, $D27),0) >= 1, TRUE,FALSE) -> FALSE | G27: =IF(IFERROR(SEARCH(G$1, $D27),0) >= 1, TRUE,FALSE) -> FALSE | H27: =IF(IFERROR(SEARCH(H$1, $D27),0) >= 1, TRUE,FALSE) -> FALSE | I27: =IF(IFERROR(SEARCH(I$1, $D27),0) >= 1, TRUE,FALSE) -> FALSE | J27: =IF(IFERROR(SEARCH(J$1, $D27),0) >= 1, TRUE,FALSE) -> TRUE | K27: =IF(IFERROR(SEARCH(K$1, $D27),0) >= 1, TRUE,FALSE) -> FALSE | M27: TRUE | N27: FALSE | O27: FALSE | P27: FALSE | Q27: =IF(ISBLANK(A27),B27,A27) -> Groeningemuseum | R27: 15 | S27: FALSE | T27: FALSE
A28: Gruuthusemuseum | B28: Musée Gruuthuse | C28: West-Vlaanderen | D28: Beeldende kunst, Toegepaste kunst en design, Geschiedenis en archeologie, Architectuur | E28: =IF(IFERROR(SEARCH(E$1, $D28),0) >= 1, TRUE,FALSE) -> TRUE | F28: =IF(IFERROR(SEARCH(F$1, $D28),0) >= 1, TRUE,FALSE) -> FALSE | G28: =IF(IFERROR(SEARCH(G$1, $D28),0) >= 1, TRUE,FALSE) -> FALSE | H28: =IF(IFERROR(SEARCH(H$1, $D28),0) >= 1, TRUE,FALSE) -> FALSE | I28: =IF(IFERROR(SEARCH(I$1, $D28),0) >= 1, TRUE,FALSE) -> TRUE | J28: =IF(IFERROR(SEARCH(J$1, $D28),0) >= 1, TRUE,FALSE) -> TRUE | K28: =IF(IFERROR(SEARCH(K$1, $D28),0) >= 1, TRUE,FALSE) -> TRUE | M28: FALSE | N28: FALSE | O28: FALSE | P28: FALSE | Q28: =IF(ISBLANK(A28),B28,A28) -> Gruuthusemuseum | R28: 15 | S28: FALSE | T28: FALSE
A29: Het James Ensorhuis | B29: La Maison de James Ensor | C29: West-Vlaanderen | D29: Beeldende kunst | E29: =IF(IFERROR(SEARCH(E$1, $D29),0) >= 1, TRUE,FALSE) -> FALSE | F29: =IF(IFERROR(SEARCH(F$1, $D29),0) >= 1, TRUE,FALSE) -> FALSE | G29: =IF(IFERROR(SEARCH(G$1, $D29),0) >= 1, TRUE,FALSE) -> FALSE | H29: =IF(IFERROR(SEARCH(H$1, $D29),0) >= 1, TRUE,FALSE) -> FALSE | I29: =IF(IFERROR(SEARCH(I$1, $D29),0) >= 1, TRUE,FALSE) -> FALSE | J29: =IF(IFERROR(SEARCH(J$1, $D29),0) >= 1, TRUE,FALSE) -> TRUE | K29: =IF(IFERROR(SEARCH(K$1, $D29),0) >= 1, TRUE,FALSE) -> FALSE | M29: TRUE | N29: FALSE | O29: FALSE | P29: FALSE | Q29: =IF(ISBLANK(A29),B29,A29) -> Het James Ensorhuis | R29: 13 | S29: FALSE | T29: TRUE | U29: 13
A30: Het Lijsternest | Streuvelshuis & Schrijversresidentie | C30: West-Vlaanderen | D30: Beeldende kunst, Architectuur, Literatuur | E30: =IF(IFERROR(SEARCH(E$1, $D30),0) >= 1, TRUE,FALSE) -> FALSE | F30: =IF(IFERROR(SEARCH(F$1, $D30),0) >= 1, TRUE,FALSE) -> FALSE | G30: =IF(IFERROR(SEARCH(G$1, $D30),0) >= 1, TRUE,FALSE) -> FALSE | H30: =IF(IFERROR(SEARCH(H$1, $D30),0) >= 1, TRUE,FALSE) -> TRUE | I30: =IF(IFERROR(SEARCH(I$1, $D30),0) >= 1, TRUE,FALSE) -> TRUE | J30: =IF(IFERROR(SEARCH(J$1, $D30),0) >= 1, TRUE,FALSE) -> TRUE | K30: =IF(IFERROR(SEARCH(K$1, $D30),0) >= 1, TRUE,FALSE) -> FALSE | M30: TRUE | N30: FALSE | O30: TRUE | P30: FALSE | Q30: =IF(ISBLANK(A30),B30,A30) -> Het Lijsternest | Streuvelshuis & Schrijversresidentie | R30: 3 | S30: TRUE | T30: FALSE
A31: HEY Museum | C31: West-Vlaanderen | D31: Beeldende kunst, Geschiedenis en archeologie | E31: =IF(IFERROR(SEARCH(E$1, $D31),0) >= 1, TRUE,FALSE) -> TRUE | F31: =IF(IFERROR(SEARCH(F$1, $D31),0) >= 1, TRUE,FALSE) -> FALSE | G31: =IF(IFERROR(SEARCH(G$1, $D31),0) >= 1, TRUE,FALSE) -> FALSE | H31: =IF(IFERROR(SEARCH(H$1, $D31),0) >= 1, TRUE,FALSE) -> FALSE | I31: =IF(IFERROR(SEARCH(I$1, $D31),0) >= 1, TRUE,FALSE) -> FALSE | J31: =IF(IFERROR(SEARCH(J$1, $D31),0) >= 1, TRUE,FALSE) -> TRUE | K31: =IF(IFERROR(SEARCH(K$1, $D31),0) >= 1, TRUE,FALSE) -> FALSE | M31: TRUE | N31: FALSE | O31: FALSE | P31: FALSE | Q31: =IF(ISBLANK(A31),B31,A31) -> HEY Museum | R31: 10 | S31: FALSE | T31: FALSE
A32: Hopmuseum Poperinge | B32: Musée du Houblon Poperinge | C32: West-Vlaanderen | D32: Geschiedenis en archeologie | E32: =IF(IFERROR(SEARCH(E$1, $D32),0) >= 1, TRUE,FALSE) -> TRUE | F32: =IF(IFERROR(SEARCH(F$1, $D32),0) >= 1, TRUE,FALSE) -> FALSE | G32: =IF(IFERROR(SEARCH(G$1, $D32),0) >= 1, TRUE,FALSE) -> FALSE | H32: =IF(IFERROR(SEARCH(H$1, $D32),0) >= 1, TRUE,FALSE) -> FALSE | I32: =IF(IFERROR(SEARCH(I$1, $D32),0) >= 1, TRUE,FALSE) -> FALSE | J32: =IF(IFERROR(SEARCH(J$1, $D32),0) >= 1, TRUE,FALSE) -> FALSE | K32: =IF(IFERROR(SEARCH(K$1, $D32),0) >= 1, TRUE,FALSE) -> FALSE | M32: TRUE | N32: TRUE | O32: FALSE | P32: FALSE | Q32: =IF(ISBLANK(A32),B32,A32) -> Hopmuseum Poperinge | R32: 7 | S32: FALSE | T32: FALSE
A33: In Flanders Fields Museum | B33: Musée In Flanders Fields | C33: West-Vlaanderen | D33: Geschiedenis en archeologie | E33: =IF(IFERROR(SEARCH(E$1, $D33),0) >= 1, TRUE,FALSE) -> TRUE | F33: =IF(IFERROR(SEARCH(F$1, $D33),0) >= 1, TRUE,FALSE) -> FALSE | G33: =IF(IFERROR(SEARCH(G$1, $D33),0) >= 1, TRUE,FALSE) -> FALSE | H33: =IF(IFERROR(SEARCH(H$1, $D33),0) >= 1, TRUE,FALSE) -> FALSE | I33: =IF(IFERROR(SEARCH(I$1, $D33),0) >= 1, TRUE,FALSE) -> FALSE | J33: =IF(IFERROR(SEARCH(J$1, $D33),0) >= 1, TRUE,FALSE) -> FALSE | K33: =IF(IFERROR(SEARCH(K$1, $D33),0) >= 1, TRUE,FALSE) -> FALSE | M33: TRUE | N33: TRUE | O33: FALSE | P33: FALSE | Q33: =IF(ISBLANK(A33),B33,A33) -> In Flanders Fields Museum | R33: 12 | S33: FALSE | T33: TRUE | U33: 12
A34: Kantmuseum Brugge | B34: Musée de la Dentelle Bruges | C34: West-Vlaanderen | D34: Toegepaste kunst en design, Geschiedenis en archeologie, Mode | E34: =IF(IFERROR(SEARCH(E$1, $D34),0) >= 1, TRUE,FALSE) -> TRUE | F34: =IF(IFERROR(SEARCH(F$1, $D34),0) >= 1, TRUE,FALSE) -> FALSE | G34: =IF(IFERROR(SEARCH(G$1, $D34),0) >= 1, TRUE,FALSE) -> TRUE | H34: =IF(IFERROR(SEARCH(H$1, $D34),0) >= 1, TRUE,FALSE) -> FALSE | I34: =IF(IFERROR(SEARCH(I$1, $D34),0) >= 1, TRUE,FALSE) -> FALSE | J34: =IF(IFERROR(SEARCH(J$1, $D34),0) >= 1, TRUE,FALSE) -> FALSE | K34: =IF(IFERROR(SEARCH(K$1, $D34),0) >= 1, TRUE,FALSE) -> TRUE | M34: TRUE | N34: FALSE | O34: FALSE | P34: FALSE | Q34: =IF(ISBLANK(A34),B34,A34) -> Kantmuseum Brugge | R34: 8 | S34: FALSE | T34: FALSE
A35: Kasteel van Loppem | B35: Château de Loppem | C35: West-Vlaanderen | D35: Beeldende kunst, Geschiedenis en archeologie | E35: =IF(IFERROR(SEARCH(E$1, $D35),0) >= 1, TRUE,FALSE) -> TRUE | F35: =IF(IFERROR(SEARCH(F$1, $D35),0) >= 1, TRUE,FALSE) -> FALSE | G35: =IF(IFERROR(SEARCH(G$1, $D35),0) >= 1, TRUE,FALSE) -> FALSE | H35: =IF(IFERROR(SEARCH(H$1, $D35),0) >= 1, TRUE,FALSE) -> FALSE | I35: =IF(IFERROR(SEARCH(I$1, $D35),0) >= 1, TRUE,FALSE) -> FALSE | J35: =IF(IFERROR(SEARCH(J$1, $D35),0) >= 1, TRUE,FALSE) -> TRUE | K35: =IF(IFERROR(SEARCH(K$1, $D35),0) >= 1, TRUE,FALSE) -> FALSE | M35: TRUE | N35: FALSE | O35: TRUE | P35: FALSE | Q35: =IF(ISBLANK(A35),B35,A35) -> Kasteel van Loppem | R35: 9 | S35: FALSE | T35: FALSE
A36: KOERS | Museum van de Wielersport | B36: Musée de la Course Cycliste | C36: West-Vlaanderen | D36: Geschiedenis en archeologie, Wetenschap en technologie | E36: =IF(IFERROR(SEARCH(E$1, $D36),0) >= 1, TRUE,FALSE) -> TRUE | F36: =IF(IFERROR(SEARCH(F$1, $D36),0) >= 1, TRUE,FALSE) -> TRUE | G36: =IF(IFERROR(SEARCH(G$1, $D36),0) >= 1, TRUE,FALSE) -> FALSE | H36: =IF(IFERROR(SEARCH(H$1, $D36),0) >= 1, TRUE,FALSE) -> FALSE | I36: =IF(IFERROR(SEARCH(I$1, $D36),0) >= 1, TRUE,FALSE) -> FALSE | J36: =IF(IFERROR(SEARCH(J$1, $D36),0) >= 1, TRUE,FALSE) -> FALSE | K36: =IF(IFERROR(SEARCH(K$1, $D36),0) >= 1, TRUE,FALSE) -> FALSE | M36: TRUE | N36: TRUE | O36: FALSE | P36: TRUE | Q36: =IF(ISBLANK(A36),B36,A36) -> KOERS | Museum van de Wielersport | R36: 9 | S36: FALSE | T36: FALSE
A37: Museum aan de IJzer | B37: Musée la tour de L’Yser | C37: West-Vlaanderen | D37: Geschiedenis en archeologie | E37: =IF(IFERROR(SEARCH(E$1, $D37),0) >= 1, TRUE,FALSE) -> TRUE | F37: =IF(IFERROR(SEARCH(F$1, $D37),0) >= 1, TRUE,FALSE) -> FALSE | G37: =IF(IFERROR(SEARCH(G$1, $D37),0) >= 1, TRUE,FALSE) -> FALSE | H37: =IF(IFERROR(SEARCH(H$1, $D37),0) >= 1, TRUE,FALSE) -> FALSE | I37: =IF(IFERROR(SEARCH(I$1, $D37),0) >= 1, TRUE,FALSE) -> FALSE | J37: =IF(IFERROR(SEARCH(J$1, $D37),0) >= 1, TRUE,FALSE) -> FALSE | K37: =IF(IFERROR(SEARCH(K$1, $D37),0) >= 1, TRUE,FALSE) -> FALSE | M37: TRUE | N37: TRUE | O37: TRUE | P37: FALSE | Q37: =IF(ISBLANK(A37),B37,A37) -> Museum aan de IJzer | R37: 9.5 | S37: FALSE | T37: TRUE | U37: 9.5
A38: Museum Sint-Janshospitaal | B38: Musée Hôpital Saint-Jean | C38: West-Vlaanderen | D38: Beeldende kunst, Toegepaste kunst en design, Geschiedenis en archeologie, Wetenschap en technologie, Architectuur | E38: =IF(IFERROR(SEARCH(E$1, $D38),0) >= 1, TRUE,FALSE) -> TRUE | F38: =IF(IFERROR(SEARCH(F$1, $D38),0) >= 1, TRUE,FALSE) -> TRUE | G38: =IF(IFERROR(SEARCH(G$1, $D38),0) >= 1, TRUE,FALSE) -> FALSE | H38: =IF(IFERROR(SEARCH(H$1, $D38),0) >= 1, TRUE,FALSE) -> FALSE | I38: =IF(IFERROR(SEARCH(I$1, $D38),0) >= 1, TRUE,FALSE) -> TRUE | J38: =IF(IFERROR(SEARCH(J$1, $D38),0) >= 1, TRUE,FALSE) -> TRUE | K38: =IF(IFERROR(SEARCH(K$1, $D38),0) >= 1, TRUE,FALSE) -> TRUE | M38: TRUE | N38: FALSE | O38: FALSE | P38: FALSE | Q38: =IF(ISBLANK(A38),B38,A38) -> Museum Sint-Janshospitaal | R38: 15 | S38: FALSE | T38: TRUE | U38: 15
A39: Mu.ZEE | Kunstmuseum aan Zee | B39: Musée Art-sur-Mer | C39: West-Vlaanderen | D39: Beeldende kunst | E39: =IF(IFERROR(SEARCH(E$1, $D39),0) >= 1, TRUE,FALSE) -> FALSE | F39: =IF(IFERROR(SEARCH(F$1, $D39),0) >= 1, TRUE,FALSE) -> FALSE | G39: =IF(IFERROR(SEARCH(G$1, $D39),0) >= 1, TRUE,FALSE) -> FALSE | H39: =IF(IFERROR(SEARCH(H$1, $D39),0) >= 1, TRUE,FALSE) -> FALSE | I39: =IF(IFERROR(SEARCH(I$1, $D39),0) >= 1, TRUE,FALSE) -> FALSE | J39: =IF(IFERROR(SEARCH(J$1, $D39),0) >= 1, TRUE,FALSE) -> TRUE | K39: =IF(IFERROR(SEARCH(K$1, $D39),0) >= 1, TRUE,FALSE) -> FALSE | M39: TRUE | N39: FALSE | O39: FALSE | P39: FALSE | Q39: =IF(ISBLANK(A39),B39,A39) -> Mu.ZEE | Kunstmuseum aan Zee | R39: 12 | S39: TRUE | T39: TRUE | U39: 12
A40: Nationaal Tabaksmuseum | B40: Musée National du Tabac | C40: West-Vlaanderen | D40: Geschiedenis en archeologie | E40: =IF(IFERROR(SEARCH(E$1, $D40),0) >= 1, TRUE,FALSE) -> TRUE | F40: =IF(IFERROR(SEARCH(F$1, $D40),0) >= 1, TRUE,FALSE) -> FALSE | G40: =IF(IFERROR(SEARCH(G$1, $D40),0) >= 1, TRUE,FALSE) -> FALSE | H40: =IF(IFERROR(SEARCH(H$1, $D40),0) >= 1, TRUE,FALSE) -> FALSE | I40: =IF(IFERROR(SEARCH(I$1, $D40),0) >= 1, TRUE,FALSE) -> FALSE | J40: =IF(IFERROR(SEARCH(J$1, $D40),0) >= 1, TRUE,FALSE) -> FALSE | K40: =IF(IFERROR(SEARCH(K$1, $D40),0) >= 1, TRUE,FALSE) -> FALSE | M40: FALSE | N40: FALSE | O40: FALSE | P40: FALSE | Q40: =IF(ISBLANK(A40),B40,A40) -> Nationaal Tabaksmuseum | R40: 4.5 | S40: FALSE | T40: TRUE | U40: 4.5
A41: NAVIGO Visserijmuseum | B41: Musée de la Pêche NAVIGO | C41: West-Vlaanderen | D41: Beeldende kunst, Wetenschap en technologie | E41: =IF(IFERROR(SEARCH(E$1, $D41),0) >= 1, TRUE,FALSE) -> FALSE | F41: =IF(IFERROR(SEARCH(F$1, $D41),0) >= 1, TRUE,FALSE) -> TRUE | G41: =IF(IFERROR(SEARCH(G$1, $D41),0) >= 1, TRUE,FALSE) -> FALSE | H41: =IF(IFERROR(SEARCH(H$1, $D41),0) >= 1, TRUE,FALSE) -> FALSE | I41: =IF(IFERROR(SEARCH(I$1, $D41),0) >= 1, TRUE,FALSE) -> FALSE | J41: =IF(IFERROR(SEARCH(J$1, $D41),0) >= 1, TRUE,FALSE) -> TRUE | K41: =IF(IFERROR(SEARCH(K$1, $D41),0) >= 1, TRUE,FALSE) -> FALSE | M41: TRUE | N41: TRUE | O41: TRUE | P41: TRUE | Q41: =IF(ISBLANK(A41),B41,A41) -> NAVIGO Visserijmuseum | R41: 10 | S41: FALSE | T41: TRUE | U41: 0
A42: O.L.V.-kerk Museum | B42: Musée de l’Église Notre-Dame | C42: West-Vlaanderen | D42: Beeldende kunst, Architectuur | E42: =IF(IFERROR(SEARCH(E$1, $D42),0) >= 1, TRUE,FALSE) -> FALSE | F42: =IF(IFERROR(SEARCH(F$1, $D42),0) >= 1, TRUE,FALSE) -> FALSE | G42: =IF(IFERROR(SEARCH(G$1, $D42),0) >= 1, TRUE,FALSE) -> FALSE | H42: =IF(IFERROR(SEARCH(H$1, $D42),0) >= 1, TRUE,FALSE) -> FALSE | I42: =IF(IFERROR(SEARCH(I$1, $D42),0) >= 1, TRUE,FALSE) -> TRUE | J42: =IF(IFERROR(SEARCH(J$1, $D42),0) >= 1, TRUE,FALSE) -> TRUE | K42: =IF(IFERROR(SEARCH(K$1, $D42),0) >= 1, TRUE,FALSE) -> FALSE | M42: FALSE | N42: FALSE | O42: FALSE | P42: FALSE | Q42: =IF(ISBLANK(A42),B42,A42) -> O.L.V.-kerk Museum | R42: 8 | S42: FALSE | T42: FALSE
A43: O.L.V. ter Potterie | B43: Musée Notre-Dame de la Poterie | C43: West-Vlaanderen | D43: Beeldende kunst, Toegepaste kunst en design, Geschiedenis en archeologie, Architectuur | E43: =IF(IFERROR(SEARCH(E$1, $D43),0) >= 1, TRUE,FALSE) -> TRUE | F43: =IF(IFERROR(SEARCH(F$1, $D43),0) >= 1, TRUE,FALSE) -> FALSE | G43: =IF(IFERROR(SEARCH(G$1, $D43),0) >= 1, TRUE,FALSE) -> FALSE | H43: =IF(IFERROR(SEARCH(H$1, $D43),0) >= 1, TRUE,FALSE) -> FALSE | I43: =IF(IFERROR(SEARCH(I$1, $D43),0) >= 1, TRUE,FALSE) -> TRUE | J43: =IF(IFERROR(SEARCH(J$1, $D43),0) >= 1, TRUE,FALSE) -> TRUE | K43: =IF(IFERROR(SEARCH(K$1, $D43),0) >= 1, TRUE,FALSE) -> TRUE | M43: FALSE | N43: FALSE | O43: FALSE | P43: FALSE | Q43: =IF(ISBLANK(A43),B43,A43) -> O.L.V. ter Potterie | R43: 8 | S43: FALSE | T43: FALSE
A44: Passchendaele Museum | C44: West-Vlaanderen | D44: Geschiedenis en archeologie | E44: =IF(IFERROR(SEARCH(E$1, $D44),0) >= 1, TRUE,FALSE) -> TRUE | F44: =IF(IFERROR(SEARCH(F$1, $D44),0) >= 1, TRUE,FALSE) -> FALSE | G44: =IF(IFERROR(SEARCH(G$1, $D44),0) >= 1, TRUE,FALSE) -> FALSE | H44: =IF(IFERROR(SEARCH(H$1, $D44),0) >= 1, TRUE,FALSE) -> FALSE | I44: =IF(IFERROR(SEARCH(I$1, $D44),0) >= 1, TRUE,FALSE) -> FALSE | J44: =IF(IFERROR(SEARCH(J$1, $D44),0) >= 1, TRUE,FALSE) -> FALSE | K44: =IF(IFERROR(SEARCH(K$1, $D44),0) >= 1, TRUE,FALSE) -> FALSE | M44: TRUE | N44: FALSE | O44: TRUE | P44: FALSE | Q44: =IF(ISBLANK(A44),B44,A44) -> Passchendaele Museum | R44: 13 | S44: FALSE | T44: TRUE | U44: 13
A45: Paul Delvaux Museum | B45: Musée Paul Delvaux | C45: West-Vlaanderen | D45: Beeldende kunst | E45: =IF(IFERROR(SEARCH(E$1, $D45),0) >= 1, TRUE,FALSE) -> FALSE | F45: =IF(IFERROR(SEARCH(F$1, $D45),0) >= 1, TRUE,FALSE) -> FALSE | G45: =IF(IFERROR(SEARCH(G$1, $D45),0) >= 1, TRUE,FALSE) -> FALSE | H45: =IF(IFERROR(SEARCH(H$1, $D45),0) >= 1, TRUE,FALSE) -> FALSE | I45: =IF(IFERROR(SEARCH(I$1, $D45),0) >= 1, TRUE,FALSE) -> FALSE | J45: =IF(IFERROR(SEARCH(J$1, $D45),0) >= 1, TRUE,FALSE) -> TRUE | K45: =IF(IFERROR(SEARCH(K$1, $D45),0) >= 1, TRUE,FALSE) -> FALSE | M45: TRUE | N45: TRUE | O45: TRUE | P45: FALSE | Q45: =IF(ISBLANK(A45),B45,A45) -> Paul Delvaux Museum | R45: 12 | S45: FALSE | T45: FALSE
A46: Peiremuzee | C46: West-Vlaanderen | D46: Beeldende kunst | E46: =IF(IFERROR(SEARCH(E$1, $D46),0) >= 1, TRUE,FALSE) -> FALSE | F46: =IF(IFERROR(SEARCH(F$1, $D46),0) >= 1, TRUE,FALSE) -> FALSE | G46: =IF(IFERROR(SEARCH(G$1, $D46),0) >= 1, TRUE,FALSE) -> FALSE | H46: =IF(IFERROR(SEARCH(H$1, $D46),0) >= 1, TRUE,FALSE) -> FALSE | I46: =IF(IFERROR(SEARCH(I$1, $D46),0) >= 1, TRUE,FALSE) -> FALSE | J46: =IF(IFERROR(SEARCH(J$1, $D46),0) >= 1, TRUE,FALSE) -> TRUE | K46: =IF(IFERROR(SEARCH(K$1, $D46),0) >= 1, TRUE,FALSE) -> FALSE | M46: TRUE | N46: FALSE | O46: FALSE | P46: FALSE | Q46: =IF(ISBLANK(A46),B46,A46) -> Peiremuzee | R46: 12 | S46: FALSE | T46: FALSE
A47: Permekemuseum | B47: Musée Permeke | C47: West-Vlaanderen | D47: Beeldende kunst | E47: =IF(IFERROR(SEARCH(E$1, $D47),0) >= 1, TRUE,FALSE) -> FALSE | F47: =IF(IFERROR(SEARCH(F$1, $D47),0) >= 1, TRUE,FALSE) -> FALSE | G47: =IF(IFERROR(SEARCH(G$1, $D47),0) >= 1, TRUE,FALSE) -> FALSE | H47: =IF(IFERROR(SEARCH(H$1, $D47),0) >= 1, TRUE,FALSE) -> FALSE | I47: =IF(IFERROR(SEARCH(I$1, $D47),0) >= 1, TRUE,FALSE) -> FALSE | J47: =IF(IFERROR(SEARCH(J$1, $D47),0) >= 1, TRUE,FALSE) -> TRUE | K47: =IF(IFERROR(SEARCH(K$1, $D47),0) >= 1, TRUE,FALSE) -> FALSE | M47: FALSE | N47: FALSE | O47: FALSE | P47: FALSE | Q47: =IF(ISBLANK(A47),B47,A47) -> Permekemuseum | R47: 12 | S47: FALSE | T47: FALSE
A48: Romeins Archeologisch Museum Oudenburg | B48: Musée d’archéologie romaine Oudenburg | C48: West-Vlaanderen | D48: Geschiedenis en archeologie | E48: =IF(IFERROR(SEARCH(E$1, $D48),0) >= 1, TRUE,FALSE) -> TRUE | F48: =IF(IFERROR(SEARCH(F$1, $D48),0) >= 1, TRUE,FALSE) -> FALSE | G48: =IF(IFERROR(SEARCH(G$1, $D48),0) >= 1, TRUE,FALSE) -> FALSE | H48: =IF(IFERROR(SEARCH(H$1, $D48),0) >= 1, TRUE,FALSE) -> FALSE | I48: =IF(IFERROR(SEARCH(I$1, $D48),0) >= 1, TRUE,FALSE) -> FALSE | J48: =IF(IFERROR(SEARCH(J$1, $D48),0) >= 1, TRUE,FALSE) -> FALSE | K48: =IF(IFERROR(SEARCH(K$1, $D48),0) >= 1, TRUE,FALSE) -> FALSE | M48: TRUE | N48: TRUE | O48: TRUE | P48: FALSE | Q48: =IF(ISBLANK(A48),B48,A48) -> Romeins Archeologisch Museum Oudenburg | R48: 8 | S48: FALSE | T48: FALSE
A49: Sint-Janshuismolen | B49: Moulin Sint-Janshuis | C49: West-Vlaanderen | D49: Geschiedenis en archeologie, Wetenschap en technologie | E49: =IF(IFERROR(SEARCH(E$1, $D49),0) >= 1, TRUE,FALSE) -> TRUE | F49: =IF(IFERROR(SEARCH(F$1, $D49),0) >= 1, TRUE,FALSE) -> TRUE | G49: =IF(IFERROR(SEARCH(G$1, $D49),0) >= 1, TRUE,FALSE) -> FALSE | H49: =IF(IFERROR(SEARCH(H$1, $D49),0) >= 1, TRUE,FALSE) -> FALSE | I49: =IF(IFERROR(SEARCH(I$1, $D49),0) >= 1, TRUE,FALSE) -> FALSE | J49: =IF(IFERROR(SEARCH(J$1, $D49),0) >= 1, TRUE,FALSE) -> FALSE | K49: =IF(IFERROR(SEARCH(K$1, $D49),0) >= 1, TRUE,FALSE) -> FALSE | M49: FALSE | N49: FALSE | O49: FALSE | P49: FALSE | Q49: =IF(ISBLANK(A49),B49,A49) -> Sint-Janshuismolen | R49: 5 | S49: FALSE | T49: FALSE
A50: Stadhuis Brugge | B50: L’Hôtel de ville Bruges | C50: West-Vlaanderen | D50: Beeldende kunst, Toegepaste kunst en design, Geschiedenis en archeologie, Architectuur | E50: =IF(IFERROR(SEARCH(E$1, $D50),0) >= 1, TRUE,FALSE) -> TRUE | F50: =IF(IFERROR(SEARCH(F$1, $D50),0) >= 1, TRUE,FALSE) -> FALSE | G50: =IF(IFERROR(SEARCH(G$1, $D50),0) >= 1, TRUE,FALSE) -> FALSE | H50: =IF(IFERROR(SEARCH(H$1, $D50),0) >= 1, TRUE,FALSE) -> FALSE | I50: =IF(IFERROR(SEARCH(I$1, $D50),0) >= 1, TRUE,FALSE) -> TRUE | J50: =IF(IFERROR(SEARCH(J$1, $D50),0) >= 1, TRUE,FALSE) -> TRUE | K50: =IF(IFERROR(SEARCH(K$1, $D50),0) >= 1, TRUE,FALSE) -> TRUE | M50: FALSE | N50: FALSE | O50: FALSE | P50: FALSE | Q50: =IF(ISBLANK(A50),B50,A50) -> Stadhuis Brugge | R50: 8 | S50: FALSE | T50: FALSE
A51: Talbot House | C51: West-Vlaanderen | D51: Geschiedenis en archeologie | E51: =IF(IFERROR(SEARCH(E$1, $D51),0) >= 1, TRUE,FALSE) -> TRUE | F51: =IF(IFERROR(SEARCH(F$1, $D51),0) >= 1, TRUE,FALSE) -> FALSE | G51: =IF(IFERROR(SEARCH(G$1, $D51),0) >= 1, TRUE,FALSE) -> FALSE | H51: =IF(IFERROR(SEARCH(H$1, $D51),0) >= 1, TRUE,FALSE) -> FALSE | I51: =IF(IFERROR(SEARCH(I$1, $D51),0) >= 1, TRUE,FALSE) -> FALSE | J51: =IF(IFERROR(SEARCH(J$1, $D51),0) >= 1, TRUE,FALSE) -> FALSE | K51: =IF(IFERROR(SEARCH(K$1, $D51),0) >= 1, TRUE,FALSE) -> FALSE | M51: TRUE | N51: FALSE | O51: FALSE | P51: FALSE | Q51: =IF(ISBLANK(A51),B51,A51) -> Talbot House | R51: 10 | S51: FALSE | T51: TRUE | U51: 10
A52: Texture | Museum van Vlas en Textiel | B52: Musée du Lin et du Textile | C52: West-Vlaanderen | D52: Toegepaste kunst en design, Wetenschap en technologie, Architectuur, Mode | E52: =IF(IFERROR(SEARCH(E$1, $D52),0) >= 1, TRUE,FALSE) -> FALSE | F52: =IF(IFERROR(SEARCH(F$1, $D52),0) >= 1, TRUE,FALSE) -> TRUE | G52: =IF(IFERROR(SEARCH(G$1, $D52),0) >= 1, TRUE,FALSE) -> TRUE | H52: =IF(IFERROR(SEARCH(H$1, $D52),0) >= 1, TRUE,FALSE) -> FALSE | I52: =IF(IFERROR(SEARCH(I$1, $D52),0) >= 1, TRUE,FALSE) -> TRUE | J52: =IF(IFERROR(SEARCH(J$1, $D52),0) >= 1, TRUE,FALSE) -> FALSE | K52: =IF(IFERROR(SEARCH(K$1, $D52),0) >= 1, TRUE,FALSE) -> TRUE | M52: TRUE | N52: TRUE | O52: TRUE | P52: FALSE | Q52: =IF(ISBLANK(A52),B52,A52) -> Texture | Museum van Vlas en Textiel | R52: 8 | S52: FALSE | T52: TRUE | U52: 8
A53: Uilenspiegelmuseum | B53: Musée d’Ulenspiegel | C53: West-Vlaanderen | D53: Literatuur | E53: =IF(IFERROR(SEARCH(E$1, $D53),0) >= 1, TRUE,FALSE) -> FALSE | F53: =IF(IFERROR(SEARCH(F$1, $D53),0) >= 1, TRUE,FALSE) -> FALSE | G53: =IF(IFERROR(SEARCH(G$1, $D53),0) >= 1, TRUE,FALSE) -> FALSE | H53: =IF(IFERROR(SEARCH(H$1, $D53),0) >= 1, TRUE,FALSE) -> TRUE | I53: =IF(IFERROR(SEARCH(I$1, $D53),0) >= 1, TRUE,FALSE) -> FALSE | J53: =IF(IFERROR(SEARCH(J$1, $D53),0) >= 1, TRUE,FALSE) -> FALSE | K53: =IF(IFERROR(SEARCH(K$1, $D53),0) >= 1, TRUE,FALSE) -> FALSE | M53: FALSE | N53: FALSE | O53: FALSE | P53: FALSE | Q53: =IF(ISBLANK(A53),B53,A53) -> Uilenspiegelmuseum | R53: 6 | S53: FALSE | T53: FALSE
A54: Volkskundemuseum | B54: Musée de la vie populaire | C54: West-Vlaanderen | D54: Geschiedenis en archeologie | E54: =IF(IFERROR(SEARCH(E$1, $D54),0) >= 1, TRUE,FALSE) -> TRUE | F54: =IF(IFERROR(SEARCH(F$1, $D54),0) >= 1, TRUE,FALSE) -> FALSE | G54: =IF(IFERROR(SEARCH(G$1, $D54),0) >= 1, TRUE,FALSE) -> FALSE | H54: =IF(IFERROR(SEARCH(H$1, $D54),0) >= 1, TRUE,FALSE) -> FALSE | I54: =IF(IFERROR(SEARCH(I$1, $D54),0) >= 1, TRUE,FALSE) -> FALSE | J54: =IF(IFERROR(SEARCH(J$1, $D54),0) >= 1, TRUE,FALSE) -> FALSE | K54: =IF(IFERROR(SEARCH(K$1, $D54),0) >= 1, TRUE,FALSE) -> FALSE | M54: FALSE | N54: FALSE | O54: FALSE | P54: FALSE | Q54: =IF(ISBLANK(A54),B54,A54) -> Volkskundemuseum | R54: 8 | S54: FALSE | T54: FALSE
A55: Westfront Nieuwpoort | C55: West-Vlaanderen | D55: Geschiedenis en archeologie, Architectuur | E55: =IF(IFERROR(SEARCH(E$1, $D55),0) >= 1, TRUE,FALSE) -> TRUE | F55: =IF(IFERROR(SEARCH(F$1, $D55),0) >= 1, TRUE,FALSE) -> FALSE | G55: =IF(IFERROR(SEARCH(G$1, $D55),0) >= 1, TRUE,FALSE) -> FALSE | H55: =IF(IFERROR(SEARCH(H$1, $D55),0) >= 1, TRUE,FALSE) -> FALSE | I55: =IF(IFERROR(SEARCH(I$1, $D55),0) >= 1, TRUE,FALSE) -> TRUE | J55: =IF(IFERROR(SEARCH(J$1, $D55),0) >= 1, TRUE,FALSE) -> FALSE | K55: =IF(IFERROR(SEARCH(K$1, $D55),0) >= 1, TRUE,FALSE) -> FALSE | M55: TRUE | N55: FALSE | O55: FALSE | P55: FALSE | Q55: =IF(ISBLANK(A55),B55,A55) -> Westfront Nieuwpoort | R55: 9.5 | S55: FALSE | T55: FALSE
A56: Yper Museum | C56: West-Vlaanderen | D56: Beeldende kunst, Toegepaste kunst en design, Geschiedenis en archeologie, Architectuur | E56: =IF(IFERROR(SEARCH(E$1, $D56),0) >= 1, TRUE,FALSE) -> TRUE | F56: =IF(IFERROR(SEARCH(F$1, $D56),0) >= 1, TRUE,FALSE) -> FALSE | G56: =IF(IFERROR(SEARCH(G$1, $D56),0) >= 1, TRUE,FALSE) -> FALSE | H56: =IF(IFERROR(SEARCH(H$1, $D56),0) >= 1, TRUE,FALSE) -> FALSE | I56: =IF(IFERROR(SEARCH(I$1, $D56),0) >= 1, TRUE,FALSE) -> TRUE | J56: =IF(IFERROR(SEARCH(J$1, $D56),0) >= 1, TRUE,FALSE) -> TRUE | K56: =IF(IFERROR(SEARCH(K$1, $D56),0) >= 1, TRUE,FALSE) -> TRUE | M56: FALSE | N56: TRUE | O56: FALSE | P56: FALSE | Q56: =IF(ISBLANK(A56),B56,A56) -> Yper Museum | R56: 8.5 | S56: FALSE | T56: FALSE
A57: Zwin Natuur Park | B57: Zwin Parc Naturel | C57: West-Vlaanderen | D57: Geschiedenis en archeologie, Wetenschap en technologie | E57: =IF(IFERROR(SEARCH(E$1, $D57),0) >= 1, TRUE,FALSE) -> TRUE | F57: =IF(IFERROR(SEARCH(F$1, $D57),0) >= 1, TRUE,FALSE) -> TRUE | G57: =IF(IFERROR(SEARCH(G$1, $D57),0) >= 1, TRUE,FALSE) -> FALSE | H57: =IF(IFERROR(SEARCH(H$1, $D57),0) >= 1, TRUE,FALSE) -> FALSE | I57: =IF(IFERROR(SEARCH(I$1, $D57),0) >= 1, TRUE,FALSE) -> FALSE | J57: =IF(IFERROR(SEARCH(J$1, $D57),0) >= 1, TRUE,FALSE) -> FALSE | K57: =IF(IFERROR(SEARCH(K$1, $D57),0) >= 1, TRUE,FALSE) -> FALSE | M57: TRUE | N57: TRUE | O57: TRUE | P57: TRUE | Q57: =IF(ISBLANK(A57),B57,A57) -> Zwin Natuur Park | R57: 12 | S57: FALSE | T57: TRUE | U57: 14
A58: Arboretum Kalmtout | C58: Antwerpen | D58: Wetenschap en technologie | E58: =IF(IFERROR(SEARCH(E$1, $D58),0) >= 1, TRUE,FALSE) -> FALSE | F58: =IF(IFERROR(SEARCH(F$1, $D58),0) >= 1, TRUE,FALSE) -> TRUE | G58: =IF(IFERROR(SEARCH(G$1, $D58),0) >= 1, TRUE,FALSE) -> FALSE | H58: =IF(IFERROR(SEARCH(H$1, $D58),0) >= 1, TRUE,FALSE) -> FALSE | I58: =IF(IFERROR(SEARCH(I$1, $D58),0) >= 1, TRUE,FALSE) -> FALSE | J58: =IF(IFERROR(SEARCH(J$1, $D58),0) >= 1, TRUE,FALSE) -> FALSE | K58: =IF(IFERROR(SEARCH(K$1, $D58),0) >= 1, TRUE,FALSE) -> FALSE | M58: TRUE | N58: TRUE | O58: TRUE | P58: TRUE | Q58: =IF(ISBLANK(A58),B58,A58) -> Arboretum Kalmtout | R58: 8 | S58: FALSE | T58: TRUE | U58: 9.5
A59: Begijnhofmuseum Turnhout | B59: Musée du béguinage Turnhout | C59: Antwerpen | D59: Beeldende kunst, Geschiedenis en archeologie | E59: =IF(IFERROR(SEARCH(E$1, $D59),0) >= 1, TRUE,FALSE) -> TRUE | F59: =IF(IFERROR(SEARCH(F$1, $D59),0) >= 1, TRUE,FALSE) -> FALSE | G59: =IF(IFERROR(SEARCH(G$1, $D59),0) >= 1, TRUE,FALSE) -> FALSE | H59: =IF(IFERROR(SEARCH(H$1, $D59),0) >= 1, TRUE,FALSE) -> FALSE | I59: =IF(IFERROR(SEARCH(I$1, $D59),0) >= 1, TRUE,FALSE) -> FALSE | J59: =IF(IFERROR(SEARCH(J$1, $D59),0) >= 1, TRUE,FALSE) -> TRUE | K59: =IF(IFERROR(SEARCH(K$1, $D59),0) >= 1, TRUE,FALSE) -> FALSE | M59: TRUE | N59: FALSE | O59: FALSE | P59: FALSE | Q59: =IF(ISBLANK(A59),B59,A59) -> Begijnhofmuseum Turnhout | R59: 5 | S59: FALSE | T59: FALSE
A60: DIVA | museum voor diamant juwelen en zilver | B60: le musée du diamant, des bijoux et de l’orfèvrerie | C60: Antwerpen | D60: Toegepaste kunst en design, Geschiedenis en archeologie, Wetenschap en technologie | E60: =IF(IFERROR(SEARCH(E$1, $D60),0) >= 1, TRUE,FALSE) -> TRUE | F60: =IF(IFERROR(SEARCH(F$1, $D60),0) >= 1, TRUE,FALSE) -> TRUE | G60: =IF(IFERROR(SEARCH(G$1, $D60),0) >= 1, TRUE,FALSE) -> FALSE | H60: =IF(IFERROR(SEARCH(H$1, $D60),0) >= 1, TRUE,FALSE) -> FALSE | I60: =IF(IFERROR(SEARCH(I$1, $D60),0) >= 1, TRUE,FALSE) -> FALSE | J60: =IF(IFERROR(SEARCH(J$1, $D60),0) >= 1, TRUE,FALSE) -> FALSE | K60: =IF(IFERROR(SEARCH(K$1, $D60),0) >= 1, TRUE,FALSE) -> TRUE | M60: TRUE | N60: FALSE | O60: FALSE | P60: FALSE | Q60: =IF(ISBLANK(A60),B60,A60) -> DIVA | museum voor diamant juwelen en zilver | R60: 12 | S60: FALSE | T60: FALSE
A61: Erfgoedbibliotheek Hendrik Conscience - Nottebohmzaal | B61: Bibliothèque Patrimoniale Hendrik Conscience - salle Nottebohm | C61: Antwerpen | D61: Geschiedenis en archeologie, Literatuur | E61: =IF(IFERROR(SEARCH(E$1, $D61),0) >= 1, TRUE,FALSE) -> TRUE | F61: =IF(IFERROR(SEARCH(F$1, $D61),0) >= 1, TRUE,FALSE) -> FALSE | G61: =IF(IFERROR(SEARCH(G$1, $D61),0) >= 1, TRUE,FALSE) -> FALSE | H61: =IF(IFERROR(SEARCH(H$1, $D61),0) >= 1, TRUE,FALSE) -> TRUE | I61: =IF(IFERROR(SEARCH(I$1, $D61),0) >= 1, TRUE,FALSE) -> FALSE | J61: =IF(IFERROR(SEARCH(J$1, $D61),0) >= 1, TRUE,FALSE) -> FALSE | K61: =IF(IFERROR(SEARCH(K$1, $D61),0) >= 1, TRUE,FALSE) -> FALSE | M61: FALSE | N61: FALSE | O61: FALSE | P61: FALSE | Q61: =IF(ISBLANK(A61),B61,A61) -> Erfgoedbibliotheek Hendrik Conscience - Nottebohmzaal | R61: 0 | S61: FALSE | T61: FALSE
A62: FOMU | Fotomuseum Antwerpen | B62: Musée de la Photographie d’Anvers | C62: Antwerpen | D62: Beeldende kunst | E62: =IF(IFERROR(SEARCH(E$1, $D62),0) >= 1, TRUE,FALSE) -> FALSE | F62: =IF(IFERROR(SEARCH(F$1, $D62),0) >= 1, TRUE,FALSE) -> FALSE | G62: =IF(IFERROR(SEARCH(G$1, $D62),0) >= 1, TRUE,FALSE) -> FALSE | H62: =IF(IFERROR(SEARCH(H$1, $D62),0) >= 1, TRUE,FALSE) -> FALSE | I62: =IF(IFERROR(SEARCH(I$1, $D62),0) >= 1, TRUE,FALSE) -> FALSE | J62: =IF(IFERROR(SEARCH(J$1, $D62),0) >= 1, TRUE,FALSE) -> TRUE | K62: =IF(IFERROR(SEARCH(K$1, $D62),0) >= 1, TRUE,FALSE) -> FALSE | M62: TRUE | N62: TRUE | O62: TRUE | P62: FALSE | Q62: =IF(ISBLANK(A62),B62,A62) -> FOMU | Fotomuseum Antwerpen | R62: 12 | S62: FALSE | T62: TRUE | U62: 12
A63: Fort van Breendonk | B63: Fort de Breendonk | C63: Antwerpen | D63: Geschiedenis en archeologie | E63: =IF(IFERROR(SEARCH(E$1, $D63),0) >= 1, TRUE,FALSE) -> TRUE | F63: =IF(IFERROR(SEARCH(F$1, $D63),0) >= 1, TRUE,FALSE) -> FALSE | G63: =IF(IFERROR(SEARCH(G$1, $D63),0) >= 1, TRUE,FALSE) -> FALSE | H63: =IF(IFERROR(SEARCH(H$1, $D63),0) >= 1, TRUE,FALSE) -> FALSE | I63: =IF(IFERROR(SEARCH(I$1, $D63),0) >= 1, TRUE,FALSE) -> FALSE | J63: =IF(IFERROR(SEARCH(J$1, $D63),0) >= 1, TRUE,FALSE) -> FALSE | K63: =IF(IFERROR(SEARCH(K$1, $D63),0) >= 1, TRUE,FALSE) -> FALSE | M63: FALSE | N63: FALSE | O63: TRUE | P63: FALSE | Q63: =IF(ISBLANK(A63),B63,A63) -> Fort van Breendonk | R63: 12 | S63: FALSE | T63: FALSE
A64: Gasthuismuseum Geel | B64: Musée de l’hôpital Geel | C64: Antwerpen | D64: Beeldende kunst, Geschiedenis en archeologie, Wetenschap en technologie, Architectuur | E64: =IF(IFERROR(SEARCH(E$1, $D64),0) >= 1, TRUE,FALSE) -> TRUE | F64: =IF(IFERROR(SEARCH(F$1, $D64),0) >= 1, TRUE,FALSE) -> TRUE | G64: =IF(IFERROR(SEARCH(G$1, $D64),0) >= 1, TRUE,FALSE) -> FALSE | H64: =IF(IFERROR(SEARCH(H$1, $D64),0) >= 1, TRUE,FALSE) -> FALSE | I64: =IF(IFERROR(SEARCH(I$1, $D64),0) >= 1, TRUE,FALSE) -> TRUE | J64: =IF(IFERROR(SEARCH(J$1, $D64),0) >= 1, TRUE,FALSE) -> TRUE | K64: =IF(IFERROR(SEARCH(K$1, $D64),0) >= 1, TRUE,FALSE) -> FALSE | M64: TRUE | N64: FALSE | O64: TRUE | P64: FALSE | Q64: =IF(ISBLANK(A64),B64,A64) -> Gasthuismuseum Geel | R64: 12 | S64: FALSE | T64: TRUE | U64: 6
A65: Het Snijders&Rockoxhuis | B65: La maison Snijders&Rockox | C65: Antwerpen | D65: Geschiedenis en archeologie | E65: =IF(IFERROR(SEARCH(E$1, $D65),0) >= 1, TRUE,FALSE) -> TRUE | F65: =IF(IFERROR(SEARCH(F$1, $D65),0) >= 1, TRUE,FALSE) -> FALSE | G65: =IF(IFERROR(SEARCH(G$1, $D65),0) >= 1, TRUE,FALSE) -> FALSE | H65: =IF(IFERROR(SEARCH(H$1, $D65),0) >= 1, TRUE,FALSE) -> FALSE | I65: =IF(IFERROR(SEARCH(I$1, $D65),0) >= 1, TRUE,FALSE) -> FALSE | J65: =IF(IFERROR(SEARCH(J$1, $D65),0) >= 1, TRUE,FALSE) -> FALSE | K65: =IF(IFERROR(SEARCH(K$1, $D65),0) >= 1, TRUE,FALSE) -> FALSE | M65: TRUE | N65: FALSE | O65: FALSE | P65: FALSE | Q65: =IF(ISBLANK(A65),B65,A65) -> Het Snijders&Rockoxhuis | R65: 10 | S65: FALSE | T65: TRUE | U65: 10
A66: Jakob Smitsmuseum | B66: Musée Jakob Smits | C66: Antwerpen | D66: Beeldende kunst | E66: =IF(IFERROR(SEARCH(E$1, $D66),0) >= 1, TRUE,FALSE) -> FALSE | F66: =IF(IFERROR(SEARCH(F$1, $D66),0) >= 1, TRUE,FALSE) -> FALSE | G66: =IF(IFERROR(SEARCH(G$1, $D66),0) >= 1, TRUE,FALSE) -> FALSE | H66: =IF(IFERROR(SEARCH(H$1, $D66),0) >= 1, TRUE,FALSE) -> FALSE | I66: =IF(IFERROR(SEARCH(I$1, $D66),0) >= 1, TRUE,FALSE) -> FALSE | J66: =IF(IFERROR(SEARCH(J$1, $D66),0) >= 1, TRUE,FALSE) -> TRUE | K66: =IF(IFERROR(SEARCH(K$1, $D66),0) >= 1, TRUE,FALSE) -> FALSE | M66: TRUE | N66: FALSE | O66: TRUE | P66: FALSE | Q66: =IF(ISBLANK(A66),B66,A66) -> Jakob Smitsmuseum | R66: 5 | S66: FALSE | T66: TRUE | U66: 5
A67: Karrenmuseum Essen | B67: Musée de Chariot Essen | C67: Antwerpen | D67: Geschiedenis en archeologie, Wetenschap en technologie | E67: =IF(IFERROR(SEARCH(E$1, $D67),0) >= 1, TRUE,FALSE) -> TRUE | F67: =IF(IFERROR(SEARCH(F$1, $D67),0) >= 1, TRUE,FALSE) -> TRUE | G67: =IF(IFERROR(SEARCH(G$1, $D67),0) >= 1, TRUE,FALSE) -> FALSE | H67: =IF(IFERROR(SEARCH(H$1, $D67),0) >= 1, TRUE,FALSE) -> FALSE | I67: =IF(IFERROR(SEARCH(I$1, $D67),0) >= 1, TRUE,FALSE) -> FALSE | J67: =IF(IFERROR(SEARCH(J$1, $D67),0) >= 1, TRUE,FALSE) -> FALSE | K67: =IF(IFERROR(SEARCH(K$1, $D67),0) >= 1, TRUE,FALSE) -> FALSE | M67: TRUE | N67: TRUE | O67: TRUE | P67: TRUE | Q67: =IF(ISBLANK(A67),B67,A67) -> Karrenmuseum Essen | R67: 6 | S67: FALSE | T67: FALSE
A68: Kazerne Dossin | B68: Caserne Dossin | C68: Antwerpen | D68: Geschiedenis en archeologie | E68: =IF(IFERROR(SEARCH(E$1, $D68),0) >= 1, TRUE,FALSE) -> TRUE | F68: =IF(IFERROR(SEARCH(F$1, $D68),0) >= 1, TRUE,FALSE) -> FALSE | G68: =IF(IFERROR(SEARCH(G$1, $D68),0) >= 1, TRUE,FALSE) -> FALSE | H68: =IF(IFERROR(SEARCH(H$1, $D68),0) >= 1, TRUE,FALSE) -> FALSE | I68: =IF(IFERROR(SEARCH(I$1, $D68),0) >= 1, TRUE,FALSE) -> FALSE | J68: =IF(IFERROR(SEARCH(J$1, $D68),0) >= 1, TRUE,FALSE) -> FALSE | K68: =IF(IFERROR(SEARCH(K$1, $D68),0) >= 1, TRUE,FALSE) -> FALSE | M68: TRUE | N68: FALSE | O68: TRUE | P68: FALSE | Q68: =IF(ISBLANK(A68),B68,A68) -> Kazerne Dossin | R68: 12 | S68: FALSE | T68: TRUE | U68: 10
A69: KMSKA | Koninklijk Museum voor Schone Kunsten Antwerpen | B69: Musée Royal des Beaux-Arts d’Anver | C69: Antwerpen | D69: Beeldende kunst | E69: =IF(IFERROR(SEARCH(E$1, $D69),0) >= 1, TRUE,FALSE) -> FALSE | F69: =IF(IFERROR(SEARCH(F$1, $D69),0) >= 1, TRUE,FALSE) -> FALSE | G69: =IF(IFERROR(SEARCH(G$1, $D69),0) >= 1, TRUE,FALSE) -> FALSE | H69: =IF(IFERROR(SEARCH(H$1, $D69),0) >= 1, TRUE,FALSE) -> FALSE | I69: =IF(IFERROR(SEARCH(I$1, $D69),0) >= 1, TRUE,FALSE) -> FALSE | J69: =IF(IFERROR(SEARCH(J$1, $D69),0) >= 1, TRUE,FALSE) -> TRUE | K69: =IF(IFERROR(SEARCH(K$1, $D69),0) >= 1, TRUE,FALSE) -> FALSE | M69: TRUE | N69: TRUE | O69: FALSE | P69: TRUE | Q69: =IF(ISBLANK(A69),B69,A69) -> KMSKA | Koninklijk Museum voor Schone Kunsten Antwerpen | R69: 20 | S69: FALSE | T69: TRUE | U69: 20
A70: Kunsthal Extra City | C70: Antwerpen | D70: Beeldende kunst | E70: =IF(IFERROR(SEARCH(E$1, $D70),0) >= 1, TRUE,FALSE) -> FALSE | F70: =IF(IFERROR(SEARCH(F$1, $D70),0) >= 1, TRUE,FALSE) -> FALSE | G70: =IF(IFERROR(SEARCH(G$1, $D70),0) >= 1, TRUE,FALSE) -> FALSE | H70: =IF(IFERROR(SEARCH(H$1, $D70),0) >= 1, TRUE,FALSE) -> FALSE | I70: =IF(IFERROR(SEARCH(I$1, $D70),0) >= 1, TRUE,FALSE) -> FALSE | J70: =IF(IFERROR(SEARCH(J$1, $D70),0) >= 1, TRUE,FALSE) -> TRUE | K70: =IF(IFERROR(SEARCH(K$1, $D70),0) >= 1, TRUE,FALSE) -> FALSE | M70: TRUE | N70: TRUE | O70: FALSE | P70: FALSE | Q70: =IF(ISBLANK(A70),B70,A70) -> Kunsthal Extra City | R70: 7 | S70: FALSE | T70: TRUE | U70: 7
A71: Kunsthal Mechelen | B71: Kunsthal Malines | C71: Antwerpen | D71: Beeldende kunst | E71: =IF(IFERROR(SEARCH(E$1, $D71),0) >= 1, TRUE,FALSE) -> FALSE | F71: =IF(IFERROR(SEARCH(F$1, $D71),0) >= 1, TRUE,FALSE) -> FALSE | G71: =IF(IFERROR(SEARCH(G$1, $D71),0) >= 1, TRUE,FALSE) -> FALSE | H71: =IF(IFERROR(SEARCH(H$1, $D71),0) >= 1, TRUE,FALSE) -> FALSE | I71: =IF(IFERROR(SEARCH(I$1, $D71),0) >= 1, TRUE,FALSE) -> FALSE | J71: =IF(IFERROR(SEARCH(J$1, $D71),0) >= 1, TRUE,FALSE) -> TRUE | K71: =IF(IFERROR(SEARCH(K$1, $D71),0) >= 1, TRUE,FALSE) -> FALSE | M71: TRUE | N71: TRUE | O71: FALSE | P71: FALSE | Q71: =IF(ISBLANK(A71),B71,A71) -> Kunsthal Mechelen | R71: 5 | S71: FALSE | T71: TRUE | U71: 5
A72: MAS | Museum aan de Stroom | C72: Antwerpen | D72: Beeldende kunst, Toegepaste kunst en design, Geschiedenis en archeologie | E72: =IF(IFERROR(SEARCH(E$1, $D72),0) >= 1, TRUE,FALSE) -> TRUE | F72: =IF(IFERROR(SEARCH(F$1, $D72),0) >= 1, TRUE,FALSE) -> FALSE | G72: =IF(IFERROR(SEARCH(G$1, $D72),0) >= 1, TRUE,FALSE) -> FALSE | H72: =IF(IFERROR(SEARCH(H$1, $D72),0) >= 1, TRUE,FALSE) -> FALSE | I72: =IF(IFERROR(SEARCH(I$1, $D72),0) >= 1, TRUE,FALSE) -> FALSE | J72: =IF(IFERROR(SEARCH(J$1, $D72),0) >= 1, TRUE,FALSE) -> TRUE | K72: =IF(IFERROR(SEARCH(K$1, $D72),0) >= 1, TRUE,FALSE) -> TRUE | M72: TRUE | N72: TRUE | O72: FALSE | P72: TRUE | Q72: =IF(ISBLANK(A72),B72,A72) -> MAS | Museum aan de Stroom | R72: 10 | S72: FALSE | T72: TRUE | U72: 10
A73: M HKA | Museum van Hedendaagse Kunst Antwerpen | B73: Musée d’Art Contemporain d’Anvers | C73: Antwerpen | D73: Beeldende kunst, Toegepaste kunst en design | E73: =IF(IFERROR(SEARCH(E$1, $D73),0) >= 1, TRUE,FALSE) -> FALSE | F73: =IF(IFERROR(SEARCH(F$1, $D73),0) >= 1, TRUE,FALSE) -> FALSE | G73: =IF(IFERROR(SEARCH(G$1, $D73),0) >= 1, TRUE,FALSE) -> FALSE | H73: =IF(IFERROR(SEARCH(H$1, $D73),0) >= 1, TRUE,FALSE) -> FALSE | I73: =IF(IFERROR(SEARCH(I$1, $D73),0) >= 1, TRUE,FALSE) -> FALSE | J73: =IF(IFERROR(SEARCH(J$1, $D73),0) >= 1, TRUE,FALSE) -> TRUE | K73: =IF(IFERROR(SEARCH(K$1, $D73),0) >= 1, TRUE,FALSE) -> TRUE | M73: TRUE | N73: TRUE | O73: FALSE | P73: FALSE | Q73: =IF(ISBLANK(A73),B73,A73) -> M HKA | Museum van Hedendaagse Kunst Antwerpen | R73: 14 | S73: FALSE | T73: TRUE | U73: 14
A74: Middelheimmuseum | B74: Musée Middelheim | C74: Antwerpen | D74: Beeldende kunst, Toegepaste kunst en design | E74: =IF(IFERROR(SEARCH(E$1, $D74),0) >= 1, TRUE,FALSE) -> FALSE | F74: =IF(IFERROR(SEARCH(F$1, $D74),0) >= 1, TRUE,FALSE) -> FALSE | G74: =IF(IFERROR(SEARCH(G$1, $D74),0) >= 1, TRUE,FALSE) -> FALSE | H74: =IF(IFERROR(SEARCH(H$1, $D74),0) >= 1, TRUE,FALSE) -> FALSE | I74: =IF(IFERROR(SEARCH(I$1, $D74),0) >= 1, TRUE,FALSE) -> FALSE | J74: =IF(IFERROR(SEARCH(J$1, $D74),0) >= 1, TRUE,FALSE) -> TRUE | K74: =IF(IFERROR(SEARCH(K$1, $D74),0) >= 1, TRUE,FALSE) -> TRUE | M74: TRUE | N74: TRUE | O74: FALSE | P74: FALSE | Q74: =IF(ISBLANK(A74),B74,A74) -> Middelheimmuseum | R74: 0 | S74: FALSE | T74: TRUE | U74: 0
A75: MoMu | ModeMuseum Antwerpen | B75: Musée de la Mode Anvers | C75: Antwerpen | D75: Toegepaste kunst en design, Mode | E75: =IF(IFERROR(SEARCH(E$1, $D75),0) >= 1, TRUE,FALSE) -> FALSE | F75: =IF(IFERROR(SEARCH(F$1, $D75),0) >= 1, TRUE,FALSE) -> FALSE | G75: =IF(IFERROR(SEARCH(G$1, $D75),0) >= 1, TRUE,FALSE) -> TRUE | H75: =IF(IFERROR(SEARCH(H$1, $D75),0) >= 1, TRUE,FALSE) -> FALSE | I75: =IF(IFERROR(SEARCH(I$1, $D75),0) >= 1, TRUE,FALSE) -> FALSE | J75: =IF(IFERROR(SEARCH(J$1, $D75),0) >= 1, TRUE,FALSE) -> FALSE | K75: =IF(IFERROR(SEARCH(K$1, $D75),0) >= 1, TRUE,FALSE) -> TRUE | M75: TRUE | N75: TRUE | O75: FALSE | P75: FALSE | Q75: =IF(ISBLANK(A75),B75,A75) -> MoMu | ModeMuseum Antwerpen | R75: 12 | S75: FALSE | T75: TRUE | U75: 12
A76: Museum De Reede | B76: Musée De Reede | C76: Antwerpen | D76: Beeldende kunst | E76: =IF(IFERROR(SEARCH(E$1, $D76),0) >= 1, TRUE,FALSE) -> FALSE | F76: =IF(IFERROR(SEARCH(F$1, $D76),0) >= 1, TRUE,FALSE) -> FALSE | G76: =IF(IFERROR(SEARCH(G$1, $D76),0) >= 1, TRUE,FALSE) -> FALSE | H76: =IF(IFERROR(SEARCH(H$1, $D76),0) >= 1, TRUE,FALSE) -> FALSE | I76: =IF(IFERROR(SEARCH(I$1, $D76),0) >= 1, TRUE,FALSE) -> FALSE | J76: =IF(IFERROR(SEARCH(J$1, $D76),0) >= 1, TRUE,FALSE) -> TRUE | K76: =IF(IFERROR(SEARCH(K$1, $D76),0) >= 1, TRUE,FALSE) -> FALSE | M76: TRUE | N76: FALSE | O76: FALSE | P76: FALSE | Q76: =IF(ISBLANK(A76),B76,A76) -> Museum De Reede | R76: 15 | S76: FALSE | T76: TRUE | U76: 15
A77: Museum Fort Liezele | B77: Musée Fort Liezele | C77: Antwerpen | D77: Geschiedenis en archeologie | E77: =IF(IFERROR(SEARCH(E$1, $D77),0) >= 1, TRUE,FALSE) -> TRUE | F77: =IF(IFERROR(SEARCH(F$1, $D77),0) >= 1, TRUE,FALSE) -> FALSE | G77: =IF(IFERROR(SEARCH(G$1, $D77),0) >= 1, TRUE,FALSE) -> FALSE | H77: =IF(IFERROR(SEARCH(H$1, $D77),0) >= 1, TRUE,FALSE) -> FALSE | I77: =IF(IFERROR(SEARCH(I$1, $D77),0) >= 1, TRUE,FALSE) -> FALSE | J77: =IF(IFERROR(SEARCH(J$1, $D77),0) >= 1, TRUE,FALSE) -> FALSE | K77: =IF(IFERROR(SEARCH(K$1, $D77),0) >= 1, TRUE,FALSE) -> FALSE | M77: TRUE | N77: TRUE | O77: TRUE | P77: TRUE | Q77: =IF(ISBLANK(A77),B77,A77) -> Museum Fort Liezele | R77: 12 | S77: FALSE | T77: FALSE
A78: Museum Hof van Busleyden | C78: Antwerpen | D78: Geschiedenis en archeologie | E78: =IF(IFERROR(SEARCH(E$1, $D78),0) >= 1, TRUE,FALSE) -> TRUE | F78: =IF(IFERROR(SEARCH(F$1, $D78),0) >= 1, TRUE,FALSE) -> FALSE | G78: =IF(IFERROR(SEARCH(G$1, $D78),0) >= 1, TRUE,FALSE) -> FALSE | H78: =IF(IFERROR(SEARCH(H$1, $D78),0) >= 1, TRUE,FALSE) -> FALSE | I78: =IF(IFERROR(SEARCH(I$1, $D78),0) >= 1, TRUE,FALSE) -> FALSE | J78: =IF(IFERROR(SEARCH(J$1, $D78),0) >= 1, TRUE,FALSE) -> FALSE | K78: =IF(IFERROR(SEARCH(K$1, $D78),0) >= 1, TRUE,FALSE) -> FALSE | M78: TRUE | N78: TRUE | O78: FALSE | P78: FALSE | Q78: =IF(ISBLANK(A78),B78,A78) -> Museum Hof van Busleyden | R78: 15 | S78: FALSE | T78: TRUE | U78: 15
A79: Museum Mayer van den Bergh | B79: Musée Mayer van den Bergh | C79: Antwerpen | D79: Beeldende kunst, Geschiedenis en archeologie | E79: =IF(IFERROR(SEARCH(E$1, $D79),0) >= 1, TRUE,FALSE) -> TRUE | F79: =IF(IFERROR(SEARCH(F$1, $D79),0) >= 1, TRUE,FALSE) -> FALSE | G79: =IF(IFERROR(SEARCH(G$1, $D79),0) >= 1, TRUE,FALSE) -> FALSE | H79: =IF(IFERROR(SEARCH(H$1, $D79),0) >= 1, TRUE,FALSE) -> FALSE | I79: =IF(IFERROR(SEARCH(I$1, $D79),0) >= 1, TRUE,FALSE) -> FALSE | J79: =IF(IFERROR(SEARCH(J$1, $D79),0) >= 1, TRUE,FALSE) -> TRUE | K79: =IF(IFERROR(SEARCH(K$1, $D79),0) >= 1, TRUE,FALSE) -> FALSE | M79: TRUE | N79: FALSE | O79: FALSE | P79: FALSE | Q79: =IF(ISBLANK(A79),B79,A79) -> Museum Mayer van den Bergh | R79: 10 | S79: TRUE | T79: FALSE
A80: Museum Plantin-Moretus | B80: Musée Plantin-Moretus | C80: Antwerpen | D80: Beeldende kunst, Geschiedenis en archeologie, Wetenschap en technologie, Architectuur, Literatuur | E80: =IF(IFERROR(SEARCH(E$1, $D80),0) >= 1, TRUE,FALSE) -> TRUE | F80: =IF(IFERROR(SEARCH(F$1, $D80),0) >= 1, TRUE,FALSE) -> TRUE | G80: =IF(IFERROR(SEARCH(G$1, $D80),0) >= 1, TRUE,FALSE) -> FALSE | H80: =IF(IFERROR(SEARCH(H$1, $D80),0) >= 1, TRUE,FALSE) -> TRUE | I80: =IF(IFERROR(SEARCH(I$1, $D80),0) >= 1, TRUE,FALSE) -> TRUE | J80: =IF(IFERROR(SEARCH(J$1, $D80),0) >= 1, TRUE,FALSE) -> TRUE | K80: =IF(IFERROR(SEARCH(K$1, $D80),0) >= 1, TRUE,FALSE) -> FALSE | M80: TRUE | N80: FALSE | O80: FALSE | P80: FALSE | Q80: =IF(ISBLANK(A80),B80,A80) -> Museum Plantin-Moretus | R80: 12 | S80: FALSE | T80: TRUE | U80: 12
A81: Museum Vleeshuis | B81: Musée Vleeshuis | C81: Antwerpen | D81: Beeldende kunst, Geschiedenis en archeologie, Architectuur | E81: =IF(IFERROR(SEARCH(E$1, $D81),0) >= 1, TRUE,FALSE) -> TRUE | F81: =IF(IFERROR(SEARCH(F$1, $D81),0) >= 1, TRUE,FALSE) -> FALSE | G81: =IF(IFERROR(SEARCH(G$1, $D81),0) >= 1, TRUE,FALSE) -> FALSE | H81: =IF(IFERROR(SEARCH(H$1, $D81),0) >= 1, TRUE,FALSE) -> FALSE | I81: =IF(IFERROR(SEARCH(I$1, $D81),0) >= 1, TRUE,FALSE) -> TRUE | J81: =IF(IFERROR(SEARCH(J$1, $D81),0) >= 1, TRUE,FALSE) -> TRUE | K81: =IF(IFERROR(SEARCH(K$1, $D81),0) >= 1, TRUE,FALSE) -> FALSE | M81: TRUE | N81: FALSE | O81: FALSE | P81: FALSE | Q81: =IF(ISBLANK(A81),B81,A81) -> Museum Vleeshuis | R81: 8 | S81: TRUE | T81: FALSE
A82: Nationaal Museum van de Speelkaart | B82: Musée National de la Carte à jouer | C82: Antwerpen | D82: Geschiedenis en archeologie, Wetenschap en technologie | E82: =IF(IFERROR(SEARCH(E$1, $D82),0) >= 1, TRUE,FALSE) -> TRUE | F82: =IF(IFERROR(SEARCH(F$1, $D82),0) >= 1, TRUE,FALSE) -> TRUE | G82: =IF(IFERROR(SEARCH(G$1, $D82),0) >= 1, TRUE,FALSE) -> FALSE | H82: =IF(IFERROR(SEARCH(H$1, $D82),0) >= 1, TRUE,FALSE) -> FALSE | I82: =IF(IFERROR(SEARCH(I$1, $D82),0) >= 1, TRUE,FALSE) -> FALSE | J82: =IF(IFERROR(SEARCH(J$1, $D82),0) >= 1, TRUE,FALSE) -> FALSE | K82: =IF(IFERROR(SEARCH(K$1, $D82),0) >= 1, TRUE,FALSE) -> FALSE | M82: TRUE | N82: TRUE | O82: TRUE | P82: FALSE | Q82: =IF(ISBLANK(A82),B82,A82) -> Nationaal Museum van de Speelkaart | R82: 5 | S82: FALSE | T82: TRUE | U82: 5
A83: Red Star Line Museum | B83: Musée Red Star Line | C83: Antwerpen | D83: Geschiedenis en archeologie | E83: =IF(IFERROR(SEARCH(E$1, $D83),0) >= 1, TRUE,FALSE) -> TRUE | F83: =IF(IFERROR(SEARCH(F$1, $D83),0) >= 1, TRUE,FALSE) -> FALSE | G83: =IF(IFERROR(SEARCH(G$1, $D83),0) >= 1, TRUE,FALSE) -> FALSE | H83: =IF(IFERROR(SEARCH(H$1, $D83),0) >= 1, TRUE,FALSE) -> FALSE | I83: =IF(IFERROR(SEARCH(I$1, $D83),0) >= 1, TRUE,FALSE) -> FALSE | J83: =IF(IFERROR(SEARCH(J$1, $D83),0) >= 1, TRUE,FALSE) -> FALSE | K83: =IF(IFERROR(SEARCH(K$1, $D83),0) >= 1, TRUE,FALSE) -> FALSE | M83: TRUE | N83: TRUE | O83: FALSE | P83: FALSE | Q83: =IF(ISBLANK(A83),B83,A83) -> Red Star Line Museum | R83: 10 | S83: FALSE | T83: TRUE | U83: 0
A84: Rubenshuis | B84: Maison Rubens | C84: Antwerpen | D84: Beeldende kunst, Geschiedenis en archeologie | E84: =IF(IFERROR(SEARCH(E$1, $D84),0) >= 1, TRUE,FALSE) -> TRUE | F84: =IF(IFERROR(SEARCH(F$1, $D84),0) >= 1, TRUE,FALSE) -> FALSE | G84: =IF(IFERROR(SEARCH(G$1, $D84),0) >= 1, TRUE,FALSE) -> FALSE | H84: =IF(IFERROR(SEARCH(H$1, $D84),0) >= 1, TRUE,FALSE) -> FALSE | I84: =IF(IFERROR(SEARCH(I$1, $D84),0) >= 1, TRUE,FALSE) -> FALSE | J84: =IF(IFERROR(SEARCH(J$1, $D84),0) >= 1, TRUE,FALSE) -> TRUE | K84: =IF(IFERROR(SEARCH(K$1, $D84),0) >= 1, TRUE,FALSE) -> FALSE | M84: TRUE | N84: FALSE | O84: FALSE | P84: FALSE | Q84: =IF(ISBLANK(A84),B84,A84) -> Rubenshuis | R84: 12 | S84: FALSE | T84: TRUE | U84: 12
A85: Sint-Pauluskerk | B85: Église Saint-Paul | C85: Antwerpen | D85: Beeldende kunst, Toegepaste kunst en design, Geschiedenis en archeologie, Architectuur, Mode, Literatuur | E85: =IF(IFERROR(SEARCH(E$1, $D85),0) >= 1, TRUE,FALSE) -> TRUE | F85: =IF(IFERROR(SEARCH(F$1, $D85),0) >= 1, TRUE,FALSE) -> FALSE | G85: =IF(IFERROR(SEARCH(G$1, $D85),0) >= 1, TRUE,FALSE) -> TRUE | H85: =IF(IFERROR(SEARCH(H$1, $D85),0) >= 1, TRUE,FALSE) -> TRUE | I85: =IF(IFERROR(SEARCH(I$1, $D85),0) >= 1, TRUE,FALSE) -> TRUE | J85: =IF(IFERROR(SEARCH(J$1, $D85),0) >= 1, TRUE,FALSE) -> TRUE | K85: =IF(IFERROR(SEARCH(K$1, $D85),0) >= 1, TRUE,FALSE) -> TRUE | M85: TRUE | N85: FALSE | O85: FALSE | P85: FALSE | Q85: =IF(ISBLANK(A85),B85,A85) -> Sint-Pauluskerk | R85: 5 | S85: FALSE | T85: TRUE | U85: 5
A86: Speelgoedmuseum | B86: Musée du jouet | C86: Antwerpen | D86: Geschiedenis en archeologie, Wetenschap en technologie | E86: =IF(IFERROR(SEARCH(E$1, $D86),0) >= 1, TRUE,FALSE) -> TRUE | F86: =IF(IFERROR(SEARCH(F$1, $D86),0) >= 1, TRUE,FALSE) -> TRUE | G86: =IF(IFERROR(SEARCH(G$1, $D86),0) >= 1, TRUE,FALSE) -> FALSE | H86: =IF(IFERROR(SEARCH(H$1, $D86),0) >= 1, TRUE,FALSE) -> FALSE | I86: =IF(IFERROR(SEARCH(I$1, $D86),0) >= 1, TRUE,FALSE) -> FALSE | J86: =IF(IFERROR(SEARCH(J$1, $D86),0) >= 1, TRUE,FALSE) -> FALSE | K86: =IF(IFERROR(SEARCH(K$1, $D86),0) >= 1, TRUE,FALSE) -> FALSE | M86: TRUE | N86: TRUE | O86: TRUE | P86: FALSE | Q86: =IF(ISBLANK(A86),B86,A86) -> Speelgoedmuseum | R86: 17.5 | S86: FALSE | T86: FALSE
A87: Stadsmuseum Lier | B87: Musée de la Ville de Lier | C87: Antwerpen | D87: Beeldende kunst, Toegepaste kunst en design, Geschiedenis en archeologie, Wetenschap en technologie, Architectuur, Mode, Literatuur | E87: =IF(IFERROR(SEARCH(E$1, $D87),0) >= 1, TRUE,FALSE) -> TRUE | F87: =IF(IFERROR(SEARCH(F$1, $D87),0) >= 1, TRUE,FALSE) -> TRUE | G87: =IF(IFERROR(SEARCH(G$1, $D87),0) >= 1, TRUE,FALSE) -> TRUE | H87: =IF(IFERROR(SEARCH(H$1, $D87),0) >= 1, TRUE,FALSE) -> TRUE | I87: =IF(IFERROR(SEARCH(I$1, $D87),0) >= 1, TRUE,FALSE) -> TRUE | J87: =IF(IFERROR(SEARCH(J$1, $D87),0) >= 1, TRUE,FALSE) -> TRUE | K87: =IF(IFERROR(SEARCH(K$1, $D87),0) >= 1, TRUE,FALSE) -> TRUE | M87: TRUE | N87: FALSE | O87: FALSE | P87: FALSE | Q87: =IF(ISBLANK(A87),B87,A87) -> Stadsmuseum Lier | R87: 4 | S87: FALSE | T87: TRUE | U87: 4
A88: Stedelijk Museum Hoogstraten | B88: Musée Municipal de Hoogstraten | C88: Antwerpen | D88: Beeldende kunst, Geschiedenis en archeologie | E88: =IF(IFERROR(SEARCH(E$1, $D88),0) >= 1, TRUE,FALSE) -> TRUE | F88: =IF(IFERROR(SEARCH(F$1, $D88),0) >= 1, TRUE,FALSE) -> FALSE | G88: =IF(IFERROR(SEARCH(G$1, $D88),0) >= 1, TRUE,FALSE) -> FALSE | H88: =IF(IFERROR(SEARCH(H$1, $D88),0) >= 1, TRUE,FALSE) -> FALSE | I88: =IF(IFERROR(SEARCH(I$1, $D88),0) >= 1, TRUE,FALSE) -> FALSE | J88: =IF(IFERROR(SEARCH(J$1, $D88),0) >= 1, TRUE,FALSE) -> TRUE | K88: =IF(IFERROR(SEARCH(K$1, $D88),0) >= 1, TRUE,FALSE) -> FALSE | M88: TRUE | N88: FALSE | O88: FALSE | P88: FALSE | Q88: =IF(ISBLANK(A88),B88,A88) -> Stedelijk Museum Hoogstraten | R88: 0 | S88: FALSE | T88: TRUE | U88: 0
A89: Suske en Wiske Museum | B89: Musée Bob et Bobette | C89: Antwerpen | D89: Geschiedenis en archeologie, Literatuur | E89: =IF(IFERROR(SEARCH(E$1, $D89),0) >= 1, TRUE,FALSE) -> TRUE | F89: =IF(IFERROR(SEARCH(F$1, $D89),0) >= 1, TRUE,FALSE) -> FALSE | G89: =IF(IFERROR(SEARCH(G$1, $D89),0) >= 1, TRUE,FALSE) -> FALSE | H89: =IF(IFERROR(SEARCH(H$1, $D89),0) >= 1, TRUE,FALSE) -> TRUE | I89: =IF(IFERROR(SEARCH(I$1, $D89),0) >= 1, TRUE,FALSE) -> FALSE | J89: =IF(IFERROR(SEARCH(J$1, $D89),0) >= 1, TRUE,FALSE) -> FALSE | K89: =IF(IFERROR(SEARCH(K$1, $D89),0) >= 1, TRUE,FALSE) -> FALSE | M89: TRUE | N89: TRUE | O89: TRUE | P89: FALSE | Q89: =IF(ISBLANK(A89),B89,A89) -> Suske en Wiske Museum | R89: 15 | S89: FALSE | T89: FALSE
A90: Taxandriamuseum | C90: Antwerpen | D90: Beeldende kunst, Geschiedenis en archeologie, Architectuur | E90: =IF(IFERROR(SEARCH(E$1, $D90),0) >= 1, TRUE,FALSE) -> TRUE | F90: =IF(IFERROR(SEARCH(F$1, $D90),0) >= 1, TRUE,FALSE) -> FALSE | G90: =IF(IFERROR(SEARCH(G$1, $D90),0) >= 1, TRUE,FALSE) -> FALSE | H90: =IF(IFERROR(SEARCH(H$1, $D90),0) >= 1, TRUE,FALSE) -> FALSE | I90: =IF(IFERROR(SEARCH(I$1, $D90),0) >= 1, TRUE,FALSE) -> TRUE | J90: =IF(IFERROR(SEARCH(J$1, $D90),0) >= 1, TRUE,FALSE) -> TRUE | K90: =IF(IFERROR(SEARCH(K$1, $D90),0) >= 1, TRUE,FALSE) -> FALSE | M90: TRUE | N90: TRUE | O90: FALSE | P90: FALSE | Q90: =IF(ISBLANK(A90),B90,A90) -> Taxandriamuseum | R90: 5 | S90: FALSE | T90: TRUE | U90: 5
A91: ‘t Grom | C91: Antwerpen | D91: Geschiedenis en archeologie, Wetenschap en technologie | E91: =IF(IFERROR(SEARCH(E$1, $D91),0) >= 1, TRUE,FALSE) -> TRUE | F91: =IF(IFERROR(SEARCH(F$1, $D91),0) >= 1, TRUE,FALSE) -> TRUE | G91: =IF(IFERROR(SEARCH(G$1, $D91),0) >= 1, TRUE,FALSE) -> FALSE | H91: =IF(IFERROR(SEARCH(H$1, $D91),0) >= 1, TRUE,FALSE) -> FALSE | I91: =IF(IFERROR(SEARCH(I$1, $D91),0) >= 1, TRUE,FALSE) -> FALSE | J91: =IF(IFERROR(SEARCH(J$1, $D91),0) >= 1, TRUE,FALSE) -> FALSE | K91: =IF(IFERROR(SEARCH(K$1, $D91),0) >= 1, TRUE,FALSE) -> FALSE | M91: TRUE | N91: TRUE | O91: TRUE | P91: TRUE | Q91: =IF(ISBLANK(A91),B91,A91) -> ‘t Grom | R91: 7 | S91: FALSE | T91: TRUE | U91: 7
A92: Het steen, The Antwerp Story | C92: Antwerpen | D92: Toegepaste kunst en design, Geschiedenis en archeologie, Wetenschap en technologie, Architectuur, Mode | E92: =IF(IFERROR(SEARCH(E$1, $D92),0) >= 1, TRUE,FALSE) -> TRUE | F92: =IF(IFERROR(SEARCH(F$1, $D92),0) >= 1, TRUE,FALSE) -> TRUE | G92: =IF(IFERROR(SEARCH(G$1, $D92),0) >= 1, TRUE,FALSE) -> TRUE | H92: =IF(IFERROR(SEARCH(H$1, $D92),0) >= 1, TRUE,FALSE) -> FALSE | I92: =IF(IFERROR(SEARCH(I$1, $D92),0) >= 1, TRUE,FALSE) -> TRUE | J92: =IF(IFERROR(SEARCH(J$1, $D92),0) >= 1, TRUE,FALSE) -> FALSE | K92: =IF(IFERROR(SEARCH(K$1, $D92),0) >= 1, TRUE,FALSE) -> TRUE | M92: TRUE | N92: FALSE | O92: FALSE | P92: FALSE | Q92: =IF(ISBLANK(A92),B92,A92) -> Het steen, The Antwerp Story | R92: 7 | S92: FALSE | T92: TRUE | U92: 7
A93: Stichting Folon | B93: Fondation Folon | C93: Waals-Brabant | D93: Beeldende kunst | E93: =IF(IFERROR(SEARCH(E$1, $D93),0) >= 1, TRUE,FALSE) -> FALSE | F93: =IF(IFERROR(SEARCH(F$1, $D93),0) >= 1, TRUE,FALSE) -> FALSE | G93: =IF(IFERROR(SEARCH(G$1, $D93),0) >= 1, TRUE,FALSE) -> FALSE | H93: =IF(IFERROR(SEARCH(H$1, $D93),0) >= 1, TRUE,FALSE) -> FALSE | I93: =IF(IFERROR(SEARCH(I$1, $D93),0) >= 1, TRUE,FALSE) -> FALSE | J93: =IF(IFERROR(SEARCH(J$1, $D93),0) >= 1, TRUE,FALSE) -> TRUE | K93: =IF(IFERROR(SEARCH(K$1, $D93),0) >= 1, TRUE,FALSE) -> FALSE | M93: TRUE | N93: TRUE | O93: TRUE | P93: TRUE | Q93: =IF(ISBLANK(A93),B93,A93) -> Stichting Folon | R93: 12 | S93: FALSE | T93: TRUE | U93: 10
A94: Hergé Museum | B94: Musée Hergé | C94: Waals-Brabant | D94: Beeldende kunst | E94: =IF(IFERROR(SEARCH(E$1, $D94),0) >= 1, TRUE,FALSE) -> FALSE | F94: =IF(IFERROR(SEARCH(F$1, $D94),0) >= 1, TRUE,FALSE) -> FALSE | G94: =IF(IFERROR(SEARCH(G$1, $D94),0) >= 1, TRUE,FALSE) -> FALSE | H94: =IF(IFERROR(SEARCH(H$1, $D94),0) >= 1, TRUE,FALSE) -> FALSE | I94: =IF(IFERROR(SEARCH(I$1, $D94),0) >= 1, TRUE,FALSE) -> FALSE | J94: =IF(IFERROR(SEARCH(J$1, $D94),0) >= 1, TRUE,FALSE) -> TRUE | K94: =IF(IFERROR(SEARCH(K$1, $D94),0) >= 1, TRUE,FALSE) -> FALSE | M94: TRUE | N94: TRUE | O94: FALSE | P94: TRUE | Q94: =IF(ISBLANK(A94),B94,A94) -> Hergé Museum | R94: 12 | S94: FALSE | T94: TRUE | U94: 12
B95: Musée L | C95: Waals-Brabant | D95: Beeldende kunst | E95: =IF(IFERROR(SEARCH(E$1, $D95),0) >= 1, TRUE,FALSE) -> FALSE | F95: =IF(IFERROR(SEARCH(F$1, $D95),0) >= 1, TRUE,FALSE) -> FALSE | G95: =IF(IFERROR(SEARCH(G$1, $D95),0) >= 1, TRUE,FALSE) -> FALSE | H95: =IF(IFERROR(SEARCH(H$1, $D95),0) >= 1, TRUE,FALSE) -> FALSE | I95: =IF(IFERROR(SEARCH(I$1, $D95),0) >= 1, TRUE,FALSE) -> FALSE | J95: =IF(IFERROR(SEARCH(J$1, $D95),0) >= 1, TRUE,FALSE) -> TRUE | K95: =IF(IFERROR(SEARCH(K$1, $D95),0) >= 1, TRUE,FALSE) -> FALSE | M95: TRUE | N95: TRUE | O95: TRUE | P95: TRUE | Q95: =IF(ISBLANK(A95),B95,A95) -> Musée L | R95: 8 | S95: FALSE | T95: TRUE | U95: 8
A96: Marthe Donas museum | B96: MiMDo - Musée Marthe Donas | C96: Waals-Brabant | D96: Beeldende kunst | E96: =IF(IFERROR(SEARCH(E$1, $D96),0) >= 1, TRUE,FALSE) -> FALSE | F96: =IF(IFERROR(SEARCH(F$1, $D96),0) >= 1, TRUE,FALSE) -> FALSE | G96: =IF(IFERROR(SEARCH(G$1, $D96),0) >= 1, TRUE,FALSE) -> FALSE | H96: =IF(IFERROR(SEARCH(H$1, $D96),0) >= 1, TRUE,FALSE) -> FALSE | I96: =IF(IFERROR(SEARCH(I$1, $D96),0) >= 1, TRUE,FALSE) -> FALSE | J96: =IF(IFERROR(SEARCH(J$1, $D96),0) >= 1, TRUE,FALSE) -> TRUE | K96: =IF(IFERROR(SEARCH(K$1, $D96),0) >= 1, TRUE,FALSE) -> FALSE | M96: TRUE | N96: FALSE | O96: TRUE | P96: FALSE | Q96: =IF(ISBLANK(A96),B96,A96) -> Marthe Donas museum | R96: 2 | S96: FALSE | T96: TRUE | U96: 2
A97: Wellington Museum | B97: Musée Wellington | C97: Waals-Brabant | D97: Geschiedenis en archeologie | E97: =IF(IFERROR(SEARCH(E$1, $D97),0) >= 1, TRUE,FALSE) -> TRUE | F97: =IF(IFERROR(SEARCH(F$1, $D97),0) >= 1, TRUE,FALSE) -> FALSE | G97: =IF(IFERROR(SEARCH(G$1, $D97),0) >= 1, TRUE,FALSE) -> FALSE | H97: =IF(IFERROR(SEARCH(H$1, $D97),0) >= 1, TRUE,FALSE) -> FALSE | I97: =IF(IFERROR(SEARCH(I$1, $D97),0) >= 1, TRUE,FALSE) -> FALSE | J97: =IF(IFERROR(SEARCH(J$1, $D97),0) >= 1, TRUE,FALSE) -> FALSE | K97: =IF(IFERROR(SEARCH(K$1, $D97),0) >= 1, TRUE,FALSE) -> FALSE | M97: TRUE | N97: FALSE | O97: FALSE | P97: FALSE | Q97: =IF(ISBLANK(A97),B97,A97) -> Wellington Museum | R97: 10 | S97: FALSE | T97: TRUE | U97: 8
A98: AfricaMuseum | C98: Vlaams-Brabant | D98: Beeldende kunst, Geschiedenis en archeologie, Wetenschap en technologie | E98: =IF(IFERROR(SEARCH(E$1, $D98),0) >= 1, TRUE,FALSE) -> TRUE | F98: =IF(IFERROR(SEARCH(F$1, $D98),0) >= 1, TRUE,FALSE) -> TRUE | G98: =IF(IFERROR(SEARCH(G$1, $D98),0) >= 1, TRUE,FALSE) -> FALSE | H98: =IF(IFERROR(SEARCH(H$1, $D98),0) >= 1, TRUE,FALSE) -> FALSE | I98: =IF(IFERROR(SEARCH(I$1, $D98),0) >= 1, TRUE,FALSE) -> FALSE | J98: =IF(IFERROR(SEARCH(J$1, $D98),0) >= 1, TRUE,FALSE) -> TRUE | K98: =IF(IFERROR(SEARCH(K$1, $D98),0) >= 1, TRUE,FALSE) -> FALSE | M98: TRUE | N98: TRUE | O98: TRUE | P98: TRUE | Q98: =IF(ISBLANK(A98),B98,A98) -> AfricaMuseum | R98: 13 | S98: FALSE | T98: TRUE | U98: 13
A99: Damiaanmuseum | B99: Musée Damien | C99: Vlaams-Brabant | D99: Geschiedenis en archeologie | E99: =IF(IFERROR(SEARCH(E$1, $D99),0) >= 1, TRUE,FALSE) -> TRUE | F99: =IF(IFERROR(SEARCH(F$1, $D99),0) >= 1, TRUE,FALSE) -> FALSE | G99: =IF(IFERROR(SEARCH(G$1, $D99),0) >= 1, TRUE,FALSE) -> FALSE | H99: =IF(IFERROR(SEARCH(H$1, $D99),0) >= 1, TRUE,FALSE) -> FALSE | I99: =IF(IFERROR(SEARCH(I$1, $D99),0) >= 1, TRUE,FALSE) -> FALSE | J99: =IF(IFERROR(SEARCH(J$1, $D99),0) >= 1, TRUE,FALSE) -> FALSE | K99: =IF(IFERROR(SEARCH(K$1, $D99),0) >= 1, TRUE,FALSE) -> FALSE | M99: TRUE | N99: FALSE | O99: TRUE | P99: FALSE | Q99: =IF(ISBLANK(A99),B99,A99) -> Damiaanmuseum | R99: 7 | S99: FALSE | T99: FALSE
A100: Dru!f, huis van de tafeldruif | B100: maison du raisin de table | C100: Vlaams-Brabant | D100: Beeldende kunst, Geschiedenis en archeologie | E100: =IF(IFERROR(SEARCH(E$1, $D100),0) >= 1, TRUE,FALSE) -> TRUE | F100: =IF(IFERROR(SEARCH(F$1, $D100),0) >= 1, TRUE,FALSE) -> FALSE | G100: =IF(IFERROR(SEARCH(G$1, $D100),0) >= 1, TRUE,FALSE) -> FALSE | H100: =IF(IFERROR(SEARCH(H$1, $D100),0) >= 1, TRUE,FALSE) -> FALSE | I100: =IF(IFERROR(SEARCH(I$1, $D100),0) >= 1, TRUE,FALSE) -> FALSE | J100: =IF(IFERROR(SEARCH(J$1, $D100),0) >= 1, TRUE,FALSE) -> TRUE | K100: =IF(IFERROR(SEARCH(K$1, $D100),0) >= 1, TRUE,FALSE) -> FALSE | M100: TRUE | N100: FALSE | O100: FALSE | P100: TRUE | Q100: =IF(ISBLANK(A100),B100,A100) -> Dru!f, huis van de tafeldruif | R100: 0 | S100: FALSE | T100: TRUE | U100: 0
...

Sheet Blad13
A1: Antwerpen musea prijzen
A2: 8
A3: 5
A4: 12
A5: 0
A6: 12
A7: 12
A8: 12
A9: 10
A10: 5
A11: 6
A12: 12
A13: 20
... A36: 7

Sheet Matchmaker
A1: Musea - Nederlandse benaming (Title) | B1: Musea - Franse benaming (Alternative Title) | C1: Provincie | D1: Alle Thema's | E1: Geschiedenis en archeologie | F1: Wetenschap en technologie | G1: Mode | H1: Literatuur | I1: Architectuur | J1: Beeldende kunst | K1: Toegepaste kunst en design | L1: Shop | M1: Café | N1: Parking | O1: Restaurant | P1: Algemene naam --> als geen NL naam dan FR | Q1: Prijs | R1: Tijdelijk gesloten | S1: Tijdelijke tentoonstelling(en) | T1: Prijs incl. tijdelijke tentoonstelling | U1: PROVINCE RATING | AC1: THEME RATING | AD1: BUDGET RATING | AI1: FACILITIES RATING | AJ1: SUITABILITY RATING | AK1: WEIGHTED RATING | AL1: RATING | AM1: Profile | AN1: Answers (if more, split by comma) | AW1: Geschiedenis en archeologie | AX1: Wetenschap en technologie | AY1: Mode | AZ1: Literatuur | BA1: Architectuur | BB1: Beeldende kunst | BC1: Toegepaste kunst en design | BD1: Shop | BE1: Café | BF1: Parking | BG1: Restaurant | BH1: =CONCATENATE("Matches for ", AN2) -> Matches for Jozefien | CE1: =CONCATENATE("Closest Match for ",AN2) -> Closest Match for Jozefien
A2: Archeologisch museum van de Boven-Maas | B2: Musée archéologique de la Haute-Meuse | C2: Namen | D2: Geschiedenis en archeologie | E2: =If(IFERROR(SEARCH(E$1, $D2),0) >= 1, true,false) -> TRUE | F2: =If(IFERROR(SEARCH(F$1, $D2),0) >= 1, true,false) -> FALSE | G2: =If(IFERROR(SEARCH(G$1, $D2),0) >= 1, true,false) -> FALSE | H2: =If(IFERROR(SEARCH(H$1, $D2),0) >= 1, true,false) -> FALSE | I2: =If(IFERROR(SEARCH(I$1, $D2),0) >= 1, true,false) -> FALSE | J2: =If(IFERROR(SEARCH(J$1, $D2),0) >= 1, true,false) -> FALSE | K2: =If(IFERROR(SEARCH(K$1, $D2),0) >= 1, true,false) -> FALSE | L2: TRUE | M2: FALSE | N2: TRUE | O2: FALSE | P2: =IF(ISBLANK(A2),B2,A2) -> Archeologisch museum van de Boven-Maas | Q2: 3.5 | R2: FALSE | S2: FALSE | U2: =if(OR(C2 = $AO$3, C2 = $AQ$3), 1, 0) -> 0 | V2: =if(OR(AW2 = $AO$4, AW2 = $AQ$4), 1, 0) -> 1 | W2: =if(OR(AX2 = $AO$4, AX2 = $AQ$4), 1, 0) -> 0 | X2: =if(OR(AY2 = $AO$4, AY2 = $AQ$4), 1, 0) -> 0 | Y2: =if(OR(AZ2 = $AO$4, AZ2 = $AQ$4), 1, 0) -> 0 | Z2: =if(OR(BA2 = $AO$4, BA2 = $AQ$4), 1, 0) -> 0 | AA2: =if(OR(BB2 = $AO$4, BB2 = $AQ$4), 1, 0) -> 0 | AB2: =if(OR(BC2 = $AO$4, BC2 = $AQ$4), 1, 0) -> 0 | AC2: =SUM(V2:AB2) -> 1 | AD2: =if($Q2 <= $AN$5, 1, 0) -> 1 | AE2: =if(OR(BD2 = $AO$6, BD2 = $AS$6, BD2 = $AT$6, BD2 = $AU$6), 1, 0) -> 1 | AF2: =if(OR(BE2 = $AO$6, BE2 = $AS$6, BE2 = $AT$6, BE2 = $AU$6), 1, 0) -> 0 | AG2: =if(OR(BF2 = $AO$6, BF2 = $AS$6, BF2 = $AT$6, BF2 = $AU$6), 1, 0) -> 1 | AH2: =if(OR(BG2 = $AO$6, BG2 = $AS$6, BG2 = $AT$6, BG2 = $AU$6), 1, 0) -> 0 | AI2: =SUM(AE2:AH2) -> 2 | AJ2: =SUM(U2,AC2,AD2,AI2) -> 4 | AK2: =(AJ2/$AJ$264)*5 -> 2.5 | AL2: =IFS(4 < AK2 , "excellent", 2.5 < AK2, "good", 1 < AK2 , "subpar", 0 <= AK2, "no match") -> subpar | AM2: Name | AN2: Jozefien | AW2: =IF(IFERROR(SEARCH(E$1, $D2),0) >= 1, E$1,0) -> Geschiedenis en archeologie | AX2: =IF(IFERROR(SEARCH(F$1, $D2),0) >= 1, F$1,0) -> 0 | AY2: =IF(IFERROR(SEARCH(G$1, $D2),0) >= 1, G$1,0) -> 0 | AZ2: =IF(IFERROR(SEARCH(H$1, $D2),0) >= 1, H$1,0) -> 0 | BA2: =IF(IFERROR(SEARCH(I$1, $D2),0) >= 1, I$1,0) -> 0 | BB2: =IF(IFERROR(SEARCH(J$1, $D2),0) >= 1, J$1,0) -> 0 | BC2: =IF(IFERROR(SEARCH(K$1, $D2),0) >= 1, K$1,0) -> 0 | BD2: =IF(L2 = true, BD$1, 0) -> Shop | BE2: =IF(M2 = true, BE$1, 0) -> 0 | BF2: =IF(N2 = true, BF$1, 0) -> Parking | BG2: =IF(O2 = true, BG$1, 0) -> 0 | BH2: =IFERROR(__xludf.DUMMYFUNCTION("IF(AN7 = ""no preference"", SORT(P2:AL261, AK2:AK261, false) ,FILTER(P2:AL261, AL2:AL261 = AN7))"),"Atlantikwall Raversyde") -> Atlantikwall Raversyde | BI2: =IFERROR(__xludf.DUMMYFUNCTION("""COMPUTED_VALUE"""),10.0) -> 10 | BJ2: =IFERROR(__xludf.DUMMYFUNCTION("""COMPUTED_VALUE"""),FALSE) -> FALSE | BK2: =IFERROR(__xludf.DUMMYFUNCTION("""COMPUTED_VALUE"""),TRUE) -> TRUE | BL2: =IFERROR(__xludf.DUMMYFUNCTION("""COMPUTED_VALUE"""),10.0) -> 10 | BM2: =IFERROR(__xludf.DUMMYFUNCTION("""COMPUTED_VALUE"""),0.0) -> 0 | BN2: =IFERROR(__xludf.DUMMYFUNCTION("""COMPUTED_VALUE"""),1.0) -> 1 | BO2: =IFERROR(__xludf.DUMMYFUNCTION("""COMPUTED_VALUE"""),0.0) -> 0 | BP2: =IFERROR(__xludf.DUMMYFUNCTION("""COMPUTED_VALUE"""),0.0) -> 0 | BQ2: =IFERROR(__xludf.DUMMYFUNCTION("""COMPUTED_VALUE"""),0.0) -> 0 | BR2: =IFERROR(__xludf.DUMMYFUNCTION("""COMPUTED_VALUE"""),0.0) -> 0 | BS2: =IFERROR(__xludf.DUMMYFUNCTION("""COMPUTED_VALUE"""),1.0) -> 1 | BT2: =IFERROR(__xludf.DUMMYFUNCTION("""COMPUTED_VALUE"""),0.0) -> 0 | BU2: =IFERROR(__xludf.DUMMYFUNCTION("""COMPUTED_VALUE"""),2.0) -> 2 | BV2: =IFERROR(__xludf.DUMMYFUNCTION("""COMPUTED_VALUE"""),1.0) -> 1 | BW2: =IFERROR(__xludf.DUMMYFUNCTION("""COMPUTED_VALUE"""),1.0) -> 1 | BX2: =IFERROR(__xludf.DUMMYFUNCTION("""COMPUTED_VALUE"""),1.0) -> 1 | BY2: =IFERROR(__xludf.DUMMYFUNCTION("""COMPUTED_VALUE"""),1.0) -> 1 | BZ2: =IFERROR(__xludf.DUMMYFUNCTION("""COMPUTED_VALUE"""),1.0) -> 1 | CA2: =IFERROR(__xludf.DUMMYFUNCTION("""COMPUTED_VALUE"""),4.0) -> 4 | CB2: =IFERROR(__xludf.DUMMYFUNCTION("""COMPUTED_VALUE"""),7.0) -> 7 | CC2: =IFERROR(__xludf.DUMMYFUNCTION("""COMPUTED_VALUE"""),4.375) -> 4.375 | CD2: =IFERROR(__xludf.DUMMYFUNCTION("""COMPUTED_VALUE"""),"excellent") -> excellent | CE2: {=SORT(BH2:CD262, CC2:CC262, false)} -> Atlantikwall Raversyde | CF2: 10 | CG2: FALSE | CH2: TRUE | CI2: 10 | CJ2: 0 | CK2: 1 | CL2: 0 | CM2: 0 | CN2: 0 | CO2: 0 | CP2: 1 | CQ2: 0 | CR2: 2 | CS2: 1 | CT2: 1 | CU2: 1 | CV2: 1 | CW2: 1 | CX2: 4 | CY2: 7 | CZ2: 4.375 | DA2: excellent
A3: Citadel van Namen / Bezoekerscentrum Terra Nova en toeristentreintje | B3: =IFERROR(__xludf.DUMMYFUNCTION("SPLIT(A3, "" - "", FALSE,FALSE)"),"Citadel van Namen / Bezoekerscentrum Terra Nova en toeristentreintje") -> Citadel van Namen / Bezoekerscentrum Terra Nova en toeristentreintje | C3: Namen | D3: Geschiedenis en archeologie | E3: =If(IFERROR(SEARCH(E$1, $D3),0) >= 1, true,false) -> TRUE | F3: =If(IFERROR(SEARCH(F$1, $D3),0) >= 1, true,false) -> FALSE | G3: =If(IFERROR(SEARCH(G$1, $D3),0) >= 1, true,false) -> FALSE | H3: =If(IFERROR(SEARCH(H$1, $D3),0) >= 1, true,false) -> FALSE | I3: =If(IFERROR(SEARCH(I$1, $D3),0) >= 1, true,false) -> FALSE | J3: =If(IFERROR(SEARCH(J$1, $D3),0) >= 1, true,false) -> FALSE | K3: =If(IFERROR(SEARCH(K$1, $D3),0) >= 1, true,false) -> FALSE | L3: TRUE | M3: TRUE | N3: FALSE | O3: FALSE | P3: =IF(ISBLANK(A3),B3,A3) -> Citadel van Namen / Bezoekerscentrum Terra Nova en toeristentreintje | Q3: 6 | R3: FALSE | S3: FALSE | U3: =if(OR(C3 = $AO$3, C3 = $AQ$3), 1, 0) -> 0 | V3: =if(OR(AW3 = $AO$4, AW3 = $AQ$4), 1, 0) -> 1 | W3: =if(OR(AX3 = $AO$4, AX3 = $AQ$4), 1, 0) -> 0 | X3: =if(OR(AY3 = $AO$4, AY3 = $AQ$4), 1, 0) -> 0 | Y3: =if(OR(AZ3 = $AO$4, AZ3 = $AQ$4), 1, 0) -> 0 | Z3: =if(OR(BA3 = $AO$4, BA3 = $AQ$4), 1, 0) -> 0 | AA3: =if(OR(BB3 = $AO$4, BB3 = $AQ$4), 1, 0) -> 0 | AB3: =if(OR(BC3 = $AO$4, BC3 = $AQ$4), 1, 0) -> 0 | AC3: =SUM(V3:AB3) -> 1 | AD3: =if($Q3 <= $AN$5, 1, 0) -> 1 | AE3: =if(OR(BD3 = $AO$6, BD3 = $AS$6, BD3 = $AT$6, BD3 = $AU$6), 1, 0) -> 1 | AF3: =if(OR(BE3 = $AO$6, BE3 = $AS$6, BE3 = $AT$6, BE3 = $AU$6), 1, 0) -> 1 | AG3: =if(OR(BF3 = $AO$6, BF3 = $AS$6, BF3 = $AT$6, BF3 = $AU$6), 1, 0) -> 0 | AH3: =if(OR(BG3 = $AO$6, BG3 = $AS$6, BG3 = $AT$6, BG3 = $AU$6), 1, 0) -> 0 | AI3: =SUM(AE3:AH3) -> 2 | AJ3: =SUM(U3,AC3,AD3,AI3) -> 4 | AK3: =(AJ3/$AJ$264)*5 -> 2.5 | AL3: =IFS(4 < AK3 , "excellent", 2.5 < AK3, "good", 1 < AK3 , "subpar", 0 <= AK3, "no match") -> subpar | AM3: Province | AN3: Oost-Vlaanderen | AO3: =IFERROR(__xludf.DUMMYFUNCTION("SPLIT(AN3, "","")"),"Oost-Vlaanderen") -> Oost-Vlaanderen | AQ3: =TRIM(AP3) | AW3: =IF(IFERROR(SEARCH(E$1, $D3),0) >= 1, E$1,0) -> Geschiedenis en archeologie | AX3: =IF(IFERROR(SEARCH(F$1, $D3),0) >= 1, F$1,0) -> 0 | AY3: =IF(IFERROR(SEARCH(G$1, $D3),0) >= 1, G$1,0) -> 0 | AZ3: =IF(IFERROR(SEARCH(H$1, $D3),0) >= 1, H$1,0) -> 0 | BA3: =IF(IFERROR(SEARCH(I$1, $D3),0) >= 1, I$1,0) -> 0 | BB3: =IF(IFERROR(SEARCH(J$1, $D3),0) >= 1, J$1,0) -> 0 | BC3: =IF(IFERROR(SEARCH(K$1, $D3),0) >= 1, K$1,0) -> 0 | BD3: =IF(L3 = true, BD$1, 0) -> Shop | BE3: =IF(M3 = true, BE$1, 0) -> Café | BF3: =IF(N3 = true, BF$1, 0) -> 0 | BG3: =IF(O3 = true, BG$1, 0) -> 0 | BH3: =IFERROR(__xludf.DUMMYFUNCTION("""COMPUTED_VALUE"""),"Museum Dr. Guislain") -> Museum Dr. Guislain | BI3: =IFERROR(__xludf.DUMMYFUNCTION("""COMPUTED_VALUE"""),10.0) -> 10 | BJ3: =IFERROR(__xludf.DUMMYFUNCTION("""COMPUTED_VALUE"""),FALSE) -> FALSE | BK3: =IFERROR(__xludf.DUMMYFUNCTION("""COMPUTED_VALUE"""),TRUE) -> TRUE | BL3: =IFERROR(__xludf.DUMMYFUNCTION("""COMPUTED_VALUE"""),10.0) -> 10 | BM3: =IFERROR(__xludf.DUMMYFUNCTION("""COMPUTED_VALUE"""),1.0) -> 1 | BN3: =IFERROR(__xludf.DUMMYFUNCTION("""COMPUTED_VALUE"""),1.0) -> 1 | BO3: =IFERROR(__xludf.DUMMYFUNCTION("""COMPUTED_VALUE"""),0.0) -> 0 | BP3: =IFERROR(__xludf.DUMMYFUNCTION("""COMPUTED_VALUE"""),0.0) -> 0 | BQ3: =IFERROR(__xludf.DUMMYFUNCTION("""COMPUTED_VALUE"""),0.0) -> 0 | BR3: =IFERROR(__xludf.DUMMYFUNCTION("""COMPUTED_VALUE"""),0.0) -> 0 | BS3: =IFERROR(__xludf.DUMMYFUNCTION("""COMPUTED_VALUE"""),1.0) -> 1 | BT3: =IFERROR(__xludf.DUMMYFUNCTION("""COMPUTED_VALUE"""),0.0) -> 0 | BU3: =IFERROR(__xludf.DUMMYFUNCTION("""COMPUTED_VALUE"""),2.0) -> 2 | BV3: =IFERROR(__xludf.DUMMYFUNCTION("""COMPUTED_VALUE"""),1.0) -> 1 | BW3: =IFERROR(__xludf.DUMMYFUNCTION("""COMPUTED_VALUE"""),1.0) -> 1 | BX3: =IFERROR(__xludf.DUMMYFUNCTION("""COMPUTED_VALUE"""),1.0) -> 1 | BY3: =IFERROR(__xludf.DUMMYFUNCTION("""COMPUTED_VALUE"""),1.0) -> 1 | BZ3: =IFERROR(__xludf.DUMMYFUNCTION("""COMPUTED_VALUE"""),0.0) -> 0 | CA3: =IFERROR(__xludf.DUMMYFUNCTION("""COMPUTED_VALUE"""),3.0) -> 3 | CB3: =IFERROR(__xludf.DUMMYFUNCTION("""COMPUTED_VALUE"""),7.0) -> 7 | CC3: =IFERROR(__xludf.DUMMYFUNCTION("""COMPUTED_VALUE"""),4.375) -> 4.375 | CD3: =IFERROR(__xludf.DUMMYFUNCTION("""COMPUTED_VALUE"""),"excellent") -> excellent | CE3: Museum Dr. Guislain | CF3: 10 | CG3: FALSE | CH3: TRUE | CI3: 10 | CJ3: 1 | CK3: 1 | CL3: 0 | CM3: 0 | CN3: 0 | CO3: 0 | CP3: 1 | CQ3: 0 | CR3: 2 | CS3: 1 | CT3: 1 | CU3: 1 | CV3: 1 | CW3: 0 | CX3: 3 | CY3: 7 | CZ3: 4.375 | DA3: excellent
A4: NAM-IP Computermuseum | B4: Computer Museum NAM-IP | C4: Namen | D4: Wetenschap en technologie | E4: =If(IFERROR(SEARCH(E$1, $D4),0) >= 1, true,false) -> FALSE | F4: =If(IFERROR(SEARCH(F$1, $D4),0) >= 1, true,false) -> TRUE | G4: =If(IFERROR(SEARCH(G$1, $D4),0) >= 1, true,false) -> FALSE | H4: =If(IFERROR(SEARCH(H$1, $D4),0) >= 1, true,false) -> FALSE | I4: =If(IFERROR(SEARCH(I$1, $D4),0) >= 1, true,false) -> FALSE | J4: =If(IFERROR(SEARCH(J$1, $D4),0) >= 1, true,false) -> FALSE | K4: =If(IFERROR(SEARCH(K$1, $D4),0) >= 1, true,false) -> FALSE | L4: TRUE | M4: TRUE | N4: TRUE | O4: FALSE | P4: =IF(ISBLANK(A4),B4,A4) -> NAM-IP Computermuseum | Q4: 8 | R4: FALSE | S4: FALSE | U4: =if(OR(C4 = $AO$3, C4 = $AQ$3), 1, 0) -> 0 | V4: =if(OR(AW4 = $AO$4, AW4 = $AQ$4), 1, 0) -> 0 | W4: =if(OR(AX4 = $AO$4, AX4 = $AQ$4), 1, 0) -> 0 | X4: =if(OR(AY4 = $AO$4, AY4 = $AQ$4), 1, 0) -> 0 | Y4: =if(OR(AZ4 = $AO$4, AZ4 = $AQ$4), 1, 0) -> 0 | Z4: =if(OR(BA4 = $AO$4, BA4 = $AQ$4), 1, 0) -> 0 | AA4: =if(OR(BB4 = $AO$4, BB4 = $AQ$4), 1, 0) -> 0 | AB4: =if(OR(BC4 = $AO$4, BC4 = $AQ$4), 1, 0) -> 0 | AC4: =SUM(V4:AB4) -> 0 | AD4: =if($Q4 <= $AN$5, 1, 0) -> 1 | AE4: =if(OR(BD4 = $AO$6, BD4 = $AS$6, BD4 = $AT$6, BD4 = $AU$6), 1, 0) -> 1 | AF4: =if(OR(BE4 = $AO$6, BE4 = $AS$6, BE4 = $AT$6, BE4 = $AU$6), 1, 0) -> 1 | AG4: =if(OR(BF4 = $AO$6, BF4 = $AS$6, BF4 = $AT$6, BF4 = $AU$6), 1, 0) -> 1 | AH4: =if(OR(BG4 = $AO$6, BG4 = $AS$6, BG4 = $AT$6, BG4 = $AU$6), 1, 0) -> 0 | AI4: =SUM(AE4:AH4) -> 3 | AJ4: =SUM(U4,AC4,AD4,AI4) -> 4 | AK4: =(AJ4/$AJ$264)*5 -> 2.5 | AL4: =IFS(4 < AK4 , "excellent", 2.5 < AK4, "good", 1 < AK4 , "subpar", 0 <= AK4, "no match") -> subpar | AM4: Theme | AN4: Geschiedenis en archeologie, Beeldende Kunst | AO4: =IFERROR(__xludf.DUMMYFUNCTION("SPLIT(AN4, "","")"),"Geschiedenis en archeologie") -> Geschiedenis en archeologie | AP4: =IFERROR(__xludf.DUMMYFUNCTION("""COMPUTED_VALUE""")," Beeldende Kunst") -> Beeldende Kunst | AQ4: =TRIM(AP4) -> Beeldende Kunst | AW4: =IF(IFERROR(SEARCH(E$1, $D4),0) >= 1, E$1,0) -> 0 | AX4: =IF(IFERROR(SEARCH(F$1, $D4),0) >= 1, F$1,0) -> Wetenschap en technologie | AY4: =IF(IFERROR(SEARCH(G$1, $D4),0) >= 1, G$1,0) -> 0 | AZ4: =IF(IFERROR(SEARCH(H$1, $D4),0) >= 1, H$1,0) -> 0 | BA4: =IF(IFERROR(SEARCH(I$1, $D4),0) >= 1, I$1,0) -> 0 | BB4: =IF(IFERROR(SEARCH(J$1, $D4),0) >= 1, J$1,0) -> 0 | BC4: =IF(IFERROR(SEARCH(K$1, $D4),0) >= 1, K$1,0) -> 0 | BD4: =IF(L4 = true, BD$1, 0) -> Shop | BE4: =IF(M4 = true, BE$1, 0) -> Café | BF4: =IF(N4 = true, BF$1, 0) -> Parking | BG4: =IF(O4 = true, BG$1, 0) -> 0 | BH4: =IFERROR(__xludf.DUMMYFUNCTION("""COMPUTED_VALUE"""),"Bakkerijmuseum") -> Bakkerijmuseum | BI4: =IFERROR(__xludf.DUMMYFUNCTION("""COMPUTED_VALUE"""),8.0) -> 8 | BJ4: =IFERROR(__xludf.DUMMYFUNCTION("""COMPUTED_VALUE"""),FALSE) -> FALSE | BK4: =IFERROR(__xludf.DUMMYFUNCTION("""COMPUTED_VALUE"""),FALSE) -> FALSE | BM4: =IFERROR(__xludf.DUMMYFUNCTION("""COMPUTED_VALUE"""),0.0) -> 0 | BN4: =IFERROR(__xludf.DUMMYFUNCTION("""COMPUTED_VALUE"""),1.0) -> 1 | BO4: =IFERROR(__xludf.DUMMYFUNCTION("""COMPUTED_VALUE"""),0.0) -> 0 | BP4: =IFERROR(__xludf.DUMMYFUNCTION("""COMPUTED_VALUE"""),0.0) -> 0 | BQ4: =IFERROR(__xludf.DUMMYFUNCTION("""COMPUTED_VALUE"""),0.0) -> 0 | BR4: =IFERROR(__xludf.DUMMYFUNCTION("""COMPUTED_VALUE"""),0.0) -> 0 | BS4: =IFERROR(__xludf.DUMMYFUNCTION("""COMPUTED_VALUE"""),0.0) -> 0 | BT4: =IFERROR(__xludf.DUMMYFUNCTION("""COMPUTED_VALUE"""),0.0) -> 0 | BU4: =IFERROR(__xludf.DUMMYFUNCTION("""COMPUTED_VALUE"""),1.0) -> 1 | BV4: =IFERROR(__xludf.DUMMYFUNCTION("""COMPUTED_VALUE"""),1.0) -> 1 | BW4: =IFERROR(__xludf.DUMMYFUNCTION("""COMPUTED_VALUE"""),1.0) -> 1 | BX4: =IFERROR(__xludf.DUMMYFUNCTION("""COMPUTED_VALUE"""),1.0) -> 1 | BY4: =IFERROR(__xludf.DUMMYFUNCTION("""COMPUTED_VALUE"""),1.0) -> 1 | BZ4: =IFERROR(__xludf.DUMMYFUNCTION("""COMPUTED_VALUE"""),1.0) -> 1 | CA4: =IFERROR(__xludf.DUMMYFUNCTION("""COMPUTED_VALUE"""),4.0) -> 4 | CB4: =IFERROR(__xludf.DUMMYFUNCTION("""COMPUTED_VALUE"""),6.0) -> 6 | CC4: =IFERROR(__xludf.DUMMYFUNCTION("""COMPUTED_VALUE"""),3.75) -> 3.75 | CD4: =IFERROR(__xludf.DUMMYFUNCTION("""COMPUTED_VALUE"""),"good") -> good | CE4: Bakkerijmuseum | CF4: 8 | CG4: FALSE | CH4: FALSE | CJ4: 0 | CK4: 1 | CL4: 0 | CM4: 0 | CN4: 0 | CO4: 0 | CP4: 0 | CQ4: 0 | CR4: 1 | CS4: 1 | CT4: 1 | CU4: 1 | CV4: 1 | CW4: 1 | CX4: 4 | CY4: 6 | CZ4: 3.75 | DA4: good
A5: Ecomuseum van de Viroin | B5: Écomusée du Viroin | C5: Namen | D5: Geschiedenis en archeologie | E5: =If(IFERROR(SEARCH(E$1, $D5),0) >= 1, true,false) -> TRUE | F5: =If(IFERROR(SEARCH(F$1, $D5),0) >= 1, true,false) -> FALSE | G5: =If(IFERROR(SEARCH(G$1, $D5),0) >= 1, true,false) -> FALSE | H5: =If(IFERROR(SEARCH(H$1, $D5),0) >= 1, true,false) -> FALSE | I5: =If(IFERROR(SEARCH(I$1, $D5),0) >= 1, true,false) -> FALSE | J5: =If(IFERROR(SEARCH(J$1, $D5),0) >= 1, true,false) -> FALSE | K5: =If(IFERROR(SEARCH(K$1, $D5),0) >= 1, true,false) -> FALSE | L5: TRUE | M5: FALSE | N5: FALSE | O5: FALSE | P5: =IF(ISBLANK(A5),B5,A5) -> Ecomuseum van de Viroin | Q5: 4 | R5: FALSE | S5: TRUE | T5: 4 | U5: =if(OR(C5 = $AO$3, C5 = $AQ$3), 1, 0) -> 0 | V5: =if(OR(AW5 = $AO$4, AW5 = $AQ$4), 1, 0) -> 1 | W5: =if(OR(AX5 = $AO$4, AX5 = $AQ$4), 1, 0) -> 0 | X5: =if(OR(AY5 = $AO$4, AY5 = $AQ$4), 1, 0) -> 0 | Y5: =if(OR(AZ5 = $AO$4, AZ5 = $AQ$4), 1, 0) -> 0 | Z5: =if(OR(BA5 = $AO$4, BA5 = $AQ$4), 1, 0) -> 0 | AA5: =if(OR(BB5 = $AO$4, BB5 = $AQ$4), 1, 0) -> 0 | AB5: =if(OR(BC5 = $AO$4, BC5 = $AQ$4), 1, 0) -> 0 | AC5: =SUM(V5:AB5) -> 1 | AD5: =if($Q5 <= $AN$5, 1, 0) -> 1 | AE5: =if(OR(BD5 = $AO$6, BD5 = $AS$6, BD5 = $AT$6, BD5 = $AU$6), 1, 0) -> 1 | AF5: =if(OR(BE5 = $AO$6, BE5 = $AS$6, BE5 = $AT$6, BE5 = $AU$6), 1, 0) -> 0 | AG5: =if(OR(BF5 = $AO$6, BF5 = $AS$6, BF5 = $AT$6, BF5 = $AU$6), 1, 0) -> 0 | AH5: =if(OR(BG5 = $AO$6, BG5 = $AS$6, BG5 = $AT$6, BG5 = $AU$6), 1, 0) -> 0 | AI5: =SUM(AE5:AH5) -> 1 | AJ5: =SUM(U5,AC5,AD5,AI5) -> 3 | AK5: =(AJ5/$AJ$264)*5 -> 1.875 | AL5: =IFS(4 < AK5 , "excellent", 2.5 < AK5, "good", 1 < AK5 , "subpar", 0 <= AK5, "no match") -> subpar | AM5: Budget | AN5: 10 | AQ5: =TRIM(AP5) | AW5: =IF(IFERROR(SEARCH(E$1, $D5),0) >= 1, E$1,0) -> Geschiedenis en archeologie | AX5: =IF(IFERROR(SEARCH(F$1, $D5),0) >= 1, F$1,0) -> 0 | AY5: =IF(IFERROR(SEARCH(G$1, $D5),0) >= 1, G$1,0) -> 0 | AZ5: =IF(IFERROR(SEARCH(H$1, $D5),0) >= 1, H$1,0) -> 0 | BA5: =IF(IFERROR(SEARCH(I$1, $D5),0) >= 1, I$1,0) -> 0 | BB5: =IF(IFERROR(SEARCH(J$1, $D5),0) >= 1, J$1,0) -> 0 | BC5: =IF(IFERROR(SEARCH(K$1, $D5),0) >= 1, K$1,0) -> 0 | BD5: =IF(L5 = true, BD$1, 0) -> Shop | BE5: =IF(M5 = true, BE$1, 0) -> 0 | BF5: =IF(N5 = true, BF$1, 0) -> 0 | BG5: =IF(O5 = true, BG$1, 0) -> 0 | BH5: =IFERROR(__xludf.DUMMYFUNCTION("""COMPUTED_VALUE"""),"NAVIGO Visserijmuseum") -> NAVIGO Visserijmuseum | BI5: =IFERROR(__xludf.DUMMYFUNCTION("""COMPUTED_VALUE"""),10.0) -> 10 | BJ5: =IFERROR(__xludf.DUMMYFUNCTION("""COMPUTED_VALUE"""),FALSE) -> FALSE | BK5: =IFERROR(__xludf.DUMMYFUNCTION("""COMPUTED_VALUE"""),TRUE) -> TRUE | BL5: =IFERROR(__xludf.DUMMYFUNCTION("""COMPUTED_VALUE"""),0.0) -> 0 | BM5: =IFERROR(__xludf.DUMMYFUNCTION("""COMPUTED_VALUE"""),0.0) -> 0 | BN5: =IFERROR(__xludf.DUMMYFUNCTION("""COMPUTED_VALUE"""),0.0) -> 0 | BO5: =IFERROR(__xludf.DUMMYFUNCTION("""COMPUTED_VALUE"""),0.0) -> 0 | BP5: =IFERROR(__xludf.DUMMYFUNCTION("""COMPUTED_VALUE"""),0.0) -> 0 | BQ5: =IFERROR(__xludf.DUMMYFUNCTION("""COMPUTED_VALUE"""),0.0) -> 0 | BR5: =IFERROR(__xludf.DUMMYFUNCTION("""COMPUTED_VALUE"""),0.0) -> 0 | BS5: =IFERROR(__xludf.DUMMYFUNCTION("""COMPUTED_VALUE"""),1.0) -> 1 | BT5: =IFERROR(__xludf.DUMMYFUNCTION("""COMPUTED_VALUE"""),0.0) -> 0 | BU5: =IFERROR(__xludf.DUMMYFUNCTION("""COMPUTED_VALUE"""),1.0) -> 1 | BV5: =IFERROR(__xludf.DUMMYFUNCTION("""COMPUTED_VALUE"""),1.0) -> 1 | BW5: =IFERROR(__xludf.DUMMYFUNCTION("""COMPUTED_VALUE"""),1.0) -> 1 | BX5: =IFERROR(__xludf.DUMMYFUNCTION("""COMPUTED_VALUE"""),1.0) -> 1 | BY5: =IFERROR(__xludf.DUMMYFUNCTION("""COMPUTED_VALUE"""),1.0) -> 1 | BZ5: =IFERROR(__xludf.DUMMYFUNCTION("""COMPUTED_VALUE"""),1.0) -> 1 | CA5: =IFERROR(__xludf.DUMMYFUNCTION("""COMPUTED_VALUE"""),4.0) -> 4 | CB5: =IFERROR(__xludf.DUMMYFUNCTION("""COMPUTED_VALUE"""),6.0) -> 6 | CC5: =IFERROR(__xludf.DUMMYFUNCTION("""COMPUTED_VALUE"""),3.75) -> 3.75 | CD5: =IFERROR(__xludf.DUMMYFUNCTION("""COMPUTED_VALUE"""),"good") -> good | CE5: NAVIGO Visserijmuseum | CF5: 10 | CG5: FALSE | CH5: TRUE | CI5: 0 | CJ5: 0 | CK5: 0 | CL5: 0 | CM5: 0 | CN5: 0 | CO5: 0 | CP5: 1 | CQ5: 0 | CR5: 1 | CS5: 1 | CT5: 1 | CU5: 1 | CV5: 1 | CW5: 1 | CX5: 4 | CY5: 6 | CZ5: 3.75 | DA5: good
A6: Andenne Museum | B6: Espace Muséal d’Andenne | C6: Namen | D6: Toegepaste kunst en design, Geschiedenis en archeologie | E6: =If(IFERROR(SEARCH(E$1, $D6),0) >= 1, true,false) -> TRUE | F6: =If(IFERROR(SEARCH(F$1, $D6),0) >= 1, true,false) -> FALSE | G6: =If(IFERROR(SEARCH(G$1, $D6),0) >= 1, true,false) -> FALSE | H6: =If(IFERROR(SEARCH(H$1, $D6),0) >= 1, true,false) -> FALSE | I6: =If(IFERROR(SEARCH(I$1, $D6),0) >= 1, true,false) -> FALSE | J6: =If(IFERROR(SEARCH(J$1, $D6),0) >= 1, true,false) -> FALSE | K6: =If(IFERROR(SEARCH(K$1, $D6),0) >= 1, true,false) -> TRUE | L6: TRUE | M6: FALSE | N6: FALSE | O6: FALSE | P6: =IF(ISBLANK(A6),B6,A6) -> Andenne Museum | Q6: 10 | R6: FALSE | S6: FALSE | U6: =if(OR(C6 = $AO$3, C6 = $AQ$3), 1, 0) -> 0 | V6: =if(OR(AW6 = $AO$4, AW6 = $AQ$4), 1, 0) -> 1 | W6: =if(OR(AX6 = $AO$4, AX6 = $AQ$4), 1, 0) -> 0 | X6: =if(OR(AY6 = $AO$4, AY6 = $AQ$4), 1, 0) -> 0 | Y6: =if(OR(AZ6 = $AO$4, AZ6 = $AQ$4), 1, 0) -> 0 | Z6: =if(OR(BA6 = $AO$4, BA6 = $AQ$4), 1, 0) -> 0 | AA6: =if(OR(BB6 = $AO$4, BB6 = $AQ$4), 1, 0) -> 0 | AB6: =if(OR(BC6 = $AO$4, BC6 = $AQ$4), 1, 0) -> 0 | AC6: =SUM(V6:AB6) -> 1 | AD6: =if($Q6 <= $AN$5, 1, 0) -> 1 | AE6: =if(OR(BD6 = $AO$6, BD6 = $AS$6, BD6 = $AT$6, BD6 = $AU$6), 1, 0) -> 1 | AF6: =if(OR(BE6 = $AO$6, BE6 = $AS$6, BE6 = $AT$6, BE6 = $AU$6), 1, 0) -> 0 | AG6: =if(OR(BF6 = $AO$6, BF6 = $AS$6, BF6 = $AT$6, BF6 = $AU$6), 1, 0) -> 0 | AH6: =if(OR(BG6 = $AO$6, BG6 = $AS$6, BG6 = $AT$6, BG6 = $AU$6), 1, 0) -> 0 | AI6: =SUM(AE6:AH6) -> 1 | AJ6: =SUM(U6,AC6,AD6,AI6) -> 3 | AK6: =(AJ6/$AJ$264)*5 -> 1.875 | AL6: =IFS(4 < AK6 , "excellent", 2.5 < AK6, "good", 1 < AK6 , "subpar", 0 <= AK6, "no match") -> subpar | AM6: Facilities | AN6: Shop, Parking, Restaurant, Café | AO6: =IFERROR(__xludf.DUMMYFUNCTION("SPLIT(AN6, "","")"),"Shop") -> Shop | AP6: =IFERROR(__xludf.DUMMYFUNCTION("""COMPUTED_VALUE""")," Parking") -> Parking | AQ6: =IFERROR(__xludf.DUMMYFUNCTION("""COMPUTED_VALUE""")," Restaurant") -> Restaurant | AR6: =IFERROR(__xludf.DUMMYFUNCTION("""COMPUTED_VALUE""")," Café") -> Café | AS6: =TRIM(AP6) -> Parking | AT6: =TRIM(AQ6) -> Restaurant | AU6: =TRIM(AR6) -> Café | AW6: =IF(IFERROR(SEARCH(E$1, $D6),0) >= 1, E$1,0) -> Geschiedenis en archeologie | AX6: =IF(IFERROR(SEARCH(F$1, $D6),0) >= 1, F$1,0) -> 0 | AY6: =IF(IFERROR(SEARCH(G$1, $D6),0) >= 1, G$1,0) -> 0 | AZ6: =IF(IFERROR(SEARCH(H$1, $D6),0) >= 1, H$1,0) -> 0 | BA6: =IF(IFERROR(SEARCH(I$1, $D6),0) >= 1, I$1,0) -> 0 | BB6: =IF(IFERROR(SEARCH(J$1, $D6),0) >= 1, J$1,0) -> 0 | BC6: =IF(IFERROR(SEARCH(K$1, $D6),0) >= 1, K$1,0) -> Toegepaste kunst en design | BD6: =IF(L6 = true, BD$1, 0) -> Shop | BE6: =IF(M6 = true, BE$1, 0) -> 0 | BF6: =IF(N6 = true, BF$1, 0) -> 0 | BG6: =IF(O6 = true, BG$1, 0) -> 0 | BH6: =IFERROR(__xludf.DUMMYFUNCTION("""COMPUTED_VALUE"""),"Karrenmuseum Essen") -> Karrenmuseum Essen | BI6: =IFERROR(__xludf.DUMMYFUNCTION("""COMPUTED_VALUE"""),6.0) -> 6 | BJ6: =IFERROR(__xludf.DUMMYFUNCTION("""COMPUTED_VALUE"""),FALSE) -> FALSE | BK6: =IFERROR(__xludf.DUMMYFUNCTION("""COMPUTED_VALUE"""),FALSE) -> FALSE | BM6: =IFERROR(__xludf.DUMMYFUNCTION("""COMPUTED_VALUE"""),0.0) -> 0 | BN6: =IFERROR(__xludf.DUMMYFUNCTION("""COMPUTED_VALUE"""),1.0) -> 1 | BO6: =IFERROR(__xludf.DUMMYFUNCTION("""COMPUTED_VALUE"""),0.0) -> 0 | BP6: =IFERROR(__xludf.DUMMYFUNCTION("""COMPUTED_VALUE"""),0.0) -> 0 | BQ6: =IFERROR(__xludf.DUMMYFUNCTION("""COMPUTED_VALUE"""),0.0) -> 0 | BR6: =IFERROR(__xludf.DUMMYFUNCTION("""COMPUTED_VALUE"""),0.0) -> 0 | BS6: =IFERROR(__xludf.DUMMYFUNCTION("""COMPUTED_VALUE"""),0.0) -> 0 | BT6: =IFERROR(__xludf.DUMMYFUNCTION("""COMPUTED_VALUE"""),0.0) -> 0 | BU6: =IFERROR(__xludf.DUMMYFUNCTION("""COMPUTED_VALUE"""),1.0) -> 1 | BV6: =IFERROR(__xludf.DUMMYFUNCTION("""COMPUTED_VALUE"""),1.0) -> 1 | BW6: =IFERROR(__xludf.DUMMYFUNCTION("""COMPUTED_VALUE"""),1.0) -> 1 | BX6: =IFERROR(__xludf.DUMMYFUNCTION("""COMPUTED_VALUE"""),1.0) -> 1 | BY6: =IFERROR(__xludf.DUMMYFUNCTION("""COMPUTED_VALUE"""),1.0) -> 1 | BZ6: =IFERROR(__xludf.DUMMYFUNCTION("""COMPUTED_VALUE"""),1.0) -> 1 | CA6: =IFERROR(__xludf.DUMMYFUNCTION("""COMPUTED_VALUE"""),4.0) -> 4 | CB6: =IFERROR(__xludf.DUMMYFUNCTION("""COMPUTED_VALUE"""),6.0) -> 6 | CC6: =IFERROR(__xludf.DUMMYFUNCTION("""COMPUTED_VALUE"""),3.75) -> 3.75 | CD6: =IFERROR(__xludf.DUMMYFUNCTION("""COMPUTED_VALUE"""),"good") -> good | CE6: Karrenmuseum Essen | CF6: 6 | CG6: FALSE | CH6: FALSE | CJ6: 0 | CK6: 1 | CL6: 0 | CM6: 0 | CN6: 0 | CO6: 0 | CP6: 0 | CQ6: 0 | CR6: 1 | CS6: 1 | CT6: 1 | CU6: 1 | CV6: 1 | CW6: 1 | CX6: 4 | CY6: 6 | CZ6: 3.75 | DA6: good
B7: Le Delta | C7: Namen | D7: Beeldende kunst | E7: =If(IFERROR(SEARCH(E$1, $D7),0) >= 1, true,false) -> FALSE | F7: =If(IFERROR(SEARCH(F$1, $D7),0) >= 1, true,false) -> FALSE | G7: =If(IFERROR(SEARCH(G$1, $D7),0) >= 1, true,false) -> FALSE | H7: =If(IFERROR(SEARCH(H$1, $D7),0) >= 1, true,false) -> FALSE | I7: =If(IFERROR(SEARCH(I$1, $D7),0) >= 1, true,false) -> FALSE | J7: =If(IFERROR(SEARCH(J$1, $D7),0) >= 1, true,false) -> TRUE | K7: =If(IFERROR(SEARCH(K$1, $D7),0) >= 1, true,false) -> FALSE | L7: TRUE | M7: FALSE | N7: FALSE | O7: TRUE | P7: =IF(ISBLANK(A7),B7,A7) -> Le Delta | Q7: 5 | R7: FALSE | S7: TRUE | T7: 5 | U7: =if(OR(C7 = $AO$3, C7 = $AQ$3), 1, 0) -> 0 | V7: =if(OR(AW7 = $AO$4, AW7 = $AQ$4), 1, 0) -> 0 | W7: =if(OR(AX7 = $AO$4, AX7 = $AQ$4), 1, 0) -> 0 | X7: =if(OR(AY7 = $AO$4, AY7 = $AQ$4), 1, 0) -> 0 | Y7: =if(OR(AZ7 = $AO$4, AZ7 = $AQ$4), 1, 0) -> 0 | Z7: =if(OR(BA7 = $AO$4, BA7 = $AQ$4), 1, 0) -> 0 | AA7: =if(OR(BB7 = $AO$4, BB7 = $AQ$4), 1, 0) -> 1 | AB7: =if(OR(BC7 = $AO$4, BC7 = $AQ$4), 1, 0) -> 0 | AC7: =SUM(V7:AB7) -> 1 | AD7: =if($Q7 <= $AN$5, 1, 0) -> 1 | AE7: =if(OR(BD7 = $AO$6, BD7 = $AS$6, BD7 = $AT$6, BD7 = $AU$6), 1, 0) -> 1 | AF7: =if(OR(BE7 = $AO$6, BE7 = $AS$6, BE7 = $AT$6, BE7 = $AU$6), 1, 0) -> 0 | AG7: =if(OR(BF7 = $AO$6, BF7 = $AS$6, BF7 = $AT$6, BF7 = $AU$6), 1, 0) -> 0 | AH7: =if(OR(BG7 = $AO$6, BG7 = $AS$6, BG7 = $AT$6, BG7 = $AU$6), 1, 0) -> 1 | AI7: =SUM(AE7:AH7) -> 2 | AJ7: =SUM(U7,AC7,AD7,AI7) -> 4 | AK7: =(AJ7/$AJ$264)*5 -> 2.5 | AL7: =IFS(4 < AK7 , "excellent", 2.5 < AK7, "good", 1 < AK7 , "subpar", 0 <= AK7, "no match") -> subpar | AM7: Desired rating | AN7: no preference | AW7: =IF(IFERROR(SEARCH(E$1, $D7),0) >= 1, E$1,0) -> 0 | AX7: =IF(IFERROR(SEARCH(F$1, $D7),0) >= 1, F$1,0) -> 0 | AY7: =IF(IFERROR(SEARCH(G$1, $D7),0) >= 1, G$1,0) -> 0 | AZ7: =IF(IFERROR(SEARCH(H$1, $D7),0) >= 1, H$1,0) -> 0 | BA7: =IF(IFERROR(SEARCH(I$1, $D7),0) >= 1, I$1,0) -> 0 | BB7: =IF(IFERROR(SEARCH(J$1, $D7),0) >= 1, J$1,0) -> Beeldende kunst | BC7: =IF(IFERROR(SEARCH(K$1, $D7),0) >= 1, K$1,0) -> 0 | BD7: =IF(L7 = true, BD$1, 0) -> Shop | BE7: =IF(M7 = true, BE$1, 0) -> 0 | BF7: =IF(N7 = true, BF$1, 0) -> 0 | BG7: =IF(O7 = true, BG$1, 0) -> Restaurant | BH7: =IFERROR(__xludf.DUMMYFUNCTION("""COMPUTED_VALUE"""),"MAS | Museum aan de Stroom") -> MAS | Museum aan de Stroom | BI7: =IFERROR(__xludf.DUMMYFUNCTION("""COMPUTED_VALUE"""),10.0) -> 10 | BJ7: =IFERROR(__xludf.DUMMYFUNCTION("""COMPUTED_VALUE"""),FALSE) -> FALSE | BK7: =IFERROR(__xludf.DUMMYFUNCTION("""COMPUTED_VALUE"""),TRUE) -> TRUE | BL7: =IFERROR(__xludf.DUMMYFUNCTION("""COMPUTED_VALUE"""),10.0) -> 10 | BM7: =IFERROR(__xludf.DUMMYFUNCTION("""COMPUTED_VALUE"""),0.0) -> 0 | BN7: =IFERROR(__xludf.DUMMYFUNCTION("""COMPUTED_VALUE"""),1.0) -> 1 | BO7: =IFERROR(__xludf.DUMMYFUNCTION("""COMPUTED_VALUE"""),0.0) -> 0 | BP7: =IFERROR(__xludf.DUMMYFUNCTION("""COMPUTED_VALUE"""),0.0) -> 0 | BQ7: =IFERROR(__xludf.DUMMYFUNCTION("""COMPUTED_VALUE"""),0.0) -> 0 | BR7: =IFERROR(__xludf.DUMMYFUNCTION("""COMPUTED_VALUE"""),0.0) -> 0 | BS7: =IFERROR(__xludf.DUMMYFUNCTION("""COMPUTED_VALUE"""),1.0) -> 1 | BT7: =IFERROR(__xludf.DUMMYFUNCTION("""COMPUTED_VALUE"""),0.0) -> 0 | BU7: =IFERROR(__xludf.DUMMYFUNCTION("""COMPUTED_VALUE"""),2.0) -> 2 | BV7: =IFERROR(__xludf.DUMMYFUNCTION("""COMPUTED_VALUE"""),1.0) -> 1 | BW7: =IFERROR(__xludf.DUMMYFUNCTION("""COMPUTED_VALUE"""),1.0) -> 1 | BX7: =IFERROR(__xludf.DUMMYFUNCTION("""COMPUTED_VALUE"""),1.0) -> 1 | BY7: =IFERROR(__xludf.DUMMYFUNCTION("""COMPUTED_VALUE"""),0.0) -> 0 | BZ7: =IFERROR(__xludf.DUMMYFUNCTION("""COMPUTED_VALUE"""),1.0) -> 1 | CA7: =IFERROR(__xludf.DUMMYFUNCTION("""COMPUTED_VALUE"""),3.0) -> 3 | CB7: =IFERROR(__xludf.DUMMYFUNCTION("""COMPUTED_VALUE"""),6.0) -> 6 | CC7: =IFERROR(__xludf.DUMMYFUNCTION("""COMPUTED_VALUE"""),3.75) -> 3.75 | CD7: =IFERROR(__xludf.DUMMYFUNCTION("""COMPUTED_VALUE"""),"good") -> good | CE7: MAS | Museum aan de Stroom | CF7: 10 | CG7: FALSE | CH7: TRUE | CI7: 10 | CJ7: 0 | CK7: 1 | CL7: 0 | CM7: 0 | CN7: 0 | CO7: 0 | CP7: 1 | CQ7: 0 | CR7: 2 | CS7: 1 | CT7: 1 | CU7: 1 | CV7: 0 | CW7: 1 | CX7: 3 | CY7: 6 | CZ7: 3.75 | DA7: good
B8: Le Pavillon | C8: Namen | D8: Beeldende kunst, Wetenschap en technologie | E8: =If(IFERROR(SEARCH(E$1, $D8),0) >= 1, true,false) -> FALSE | F8: =If(IFERROR(SEARCH(F$1, $D8),0) >= 1, true,false) -> TRUE | G8: =If(IFERROR(SEARCH(G$1, $D8),0) >= 1, true,false) -> FALSE | H8: =If(IFERROR(SEARCH(H$1, $D8),0) >= 1, true,false) -> FALSE | I8: =If(IFERROR(SEARCH(I$1, $D8),0) >= 1, true,false) -> FALSE | J8: =If(IFERROR(SEARCH(J$1, $D8),0) >= 1, true,false) -> TRUE | K8: =If(IFERROR(SEARCH(K$1, $D8),0) >= 1, true,false) -> FALSE | L8: TRUE | M8: FALSE | N8: FALSE | O8: FALSE | P8: =IF(ISBLANK(A8),B8,A8) -> Le Pavillon | Q8: 10 | R8: FALSE | S8: TRUE | T8: 10 | U8: =if(OR(C8 = $AO$3, C8 = $AQ$3), 1, 0) -> 0 | V8: =if(OR(AW8 = $AO$4, AW8 = $AQ$4), 1, 0) -> 0 | W8: =if(OR(AX8 = $AO$4, AX8 = $AQ$4), 1, 0) -> 0 | X8: =if(OR(AY8 = $AO$4, AY8 = $AQ$4), 1, 0) -> 0 | Y8: =if(OR(AZ8 = $AO$4, AZ8 = $AQ$4), 1, 0) -> 0 | Z8: =if(OR(BA8 = $AO$4, BA8 = $AQ$4), 1, 0) -> 0 | AA8: =if(OR(BB8 = $AO$4, BB8 = $AQ$4), 1, 0) -> 1 | AB8: =if(OR(BC8 = $AO$4, BC8 = $AQ$4), 1, 0) -> 0 | AC8: =SUM(V8:AB8) -> 1 | AD8: =if($Q8 <= $AN$5, 1, 0) -> 1 | AE8: =if(OR(BD8 = $AO$6, BD8 = $AS$6, BD8 = $AT$6, BD8 = $AU$6), 1, 0) -> 1 | AF8: =if(OR(BE8 = $AO$6, BE8 = $AS$6, BE8 = $AT$6, BE8 = $AU$6), 1, 0) -> 0 | AG8: =if(OR(BF8 = $AO$6, BF8 = $AS$6, BF8 = $AT$6, BF8 = $AU$6), 1, 0) -> 0 | AH8: =if(OR(BG8 = $AO$6, BG8 = $AS$6, BG8 = $AT$6, BG8 = $AU$6), 1, 0) -> 0 | AI8: =SUM(AE8:AH8) -> 1 | AJ8: =SUM(U8,AC8,AD8,AI8) -> 3 | AK8: =(AJ8/$AJ$264)*5 -> 1.875 | AL8: =IFS(4 < AK8 , "excellent", 2.5 < AK8, "good", 1 < AK8 , "subpar", 0 <= AK8, "no match") -> subpar | AW8: =IF(IFERROR(SEARCH(E$1, $D8),0) >= 1, E$1,0) -> 0 | AX8: =IF(IFERROR(SEARCH(F$1, $D8),0) >= 1, F$1,0) -> Wetenschap en technologie | AY8: =IF(IFERROR(SEARCH(G$1, $D8),0) >= 1, G$1,0) -> 0 | AZ8: =IF(IFERROR(SEARCH(H$1, $D8),0) >= 1, H$1,0) -> 0 | BA8: =IF(IFERROR(SEARCH(I$1, $D8),0) >= 1, I$1,0) -> 0 | BB8: =IF(IFERROR(SEARCH(J$1, $D8),0) >= 1, J$1,0) -> Beeldende kunst | BC8: =IF(IFERROR(SEARCH(K$1, $D8),0) >= 1, K$1,0) -> 0 | BD8: =IF(L8 = true, BD$1, 0) -> Shop | BE8: =IF(M8 = true, BE$1, 0) -> 0 | BF8: =IF(N8 = true, BF$1, 0) -> 0 | BG8: =IF(O8 = true, BG$1, 0) -> 0 | BH8: =IFERROR(__xludf.DUMMYFUNCTION("""COMPUTED_VALUE"""),"‘t Grom") -> ‘t Grom | BI8: =IFERROR(__xludf.DUMMYFUNCTION("""COMPUTED_VALUE"""),7.0) -> 7 | BJ8: =IFERROR(__xludf.DUMMYFUNCTION("""COMPUTED_VALUE"""),FALSE) -> FALSE | BK8: =IFERROR(__xludf.DUMMYFUNCTION("""COMPUTED_VALUE"""),TRUE) -> TRUE | BL8: =IFERROR(__xludf.DUMMYFUNCTION("""COMPUTED_VALUE"""),7.0) -> 7 | BM8: =IFERROR(__xludf.DUMMYFUNCTION("""COMPUTED_VALUE"""),0.0) -> 0 | BN8: =IFERROR(__xludf.DUMMYFUNCTION("""COMPUTED_VALUE"""),1.0) -> 1 | BO8: =IFERROR(__xludf.DUMMYFUNCTION("""COMPUTED_VALUE"""),0.0) -> 0 | BP8: =IFERROR(__xludf.DUMMYFUNCTION("""COMPUTED_VALUE"""),0.0) -> 0 | BQ8: =IFERROR(__xludf.DUMMYFUNCTION("""COMPUTED_VALUE"""),0.0) -> 0 | BR8: =IFERROR(__xludf.DUMMYFUNCTION("""COMPUTED_VALUE"""),0.0) -> 0 | BS8: =IFERROR(__xludf.DUMMYFUNCTION("""COMPUTED_VALUE"""),0.0) -> 0 | BT8: =IFERROR(__xludf.DUMMYFUNCTION("""COMPUTED_VALUE"""),0.0) -> 0 | BU8: =IFERROR(__xludf.DUMMYFUNCTION("""COMPUTED_VALUE"""),1.0) -> 1 | BV8: =IFERROR(__xludf.DUMMYFUNCTION("""COMPUTED_VALUE"""),1.0) -> 1 | BW8: =IFERROR(__xludf.DUMMYFUNCTION("""COMPUTED_VALUE"""),1.0) -> 1 | BX8: =IFERROR(__xludf.DUMMYFUNCTION("""COMPUTED_VALUE"""),1.0) -> 1 | BY8: =IFERROR(__xludf.DUMMYFUNCTION("""COMPUTED_VALUE"""),1.0) -> 1 | BZ8: =IFERROR(__xludf.DUMMYFUNCTION("""COMPUTED_VALUE"""),1.0) -> 1 | CA8: =IFERROR(__xludf.DUMMYFUNCTION("""COMPUTED_VALUE"""),4.0) -> 4 | CB8: =IFERROR(__xludf.DUMMYFUNCTION("""COMPUTED_VALUE"""),6.0) -> 6 | CC8: =IFERROR(__xludf.DUMMYFUNCTION("""COMPUTED_VALUE"""),3.75) -> 3.75 | CD8: =IFERROR(__xludf.DUMMYFUNCTION("""COMPUTED_VALUE"""),"good") -> good | CE8: ‘t Grom | CF8: 7 | CG8: FALSE | CH8: TRUE | CI8: 7 | CJ8: 0 | CK8: 1 | CL8: 0 | CM8: 0 | CN8: 0 | CO8: 0 | CP8: 0 | CQ8: 0 | CR8: 1 | CS8: 1 | CT8: 1 | CU8: 1 | CV8: 1 | CW8: 1 | CX8: 4 | CY8: 6 | CZ8: 3.75 | DA8: good
B9: Maison du patrimoine médiéval mosan | C9: Namen | D9: Geschiedenis en archeologie | E9: =If(IFERROR(SEARCH(E$1, $D9),0) >= 1, true,false) -> TRUE | F9: =If(IFERROR(SEARCH(F$1, $D9),0) >= 1, true,false) -> FALSE | G9: =If(IFERROR(SEARCH(G$1, $D9),0) >= 1, true,false) -> FALSE | H9: =If(IFERROR(SEARCH(H$1, $D9),0) >= 1, true,false) -> FALSE | I9: =If(IFERROR(SEARCH(I$1, $D9),0) >= 1, true,false) -> FALSE | J9: =If(IFERROR(SEARCH(J$1, $D9),0) >= 1, true,false) -> FALSE | K9: =If(IFERROR(SEARCH(K$1, $D9),0) >= 1, true,false) -> FALSE | L9: TRUE | M9: FALSE | N9: TRUE | O9: FALSE | P9: =IF(ISBLANK(A9),B9,A9) -> Maison du patrimoine médiéval mosan | Q9: 6 | R9: FALSE | S9: TRUE | T9: 6 | U9: =if(OR(C9 = $AO$3, C9 = $AQ$3), 1, 0) -> 0 | V9: =if(OR(AW9 = $AO$4, AW9 = $AQ$4), 1, 0) -> 1 | W9: =if(OR(AX9 = $AO$4, AX9 = $AQ$4), 1, 0) -> 0 | X9: =if(OR(AY9 = $AO$4, AY9 = $AQ$4), 1, 0) -> 0 | Y9: =if(OR(AZ9 = $AO$4, AZ9 = $AQ$4), 1, 0) -> 0 | Z9: =if(OR(BA9 = $AO$4, BA9 = $AQ$4), 1, 0) -> 0 | AA9: =if(OR(BB9 = $AO$4, BB9 = $AQ$4), 1, 0) -> 0 | AB9: =if(OR(BC9 = $AO$4, BC9 = $AQ$4), 1, 0) -> 0 | AC9: =SUM(V9:AB9) -> 1 | AD9: =if($Q9 <= $AN$5, 1, 0) -> 1 | AE9: =if(OR(BD9 = $AO$6, BD9 = $AS$6, BD9 = $AT$6, BD9 = $AU$6), 1, 0) -> 1 | AF9: =if(OR(BE9 = $AO$6, BE9 = $AS$6, BE9 = $AT$6, BE9 = $AU$6), 1, 0) -> 0 | AG9: =if(OR(BF9 = $AO$6, BF9 = $AS$6, BF9 = $AT$6, BF9 = $AU$6), 1, 0) -> 1 | AH9: =if(OR(BG9 = $AO$6, BG9 = $AS$6, BG9 = $AT$6, BG9 = $AU$6), 1, 0) -> 0 | AI9: =SUM(AE9:AH9) -> 2 | AJ9: =SUM(U9,AC9,AD9,AI9) -> 4 | AK9: =(AJ9/$AJ$264)*5 -> 2.5 | AL9: =IFS(4 < AK9 , "excellent", 2.5 < AK9, "good", 1 < AK9 , "subpar", 0 <= AK9, "no match") -> subpar | AW9: =IF(IFERROR(SEARCH(E$1, $D9),0) >= 1, E$1,0) -> Geschiedenis en archeologie | AX9: =IF(IFERROR(SEARCH(F$1, $D9),0) >= 1, F$1,0) -> 0 | AY9: =IF(IFERROR(SEARCH(G$1, $D9),0) >= 1, G$1,0) -> 0 | AZ9: =IF(IFERROR(SEARCH(H$1, $D9),0) >= 1, H$1,0) -> 0 | BA9: =IF(IFERROR(SEARCH(I$1, $D9),0) >= 1, I$1,0) -> 0 | BB9: =IF(IFERROR(SEARCH(J$1, $D9),0) >= 1, J$1,0) -> 0 | BC9: =IF(IFERROR(SEARCH(K$1, $D9),0) >= 1, K$1,0) -> 0 | BD9: =IF(L9 = true, BD$1, 0) -> Shop | BE9: =IF(M9 = true, BE$1, 0) -> 0 | BF9: =IF(N9 = true, BF$1, 0) -> Parking | BG9: =IF(O9 = true, BG$1, 0) -> 0 | BH9: =IFERROR(__xludf.DUMMYFUNCTION("""COMPUTED_VALUE"""),"Musée L") -> Musée L | BI9: =IFERROR(__xludf.DUMMYFUNCTION("""COMPUTED_VALUE"""),8.0) -> 8 | BJ9: =IFERROR(__xludf.DUMMYFUNCTION("""COMPUTED_VALUE"""),FALSE) -> FALSE | BK9: =IFERROR(__xludf.DUMMYFUNCTION("""COMPUTED_VALUE"""),TRUE) -> TRUE | BL9: =IFERROR(__xludf.DUMMYFUNCTION("""COMPUTED_VALUE"""),8.0) -> 8 | BM9: =IFERROR(__xludf.DUMMYFUNCTION("""COMPUTED_VALUE"""),0.0) -> 0 | BN9: =IFERROR(__xludf.DUMMYFUNCTION("""COMPUTED_VALUE"""),0.0) -> 0 | BO9: =IFERROR(__xludf.DUMMYFUNCTION("""COMPUTED_VALUE"""),0.0) -> 0 | BP9: =IFERROR(__xludf.DUMMYFUNCTION("""COMPUTED_VALUE"""),0.0) -> 0 | BQ9: =IFERROR(__xludf.DUMMYFUNCTION("""COMPUTED_VALUE"""),0.0) -> 0 | BR9: =IFERROR(__xludf.DUMMYFUNCTION("""COMPUTED_VALUE"""),0.0) -> 0 | BS9: =IFERROR(__xludf.DUMMYFUNCTION("""COMPUTED_VALUE"""),1.0) -> 1 | BT9: =IFERROR(__xludf.DUMMYFUNCTION("""COMPUTED_VALUE"""),0.0) -> 0 | BU9: =IFERROR(__xludf.DUMMYFUNCTION("""COMPUTED_VALUE"""),1.0) -> 1 | BV9: =IFERROR(__xludf.DUMMYFUNCTION("""COMPUTED_VALUE"""),1.0) -> 1 | BW9: =IFERROR(__xludf.DUMMYFUNCTION("""COMPUTED_VALUE"""),1.0) -> 1 | BX9: =IFERROR(__xludf.DUMMYFUNCTION("""COMPUTED_VALUE"""),1.0) -> 1 | BY9: =IFERROR(__xludf.DUMMYFUNCTION("""COMPUTED_VALUE"""),1.0) -> 1 | BZ9: =IFERROR(__xludf.DUMMYFUNCTION("""COMPUTED_VALUE"""),1.0) -> 1 | CA9: =IFERROR(__xludf.DUMMYFUNCTION("""COMPUTED_VALUE"""),4.0) -> 4 | CB9: =IFERROR(__xludf.DUMMYFUNCTION("""COMPUTED_VALUE"""),6.0) -> 6 | CC9: =IFERROR(__xludf.DUMMYFUNCTION("""COMPUTED_VALUE"""),3.75) -> 3.75 | CD9: =IFERROR(__xludf.DUMMYFUNCTION("""COMPUTED_VALUE"""),"good") -> good | CE9: Musée L | CF9: 8 | CG9: FALSE | CH9: TRUE | CI9: 8 | CJ9: 0 | CK9: 0 | CL9: 0 | CM9: 0 | CN9: 0 | CO9: 0 | CP9: 1 | CQ9: 0 | CR9: 1 | CS9: 1 | CT9: 1 | CU9: 1 | CV9: 1 | CW9: 1 | CX9: 4 | CY9: 6 | CZ9: 3.75 | DA9: good
A10: Archeopark van Rochefort | B10: Malagne | Archéoparc de Rochefort | C10: Namen | D10: Geschiedenis en archeologie | E10: =If(IFERROR(SEARCH(E$1, $D10),0) >= 1, true,false) -> TRUE | F10: =If(IFERROR(SEARCH(F$1, $D10),0) >= 1, true,false) -> FALSE | G10: =If(IFERROR(SEARCH(G$1, $D10),0) >= 1, true,false) -> FALSE | H10: =If(IFERROR(SEARCH(H$1, $D10),0) >= 1, true,false) -> FALSE | I10: =If(IFERROR(SEARCH(I$1, $D10),0) >= 1, true,false) -> FALSE | J10: =If(IFERROR(SEARCH(J$1, $D10),0) >= 1, true,false) -> FALSE | K10: =If(IFERROR(SEARCH(K$1, $D10),0) >= 1, true,false) -> FALSE | L10: TRUE | M10: TRUE | N10: TRUE | O10: FALSE | P10: =IF(ISBLANK(A10),B10,A10) -> Archeopark van Rochefort | Q10: 8 | R10: FALSE | S10: FALSE | U10: =if(OR(C10 = $AO$3, C10 = $AQ$3), 1, 0) -> 0 | V10: =if(OR(AW10 = $AO$4, AW10 = $AQ$4), 1, 0) -> 1 | W10: =if(OR(AX10 = $AO$4, AX10 = $AQ$4), 1, 0) -> 0 | X10: =if(OR(AY10 = $AO$4, AY10 = $AQ$4), 1, 0) -> 0 | Y10: =if(OR(AZ10 = $AO$4, AZ10 = $AQ$4), 1, 0) -> 0 | Z10: =if(OR(BA10 = $AO$4, BA10 = $AQ$4), 1, 0) -> 0 | AA10: =if(OR(BB10 = $AO$4, BB10 = $AQ$4), 1, 0) -> 0 | AB10: =if(OR(BC10 = $AO$4, BC10 = $AQ$4), 1, 0) -> 0 | AC10: =SUM(V10:AB10) -> 1 | AD10: =if($Q10 <= $AN$5, 1, 0) -> 1 | AE10: =if(OR(BD10 = $AO$6, BD10 = $AS$6, BD10 = $AT$6, BD10 = $AU$6), 1, 0) -> 1 | AF10: =if(OR(BE10 = $AO$6, BE10 = $AS$6, BE10 = $AT$6, BE10 = $AU$6), 1, 0) -> 1 | AG10: =if(OR(BF10 = $AO$6, BF10 = $AS$6, BF10 = $AT$6, BF10 = $AU$6), 1, 0) -> 1 | AH10: =if(OR(BG10 = $AO$6, BG10 = $AS$6, BG10 = $AT$6, BG10 = $AU$6), 1, 0) -> 0 | AI10: =SUM(AE10:AH10) -> 3 | AJ10: =SUM(U10,AC10,AD10,AI10) -> 5 | AK10: =(AJ10/$AJ$264)*5 -> 3.125 | AL10: =IFS(4 < AK10 , "excellent", 2.5 < AK10, "good", 1 < AK10 , "subpar", 0 <= AK10, "no match") -> good | AW10: =IF(IFERROR(SEARCH(E$1, $D10),0) >= 1, E$1,0) -> Geschiedenis en archeologie | AX10: =IF(IFERROR(SEARCH(F$1, $D10),0) >= 1, F$1,0) -> 0 | AY10: =IF(IFERROR(SEARCH(G$1, $D10),0) >= 1, G$1,0) -> 0 | AZ10: =IF(IFERROR(SEARCH(H$1, $D10),0) >= 1, H$1,0) -> 0 | BA10: =IF(IFERROR(SEARCH(I$1, $D10),0) >= 1, I$1,0) -> 0 | BB10: =IF(IFERROR(SEARCH(J$1, $D10),0) >= 1, J$1,0) -> 0 | BC10: =IF(IFERROR(SEARCH(K$1, $D10),0) >= 1, K$1,0) -> 0 | BD10: =IF(L10 = true, BD$1, 0) -> Shop | BE10: =IF(M10 = true, BE$1, 0) -> Café | BF10: =IF(N10 = true, BF$1, 0) -> Parking | BG10: =IF(O10 = true, BG$1, 0) -> 0 | BH10: =IFERROR(__xludf.DUMMYFUNCTION("""COMPUTED_VALUE"""),"AfricaMuseum") -> AfricaMuseum | BI10: =IFERROR(__xludf.DUMMYFUNCTION("""COMPUTED_VALUE"""),13.0) -> 13 | BJ10: =IFERROR(__xludf.DUMMYFUNCTION("""COMPUTED_VALUE"""),FALSE) -> FALSE | BK10: =IFERROR(__xludf.DUMMYFUNCTION("""COMPUTED_VALUE"""),TRUE) -> TRUE | BL10: =IFERROR(__xludf.DUMMYFUNCTION("""COMPUTED_VALUE"""),13.0) -> 13 | BM10: =IFERROR(__xludf.DUMMYFUNCTION("""COMPUTED_VALUE"""),0.0) -> 0 | BN10: =IFERROR(__xludf.DUMMYFUNCTION("""COMPUTED_VALUE"""),1.0) -> 1 | BO10: =IFERROR(__xludf.DUMMYFUNCTION("""COMPUTED_VALUE"""),0.0) -> 0 | BP10: =IFERROR(__xludf.DUMMYFUNCTION("""COMPUTED_VALUE"""),0.0) -> 0 | BQ10: =IFERROR(__xludf.DUMMYFUNCTION("""COMPUTED_VALUE"""),0.0) -> 0 | BR10: =IFERROR(__xludf.DUMMYFUNCTION("""COMPUTED_VALUE"""),0.0) -> 0 | BS10: =IFERROR(__xludf.DUMMYFUNCTION("""COMPUTED_VALUE"""),1.0) -> 1 | BT10: =IFERROR(__xludf.DUMMYFUNCTION("""COMPUTED_VALUE"""),0.0) -> 0 | BU10: =IFERROR(__xludf.DUMMYFUNCTION("""COMPUTED_VALUE"""),2.0) -> 2 | BV10: =IFERROR(__xludf.DUMMYFUNCTION("""COMPUTED_VALUE"""),0.0) -> 0 | BW10: =IFERROR(__xludf.DUMMYFUNCTION("""COMPUTED_VALUE"""),1.0) -> 1 | BX10: =IFERROR(__xludf.DUMMYFUNCTION("""COMPUTED_VALUE"""),1.0) -> 1 | BY10: =IFERROR(__xludf.DUMMYFUNCTION("""COMPUTED_VALUE"""),1.0) -> 1 | BZ10: =IFERROR(__xludf.DUMMYFUNCTION("""COMPUTED_VALUE"""),1.0) -> 1 | CA10: =IFERROR(__xludf.DUMMYFUNCTION("""COMPUTED_VALUE"""),4.0) -> 4 | CB10: =IFERROR(__xludf.DUMMYFUNCTION("""COMPUTED_VALUE"""),6.0) -> 6 | CC10: =IFERROR(__xludf.DUMMYFUNCTION("""COMPUTED_VALUE"""),3.75) -> 3.75 | CD10: =IFERROR(__xludf.DUMMYFUNCTION("""COMPUTED_VALUE"""),"good") -> good | CE10: AfricaMuseum | CF10: 13 | CG10: FALSE | CH10: TRUE | CI10: 13 | CJ10: 0 | CK10: 1 | CL10: 0 | CM10: 0 | CN10: 0 | CO10: 0 | CP10: 1 | CQ10: 0 | CR10: 2 | CS10: 0 | CT10: 1 | CU10: 1 | CV10: 1 | CW10: 1 | CX10: 4 | CY10: 6 | CZ10: 3.75 | DA10: good
A11: MusAfrica Namen | B11: MusAfrica Namur | C11: Namen | D11: Toegepaste kunst en design, Geschiedenis en archeologie | E11: =If(IFERROR(SEARCH(E$1, $D11),0) >= 1, true,false) -> TRUE | F11: =If(IFERROR(SEARCH(F$1, $D11),0) >= 1, true,false) -> FALSE | G11: =If(IFERROR(SEARCH(G$1, $D11),0) >= 1, true,false) -> FALSE | H11: =If(IFERROR(SEARCH(H$1, $D11),0) >= 1, true,false) -> FALSE | I11: =If(IFERROR(SEARCH(I$1, $D11),0) >= 1, true,false) -> FALSE | J11: =If(IFERROR(SEARCH(J$1, $D11),0) >= 1, true,false) -> FALSE | K11: =If(IFERROR(SEARCH(K$1, $D11),0) >= 1, true,false) -> TRUE | L11: TRUE | M11: FALSE | N11: FALSE | O11: FALSE | P11: =IF(ISBLANK(A11),B11,A11) -> MusAfrica Namen | Q11: 8 | R11: FALSE | S11: FALSE | U11: =if(OR(C11 = $AO$3, C11 = $AQ$3), 1, 0) -> 0 | V11: =if(OR(AW11 = $AO$4, AW11 = $AQ$4), 1, 0) -> 1 | W11: =if(OR(AX11 = $AO$4, AX11 = $AQ$4), 1, 0) -> 0 | X11: =if(OR(AY11 = $AO$4, AY11 = $AQ$4), 1, 0) -> 0 | Y11: =if(OR(AZ11 = $AO$4, AZ11 = $AQ$4), 1, 0) -> 0 | Z11: =if(OR(BA11 = $AO$4, BA11 = $AQ$4), 1, 0) -> 0 | AA11: =if(OR(BB11 = $AO$4, BB11 = $AQ$4), 1, 0) -> 0 | AB11: =if(OR(BC11 = $AO$4, BC11 = $AQ$4), 1, 0) -> 0 | AC11: =SUM(V11:AB11) -> 1 | AD11: =if($Q11 <= $AN$5, 1, 0) -> 1 | AE11: =if(OR(BD11 = $AO$6, BD11 = $AS$6, BD11 = $AT$6, BD11 = $AU$6), 1, 0) -> 1 | AF11: =if(OR(BE11 = $AO$6, BE11 = $AS$6, BE11 = $AT$6, BE11 = $AU$6), 1, 0) -> 0 | AG11: =if(OR(BF11 = $AO$6, BF11 = $AS$6, BF11 = $AT$6, BF11 = $AU$6), 1, 0) -> 0 | AH11: =if(OR(BG11 = $AO$6, BG11 = $AS$6, BG11 = $AT$6, BG11 = $AU$6), 1, 0) -> 0 | AI11: =SUM(AE11:AH11) -> 1 | AJ11: =SUM(U11,AC11,AD11,AI11) -> 3 | AK11: =(AJ11/$AJ$264)*5 -> 1.875 | AL11: =IFS(4 < AK11 , "excellent", 2.5 < AK11, "good", 1 < AK11 , "subpar", 0 <= AK11, "no match") -> subpar | AW11: =IF(IFERROR(SEARCH(E$1, $D11),0) >= 1, E$1,0) -> Geschiedenis en archeologie | AX11: =IF(IFERROR(SEARCH(F$1, $D11),0) >= 1, F$1,0) -> 0 | AY11: =IF(IFERROR(SEARCH(G$1, $D11),0) >= 1, G$1,0) -> 0 | AZ11: =IF(IFERROR(SEARCH(H$1, $D11),0) >= 1, H$1,0) -> 0 | BA11: =IF(IFERROR(SEARCH(I$1, $D11),0) >= 1, I$1,0) -> 0 | BB11: =IF(IFERROR(SEARCH(J$1, $D11),0) >= 1, J$1,0) -> 0 | BC11: =IF(IFERROR(SEARCH(K$1, $D11),0) >= 1, K$1,0) -> Toegepaste kunst en design | BD11: =IF(L11 = true, BD$1, 0) -> Shop | BE11: =IF(M11 = true, BE$1, 0) -> 0 | BF11: =IF(N11 = true, BF$1, 0) -> 0 | BG11: =IF(O11 = true, BG$1, 0) -> 0 | BH11: =IFERROR(__xludf.DUMMYFUNCTION("""COMPUTED_VALUE"""),"Museum PARCUM, Abdij van Park Leuven") -> Museum PARCUM, Abdij van Park Leuven | BI11: =IFERROR(__xludf.DUMMYFUNCTION("""COMPUTED_VALUE"""),12.0) -> 12 | BJ11: =IFERROR(__xludf.DUMMYFUNCTION("""COMPUTED_VALUE"""),FALSE) -> FALSE | BK11: =IFERROR(__xludf.DUMMYFUNCTION("""COMPUTED_VALUE"""),TRUE) -> TRUE | BL11: =IFERROR(__xludf.DUMMYFUNCTION("""COMPUTED_VALUE"""),12.0) -> 12 | BM11: =IFERROR(__xludf.DUMMYFUNCTION("""COMPUTED_VALUE"""),0.0) -> 0 | BN11: =IFERROR(__xludf.DUMMYFUNCTION("""COMPUTED_VALUE"""),1.0) -> 1 | BO11: =IFERROR(__xludf.DUMMYFUNCTION("""COMPUTED_VALUE"""),0.0) -> 0 | BP11: =IFERROR(__xludf.DUMMYFUNCTION("""COMPUTED_VALUE"""),0.0) -> 0 | BQ11: =IFERROR(__xludf.DUMMYFUNCTION("""COMPUTED_VALUE"""),0.0) -> 0 | BR11: =IFERROR(__xludf.DUMMYFUNCTION("""COMPUTED_VALUE"""),0.0) -> 0 | BS11: =IFERROR(__xludf.DUMMYFUNCTION("""COMPUTED_VALUE"""),1.0) -> 1 | BT11: =IFERROR(__xludf.DUMMYFUNCTION("""COMPUTED_VALUE"""),0.0) -> 0 | BU11: =IFERROR(__xludf.DUMMYFUNCTION("""COMPUTED_VALUE"""),2.0) -> 2 | BV11: =IFERROR(__xludf.DUMMYFUNCTION("""COMPUTED_VALUE"""),0.0) -> 0 | BW11: =IFERROR(__xludf.DUMMYFUNCTION("""COMPUTED_VALUE"""),1.0) -> 1 | BX11: =IFERROR(__xludf.DUMMYFUNCTION("""COMPUTED_VALUE"""),1.0) -> 1 | BY11: =IFERROR(__xludf.DUMMYFUNCTION("""COMPUTED_VALUE"""),1.0) -> 1 | BZ11: =IFERROR(__xludf.DUMMYFUNCTION("""COMPUTED_VALUE"""),1.0) -> 1 | CA11: =IFERROR(__xludf.DUMMYFUNCTION("""COMPUTED_VALUE"""),4.0) -> 4 | CB11: =IFERROR(__xludf.DUMMYFUNCTION("""COMPUTED_VALUE"""),6.0) -> 6 | CC11: =IFERROR(__xludf.DUMMYFUNCTION("""COMPUTED_VALUE"""),3.75) -> 3.75 | CD11: =IFERROR(__xludf.DUMMYFUNCTION("""COMPUTED_VALUE"""),"good") -> good | CE11: Museum PARCUM, Abdij van Park Leuven | CF11: 12 | CG11: FALSE | CH11: TRUE | CI11: 12 | CJ11: 0 | CK11: 1 | CL11: 0 | CM11: 0 | CN11: 0 | CO11: 0 | CP11: 1 | CQ11: 0 | CR11: 2 | CS11: 0 | CT11: 1 | CU11: 1 | CV11: 1 | CW11: 1 | CX11: 4 | CY11: 6 | CZ11: 3.75 | DA11: good
A12: Aardbeimuseum | B12: Musée de la Fraise | C12: Namen | D12: Beeldende kunst, Geschiedenis en archeologie, Wetenschap en technologie | E12: =If(IFERROR(SEARCH(E$1, $D12),0) >= 1, true,false) -> TRUE | F12: =If(IFERROR(SEARCH(F$1, $D12),0) >= 1, true,false) -> TRUE | G12: =If(IFERROR(SEARCH(G$1, $D12),0) >= 1, true,false) -> FALSE | H12: =If(IFERROR(SEARCH(H$1, $D12),0) >= 1, true,false) -> FALSE | I12: =If(IFERROR(SEARCH(I$1, $D12),0) >= 1, true,false) -> FALSE | J12: =If(IFERROR(SEARCH(J$1, $D12),0) >= 1, true,false) -> TRUE | K12: =If(IFERROR(SEARCH(K$1, $D12),0) >= 1, true,false) -> FALSE | L12: TRUE | M12: FALSE | N12: FALSE | O12: FALSE | P12: =IF(ISBLANK(A12),B12,A12) -> Aardbeimuseum | Q12: 6 | R12: FALSE | S12: FALSE | U12: =if(OR(C12 = $AO$3, C12 = $AQ$3), 1, 0) -> 0 | V12: =if(OR(AW12 = $AO$4, AW12 = $AQ$4), 1, 0) -> 1 | W12: =if(OR(AX12 = $AO$4, AX12 = $AQ$4), 1, 0) -> 0 | X12: =if(OR(AY12 = $AO$4, AY12 = $AQ$4), 1, 0) -> 0 | Y12: =if(OR(AZ12 = $AO$4, AZ12 = $AQ$4), 1, 0) -> 0 | Z12: =if(OR(BA12 = $AO$4, BA12 = $AQ$4), 1, 0) -> 0 | AA12: =if(OR(BB12 = $AO$4, BB12 = $AQ$4), 1, 0) -> 1 | AB12: =if(OR(BC12 = $AO$4, BC12 = $AQ$4), 1, 0) -> 0 | AC12: =SUM(V12:AB12) -> 2 | AD12: =if($Q12 <= $AN$5, 1, 0) -> 1 | AE12: =if(OR(BD12 = $AO$6, BD12 = $AS$6, BD12 = $AT$6, BD12 = $AU$6), 1, 0) -> 1 | AF12: =if(OR(BE12 = $AO$6, BE12 = $AS$6, BE12 = $AT$6, BE12 = $AU$6), 1, 0) -> 0 | AG12: =if(OR(BF12 = $AO$6, BF12 = $AS$6, BF12 = $AT$6, BF12 = $AU$6), 1, 0) -> 0 | AH12: =if(OR(BG12 = $AO$6, BG12 = $AS$6, BG12 = $AT$6, BG12 = $AU$6), 1, 0) -> 0 | AI12: =SUM(AE12:AH12) -> 1 | AJ12: =SUM(U12,AC12,AD12,AI12) -> 4 | AK12: =(AJ12/$AJ$264)*5 -> 2.5 | AL12: =IFS(4 < AK12 , "excellent", 2.5 < AK12, "good", 1 < AK12 , "subpar", 0 <= AK12, "no match") -> subpar | AW12: =IF(IFERROR(SEARCH(E$1, $D12),0) >= 1, E$1,0) -> Geschiedenis en archeologie | AX12: =IF(IFERROR(SEARCH(F$1, $D12),0) >= 1, F$1,0) -> Wetenschap en technologie | AY12: =IF(IFERROR(SEARCH(G$1, $D12),0) >= 1, G$1,0) -> 0 | AZ12: =IF(IFERROR(SEARCH(H$1, $D12),0) >= 1, H$1,0) -> 0 | BA12: =IF(IFERROR(SEARCH(I$1, $D12),0) >= 1, I$1,0) -> 0 | BB12: =IF(IFERROR(SEARCH(J$1, $D12),0) >= 1, J$1,0) -> Beeldende kunst | BC12: =IF(IFERROR(SEARCH(K$1, $D12),0) >= 1, K$1,0) -> 0 | BD12: =IF(L12 = true, BD$1, 0) -> Shop | BE12: =IF(M12 = true, BE$1, 0) -> 0 | BF12: =IF(N12 = true, BF$1, 0) -> 0 | BG12: =IF(O12 = true, BG$1, 0) -> 0 | BH12: =IFERROR(__xludf.DUMMYFUNCTION("""COMPUTED_VALUE"""),"C-mine") -> C-mine | BI12: =IFERROR(__xludf.DUMMYFUNCTION("""COMPUTED_VALUE"""),14.0) -> 14 | BJ12: =IFERROR(__xludf.DUMMYFUNCTION("""COMPUTED_VALUE"""),FALSE) -> FALSE | BK12: =IFERROR(__xludf.DUMMYFUNCTION("""COMPUTED_VALUE"""),TRUE) -> TRUE | BL12: =IFERROR(__xludf.DUMMYFUNCTION("""COMPUTED_VALUE"""),14.0) -> 14 | BM12: =IFERROR(__xludf.DUMMYFUNCTION("""COMPUTED_VALUE"""),0.0) -> 0 | BN12: =IFERROR(__xludf.DUMMYFUNCTION("""COMPUTED_VALUE"""),1.0) -> 1 | BO12: =IFERROR(__xludf.DUMMYFUNCTION("""COMPUTED_VALUE"""),0.0) -> 0 | BP12: =IFERROR(__xludf.DUMMYFUNCTION("""COMPUTED_VALUE"""),0.0) -> 0 | BQ12: =IFERROR(__xludf.DUMMYFUNCTION("""COMPUTED_VALUE"""),0.0) -> 0 | BR12: =IFERROR(__xludf.DUMMYFUNCTION("""COMPUTED_VALUE"""),0.0) -> 0 | BS12: =IFERROR(__xludf.DUMMYFUNCTION("""COMPUTED_VALUE"""),1.0) -> 1 | BT12: =IFERROR(__xludf.DUMMYFUNCTION("""COMPUTED_VALUE"""),0.0) -> 0 | BU12: =IFERROR(__xludf.DUMMYFUNCTION("""COMPUTED_VALUE"""),2.0) -> 2 | BV12: =IFERROR(__xludf.DUMMYFUNCTION("""COMPUTED_VALUE"""),0.0) -> 0 | BW12: =IFERROR(__xludf.DUMMYFUNCTION("""COMPUTED_VALUE"""),1.0) -> 1 | BX12: =IFERROR(__xludf.DUMMYFUNCTION("""COMPUTED_VALUE"""),1.0) -> 1 | BY12: =IFERROR(__xludf.DUMMYFUNCTION("""COMPUTED_VALUE"""),1.0) -> 1 | BZ12: =IFERROR(__xludf.DUMMYFUNCTION("""COMPUTED_VALUE"""),1.0) -> 1 | CA12: =IFERROR(__xludf.DUMMYFUNCTION("""COMPUTED_VALUE"""),4.0) -> 4 | CB12: =IFERROR(__xludf.DUMMYFUNCTION("""COMPUTED_VALUE"""),6.0) -> 6 | CC12: =IFERROR(__xludf.DUMMYFUNCTION("""COMPUTED_VALUE"""),3.75) -> 3.75 | CD12: =IFERROR(__xludf.DUMMYFUNCTION("""COMPUTED_VALUE"""),"good") -> good | CE12: C-mine | CF12: 14 | CG12: FALSE | CH12: TRUE | CI12: 14 | CJ12: 0 | CK12: 1 | CL12: 0 | CM12: 0 | CN12: 0 | CO12: 0 | CP12: 1 | CQ12: 0 | CR12: 2 | CS12: 0 | CT12: 1 | CU12: 1 | CV12: 1 | CW12: 1 | CX12: 4 | CY12: 6 | CZ12: 3.75 | DA12: good
